Workbook

Sheet Daily_Returns_Q1_Q2
A1: date | B1: IBM | C1: GE | D1: LLY | E1: F | F1: BAC | G1: KR | H1: ITUB | I1: GG | J1: SIRI | K1: ACB | L1: VALE | M1: PFE | N1: CTL | O1: T | P1: ECA | Q1: ABEV | R1: CVS | S1: MRVL | T1: CSCO | U1: MO | V1: BMY | W1: WFC | X1: HBAN
A2: 42373 | B2: -0.00073576783 | C2: 0.00097635896 | D2: 0.014852325 | E2: -0.018057551 | F2: 0 | G2: 0.022343279 | H2: 0.0080064403 | I2: -0.023028694 | J2: -0.010178195 | K2: 0.046628518 | L2: -0.0031695716 | M2: 0.0071729463 | N2: -0.0047904618 | O2: 0.0069626531 | P2: 0.026924677 | Q2: 0.013953702 | R2: 0.0028985402 | S2: -0.032335349 | T2: -0.004554047 | U2: 0.020011016 | V2: 0.019501279 | W2: -0.00037808049 | X2: 0.0018674569
A3: 42374 | B3: -0.0050181489 | C3: -0.016068534 | D3: -0.0063211943 | E3: -0.04547937 | F3: -0.021532692 | G3: -0.00095081813 | H3: -0.0080064403 | I3: 0.018803995 | J3: -0.0051282114 | K3: -0.0068572177 | L3: -0.079249372 | M3: -0.017871606 | N3: -0.010863131 | O3: -0.015440912 | P3: -0.062642821 | Q3: -0.011614466 | R3: -0.012272648 | S3: -0.056744279 | T3: -0.010707585 | U3: 0.010533549 | V3: -0.017712595 | W3: -0.019280894 | X3: -0.015985303
A4: 42375 | B4: -0.017237285 | C4: -0.043235336 | D4: -0.026306118 | E4: -0.031773293 | F4: -0.036736235 | G4: -0.023581448 | H4: -0.031022866 | I4: 0.074228913 | J4: -0.01293684 | K4: -0.061485068 | L4: -0.071204462 | M4: -0.0066656648 | N4: -0.020433895 | O4: -0.016279864 | P4: -0.049699622 | Q4: -0.040529998 | R4: -0.014546449 | S4: 0.0098888225 | T4: -0.023338297 | U4: -0.017560741 | V4: -0.028090046 | W4: -0.028942175 | X4: -0.030801343
A5: 42376 | B5: -0.0093009533 | C5: -0.018112651 | D5: -0.0019673394 | E5: -0.012678446 | F5: -0.019544609 | G5: -0.0065958578 | H5: 0 | I5: -0.018247273 | J5: -0.0078431701 | K5: 0.026475692 | L5: -0.041437241 | M5: -0.012820676 | N5: -0.01037569 | O5: 0.00089493203 | P5: 0.03750436 | Q5: 0.016888144 | R5: -0.0066049324 | S5: 0.011009304 | T5: -0.025105887 | U5: 0.0017185481 | V5: -0.025753825 | W5: -0.016807121 | X5: -0.017751882
A6: 42377 | B6: 0.012081932 | C6: 0.0045590118 | D6: -0.012134911 | E6: 0.018175174 | F6: 0.0072108218 | G6: 0.011696029 | H6: -0.0016597498 | I6: -0.05598164 | J6: 0.002621231 | K6: -0.0023781627 | L6: -0.023347342 | M6: 0.0022555091 | N6: 0.0062383869 | O6: 0.012150093 | P6: -0.035383521 | Q6: -0.016888144 | R6: 0.014431497 | S6: 0.012091977 | T6: 0.019581036 | U6: 0.020731369 | V6: -0.010267866 | W6: 0.010637306 | X6: 0.0049628081
A7: 42380 | B7: -0.0024800061 | C7: 0.0020971429 | D7: 0.0016182848 | E7: 0.0062451351 | F7: 0 | G7: -0.00096939175 | H7: 0.014839499 | I7: -0.031830716 | J7: -0.0078843961 | K7: 0.011834517 | L7: -0.069274159 | M7: -0.0022555091 | N7: -0.030305401 | O7: -0.0014738171 | P7: -0.032295513 | Q7: 0.021661419 | R7: 0.008079413 | S7: 0.019048178 | T7: 0.0031608056 | U7: -0.0013463148 | V7: 0.0072773473 | W7: 0.025038281 | X7: 0.0078895795
A8: 42381 | B8: -0.013102742 | C8: -0.014064913 | D8: -0.013776028 | E8: -0.051907905 | F8: -0.02714505 | G8: -0.050731934 | H8: -0.024856334 | I8: -0.024780006 | J8: -0.021334122 | K8: -0.035932046 | L8: -0.060888313 | M8: -0.020531898 | N8: -0.016372583 | O8: -0.0047309325 | P8: -0.079678164 | Q8: -0.014388724 | R8: -0.016649508 | S8: -0.022660431 | T8: -0.030032287 | U8: -0.027314813 | V8: -0.03464105 | W8: -0.032251308 | X8: -0.043157756
A9: 42382 | B9: 0.013178057 | C9: 0.02862325 | D9: 0.040044868 | E9: -0.00082002704 | F9: 0.0060221095 | G9: -0.0043462163 | H9: 0.021577646 | I9: -0.067649645 | J9: 0.0026917891 | K9: -0.034742945 | L9: 0.089996469 | M9: 0.024074024 | N9: 0.037096513 | O9: 0.016461205 | P9: -0.023981943 | Q9: 0.021506242 | R9: 0.014766659 | S9: 0.0060132701 | T9: 0.0024360331 | U9: 0.0075862854 | V9: 0.035743842 | W9: 0.018133402 | X9: 0.010204209
A10: 42383 | B10: -0.021907051 | C10: -0.019809568 | D10: -0.015875325 | E10: -0.018212367 | F10: -0.035997077 | G10: -0.013932039 | H10: -0.041917311 | I10: -0.010602568 | J10: -0.024490996 | K10: -0.070617595 | L10: -0.029108156 | M10: -0.0096900353 | N10: -0.025435813 | O10: -0.0090789188 | P10: -0.11022666 | Q10: -0.041019038 | R10: -0.017000574 | S10: -0.027965409 | T10: -0.043088645 | U10: -0.017675048 | V10: -0.011560815 | W10: -0.036601707 | X10: -0.02779391
A11: 42384 | B11: -0.014875909 | C11: 0 | D11: 0.02420019 | E11: -0.0016722795 | F11: -0.015331329 | G11: -0.0078248456 | H11: -0.013793309 | I11: -0.047628004 | J11: 0.0082304911 | K11: 0.037238343 | L11: -0.017021672 | M11: -0.0039024092 | N11: -0.0030101765 | O11: 0.015182675 | P11: -0.12083649 | Q11: 0.017094475 | R11: 0.012277843 | S11: -0.042827664 | T11: 0.009690387 | U11: 0.020762004 | V11: 0.00682597 | W11: -0.012573609 | X11: -0.010493316
A12: 42388 | B12: -0.050016425 | C12: -0.017348617 | D12: -0.0073560849 | E12: -0.0041928944 | F12: -0.039389281 | G12: -0.0089427257 | H12: -0.015748342 | I12: 0.0020304072 | J12: -0.016529352 | K12: -0.042673069 | L12: 0 | M12: -0.00097801757 | N12: -0.043121488 | O12: -0.017834029 | P12: 0.067972989 | Q12: -0.024511007 | R12: -0.0099376525 | S12: 0.017857601 | T12: -0.040647339 | U12: -0.020412407 | V12: 0.0053644836 | W12: -0.0070774683 | X12: -0.023480195
A13: 42389 | B13: 0.0085795602 | C13: 0.020852523 | D13: -0.014876523 | E13: 0.0092012871 | F13: -0.024400466 | G13: -0.018667127 | H13: -0.032260902 | I13: -0.0040650425 | J13: 0.016529352 | K13: -0.0054645054 | L13: -0.057410853 | M13: -0.0026126705 | N13: 0.016942049 | O13: 0.01870304 | P13: 0.087487437 | Q13: -0.037931245 | R13: 0.0038176144 | S13: 0.024970063 | T13: 0 | U13: 0.0040115086 | V13: -0.0066308763 | W13: 0.0029203065 | X13: -0.028479496
... A503: 43097 | B503: -0.0040330188 | C503: 0.0051709304 | D503: -0.0069613161 | E503: -0.0071799394 | F503: -0.0094403527 | G503: -0.0072595184 | H503: 0.0053992146 | I503: 0.0047096177 | J503: -0.0037243955 | K503: 0.062182195 | L503: 0.0040966249 | M503: -0.0041327435 | N503: -0.026037005 | O503: -0.0076864132 | P503: 0.00075048627 | Q503: 0.0062111941 | R503: -0.0075576181 | S503: -0.019373304 | T503: -0.0075433032 | U503: 0.0019625324 | V503: -0.0079643116 | W503: -0.010330519 | X503: -0.0122868

Sheet Optimal_Portfolio_Q3-Q8
A1: Optimal Portfolio Calculation--Cells in Yellow Are Not Optimal nor Correct, So You Need to Compute By Yourself
A3: COVARIANCE MATRIX | B3: IBM | C3: GE | D3: LLY | E3: F | F3: BAC | G3: KR | H3: ITUB | I3: GG | J3: SIRI | K3: ACB | L3: VALE | M3: PFE | N3: CTL | O3: T | P3: ECA | Q3: ABEV | R3: CVS | S3: MRVL | T3: CSCO | U3: MO | V3: BMY | W3: WFC | X3: HBAN
A4: IBM | B4: 0.000127 | C4: =_xlfn.COVARIANCE.S(Daily_Returns_Q1_Q2!B2:B503,Daily_Returns_Q1_Q2!C2:C503) | D4: 1.9e-05 | E4: 5.5e-05 | F4: 7e-05 | G4: 5e-06 | H4: 7.3e-05 | I4: 1.1e-05 | J4: 3.2e-05 | K4: 3.1e-05 | L4: 0.000104 | M4: 2.2e-05 | N4: 3.5e-05 | O4: 2.4e-05 | P4: 8.4e-05 | Q4: 4.6e-05 | R4: 2e-05 | S4: 5.8e-05 | T4: 4.7e-05 | U4: 1.6e-05 | V4: 1.4e-05 | W4: 5e-05 | X4: 6.9e-05
A5: GE | B5: =C4 | C5: 0.000139 | D5: 2.2e-05 | E5: 7e-05 | F5: 8.7e-05 | G5: 1.5e-05 | H5: 8.4e-05 | I5: -2.6e-05 | J5: 3.9e-05 | K5: -1.4e-05 | L5: 0.000137 | M5: 2.9e-05 | N5: 5.1e-05 | O5: 3.9e-05 | P5: 8.5e-05 | Q5: 4.8e-05 | R5: 3.9e-05 | S5: 5.1e-05 | T5: 4.1e-05 | U5: 2e-05 | V5: 3.2e-05 | W5: 6.2e-05 | X5: 7.6e-05
A6: LLY | B6: 1.9e-05 | C6: 2.2e-05 | D6: 0.000163 | E6: 3e-05 | F6: 4.1e-05 | G6: 2e-05 | H6: 3e-05 | I6: 1.1e-05 | J6: 2.6e-05 | K6: 1.1e-05 | L6: 5.1e-05 | M6: 5.3e-05 | N6: 3.3e-05 | O6: 2e-05 | P6: 1.9e-05 | Q6: 2.7e-05 | R6: 2.9e-05 | S6: 2.5e-05 | T6: 3.4e-05 | U6: 1.4e-05 | V6: 7.1e-05 | W6: 3.1e-05 | X6: 3e-05
A7: F | B7: 5.5e-05 | C7: 7e-05 | D7: 3e-05 | E7: 0.000204 | F7: 0.000127 | G7: 3.5e-05 | H7: 9.2e-05 | I7: -4e-06 | J7: 7.1e-05 | K7: 2.6e-05 | L7: 0.000193 | M7: 3.5e-05 | N7: 7.5e-05 | O7: 3.2e-05 | P7: 0.000152 | Q7: 5.1e-05 | R7: 3.3e-05 | S7: 8.9e-05 | T7: 6.5e-05 | U7: 1.1e-05 | V7: 5.5e-05 | W7: 9.4e-05 | X7: 0.000115
A8: BAC | B8: 7e-05 | C8: 8.7e-05 | D8: 4.1e-05 | E8: 0.000127 | F8: 0.000296 | G8: 5.8e-05 | H8: 0.000129 | I8: -0.000121 | J8: 8.5e-05 | K8: 4.4e-05 | L8: 0.000257 | M8: 5.3e-05 | N8: 7.4e-05 | O8: 1.9e-05 | P8: 0.000214 | Q8: 7.2e-05 | R8: 4.5e-05 | S8: 0.000103 | T8: 6.9e-05 | U8: -9e-06 | V8: 4e-05 | W8: 0.000175 | X8: 0.000233
A9: KR | B9: 5e-06 | C9: 1.5e-05 | D9: 2e-05 | E9: 3.5e-05 | F9: 5.8e-05 | G9: 0.000366 | H9: -1.6e-05 | I9: -2.4e-05 | J9: 3e-05 | K9: 4.2e-05 | L9: 1.9e-05 | M9: 2.1e-05 | N9: 6.5e-05 | O9: 1.5e-05 | P9: 4.9e-05 | Q9: 1.6e-05 | R9: 6.3e-05 | S9: 3.8e-05 | T9: 2.6e-05 | U9: 9e-06 | V9: 2.8e-05 | W9: 4.2e-05 | X9: 4.3e-05
A10: ITUB | B10: 7.3e-05 | C10: 8.4e-05 | D10: 3e-05 | E10: 9.2e-05 | F10: 0.000129 | G10: -1.6e-05 | H10: 0.000701 | I10: 0.00013 | J10: 7e-05 | K10: 9.9e-05 | L10: 0.000529 | M10: 1.2e-05 | N10: 0.000106 | O10: 5.2e-05 | P10: 0.000294 | Q10: 0.00034 | R10: 3.8e-05 | S10: 0.000127 | T10: 0.000113 | U10: 5e-05 | V10: 6.3e-05 | W10: 6.8e-05 | X10: 0.000106
A11: GG | B11: 1.1e-05 | C11: -2.6e-05 | D11: 1.1e-05 | E11: -4e-06 | F11: -0.000121 | G11: -2.4e-05 | H11: 0.00013 | I11: 0.000642 | J11: -3e-06 | K11: -5.8e-05 | L11: 0.000235 | M11: -1.7e-05 | N11: 5.4e-05 | O11: 3e-05 | P11: 0.000148 | Q11: 9e-05 | R11: -1.5e-05 | S11: 9e-06 | T11: 1.4e-05 | U11: 1.2e-05 | V11: 1.6e-05 | W11: -7.9e-05 | X11: -0.00011
A12: SIRI | B12: 3.2e-05 | C12: 3.9e-05 | D12: 2.6e-05 | E12: 7.1e-05 | F12: 8.5e-05 | G12: 3e-05 | H12: 7e-05 | I12: -3e-06 | J12: 0.000169 | K12: 5.2e-05 | L12: 0.000121 | M12: 2.1e-05 | N12: 6.1e-05 | O12: 2.9e-05 | P12: 9.4e-05 | Q12: 4.8e-05 | R12: 2e-05 | S12: 7.6e-05 | T12: 4.7e-05 | U12: 1.9e-05 | V12: 1.8e-05 | W12: 5.7e-05 | X12: 6.3e-05
A13: ACB | B13: 3.1e-05 | C13: -1.4e-05 | D13: 1.1e-05 | E13: 2.6e-05 | F13: 4.4e-05 | G13: 4.2e-05 | H13: 9.9e-05 | I13: -5.8e-05 | J13: 5.2e-05 | K13: 0.002376 | L13: 0.000164 | M13: 2e-05 | N13: 2.3e-05 | O13: -6e-06 | P13: 0.000149 | Q13: 0.000103 | R13: 3.6e-05 | S13: 6.6e-05 | T13: 4.5e-05 | U13: 1.9e-05 | V13: -1.8e-05 | W13: 2.5e-05 | X13: 5.7e-05
A14: VALE | B14: 0.000104 | C14: 0.000137 | D14: 5.1e-05 | E14: 0.000193 | F14: 0.000257 | G14: 1.9e-05 | H14: 0.000529 | I14: 0.000235 | J14: 0.000121 | K14: 0.000164 | L14: 0.001406 | M14: 3.9e-05 | N14: 0.000184 | O14: 5.8e-05 | P14: 0.000536 | Q14: 0.000326 | R14: 4.6e-05 | S14: 0.000174 | T14: 0.000129 | U14: 1.8e-05 | V14: 8.5e-05 | W14: 0.000159 | X14: 0.000218
A15: PFE | B15: 2.2e-05 | C15: 2.9e-05 | D15: 5.3e-05 | E15: 3.5e-05 | F15: 5.3e-05 | G15: 2.1e-05 | H15: 1.2e-05 | I15: -1.7e-05 | J15: 2.1e-05 | K15: 2e-05 | L15: 3.9e-05 | M15: 9.5e-05 | N15: 2.4e-05 | O15: 1.4e-05 | P15: 1e-05 | Q15: 2.1e-05 | R15: 3.9e-05 | S15: 2.8e-05 | T15: 2.8e-05 | U15: 4e-06 | V15: 5.6e-05 | W15: 4.6e-05 | X15: 5.2e-05
A16: CTL | B16: 3.5e-05 | C16: 5.1e-05 | D16: 3.3e-05 | E16: 7.5e-05 | F16: 7.4e-05 | G16: 6.5e-05 | H16: 0.000106 | I16: 5.4e-05 | J16: 6.1e-05 | K16: 2.3e-05 | L16: 0.000184 | M16: 2.4e-05 | N16: 0.000455 | O16: 5.9e-05 | P16: 0.000162 | Q16: 8.2e-05 | R16: 3e-05 | S16: 5.8e-05 | T16: 8.2e-05 | U16: 3.4e-05 | V16: 4e-05 | W16: 5.5e-05 | X16: 5.1e-05
A17: T | B17: 2.4e-05 | C17: 3.9e-05 | D17: 2e-05 | E17: 3.2e-05 | F17: 1.9e-05 | G17: 1.5e-05 | H17: 5.2e-05 | I17: 3e-05 | J17: 2.9e-05 | K17: -6e-06 | L17: 5.8e-05 | M17: 1.4e-05 | N17: 5.9e-05 | O17: 0.000105 | P17: 4.5e-05 | Q17: 3.7e-05 | R17: 1.9e-05 | S17: 1.3e-05 | T17: 2.4e-05 | U17: 3.4e-05 | V17: 1.1e-05 | W17: 2e-05 | X17: 2e-05
... A26: HBAN | B26: 6.9e-05 | C26: 7.6e-05 | D26: 3e-05 | E26: 0.000115 | F26: 0.000233 | G26: 4.3e-05 | H26: 0.000106 | I26: -0.00011 | J26: 6.3e-05 | K26: 5.7e-05 | L26: 0.000218 | M26: 5.2e-05 | N26: 5.1e-05 | O26: 2e-05 | P26: 0.000163 | Q26: 5.4e-05 | R26: 4.7e-05 | S26: 9.5e-05 | T26: 5.4e-05 | U26: -1e-05 | V26: 3.6e-05 | W26: 0.000165 | X26: 0.000295
B30: IBM | C30: GE | D30: LLY | E30: F | F30: BAC | G30: KR | H30: ITUB | I30: GG | J30: SIRI | K30: ACB | L30: VALE | M30: PFE | N30: CTL | O30: T | P30: ECA | Q30: ABEV | R30: CVS | S30: MRVL | T30: CSCO | U30: MO | V30: BMY | W30: WFC | X30: HBAN
A31: Average_Daily_Returns | B31: 0.000241 | C31: =AVERAGE(Daily_Returns_Q1_Q2!C2:C503) | D31: 3.8e-05 | E31: -0.000223 | F31: 0.001167 | G31: -0.000807 | H31: 0.001658 | I31: 0.000147 | J31: 0.000608 | K31: 0.005781 | L31: 0.002696 | M31: 0.00025 | N31: -0.000815 | O31: 0.000247 | P31: 0.001902 | Q31: 0.000825 | R31: -0.000569 | S31: 0.001777 | T31: 0.00074 | U31: 0.000435 | V31: -0.000179 | W31: 0.000273 | X31: 0.000614
B33: IBM | C33: GE | D33: LLY | E33: F | F33: BAC | G33: KR | H33: ITUB | I33: GG | J33: SIRI | K33: ACB | L33: VALE | M33: PFE | N33: CTL | O33: T | P33: ECA | Q33: ABEV | R33: CVS | S33: MRVL | T33: CSCO | U33: MO | V33: BMY | W33: WFC | X33: HBAN
A34: Percentage_Portfolio_Allocation_1 | B34: 0.089023557 | C34: -0.020725238 | D34: 0.02362748 | E34: -0.043433669 | F34: 0.058478954 | G34: 0.022396137 | H34: -0.024999679 | I34: 0.070482263 | J34: 0.065180425 | K34: 0.019914185 | L34: -0.02437887 | M34: 0.17286329 | N34: -0.035327997 | O34: 0.14679367 | P34: 0.0043730752 | Q34: 0.022322851 | R34: 0.032272739 | S34: 0.03501936 | T34: 0.061743817 | U34: 0.23273382 | V34: 0.044561079 | W34: 0.030124678 | X34: 0.016954067
A38: Portfolio_Expected_Returns | B38: =SUMPRODUCT(B31:X31,B34:X34)
A39: Total_Wealth | B39: =SUM(B34:X34)
A40: Portfolio_Variance | B40: =SUMPRODUCT(B34:X34,MMULT(B34:X34,B4:X26))
A42: Q4: Expected return of x1 (= B38 above) — equal to 0.05%, the constraint binds
A44: Q5: Percentage_Portfolio_Allocation_2 (x2, target mean >= 0.0008)
B45: 0.084928244 | C45: -0.089604703 | D45: 0.012974617 | E45: -0.065535851 | F45: 0.10546914 | G45: 0.0094669131 | H45: -0.021141524 | I45: 0.069525783 | J45: 0.067590355 | K45: 0.028724255 | L45: -0.01578853 | M45: 0.19202727 | N45: -0.050503554 | O45: 0.17399892 | P45: 0.006206528 | Q45: 0.013683083 | R45: 0.021684799 | S45: 0.051551779 | T45: 0.083276946 | U45: 0.25651009 | V45: 0.044236638 | W45: 0.012520617 | X45: 0.0081981893
A47: Portfolio_Expected_Returns_2 | B47: =SUMPRODUCT(B31:X31,B45:X45)
A48: Total_Wealth_2 | B48: =SUM(B45:X45)
A49: Portfolio_Variance_2 [Q5 answer] | B49: =SUMPRODUCT(B45:X45,MMULT(B45:X45,B4:X26))
A52: Q6: Percentage_Portfolio_Allocation_3 (x3, target mean >= 0.001)
B53: 0.082198035 | C53: -0.13552435 | D53: 0.0058727092 | E53: -0.080270638 | F53: 0.13679592 | G53: 0.00084743045 | H53: -0.018569421 | I53: 0.068888129 | J53: 0.069196974 | K53: 0.034597635 | L53: -0.010061638 | M53: 0.20480326 | N53: -0.060620592 | O53: 0.19213574 | P53: 0.0074288299 | Q53: 0.0079232377 | R53: 0.014626172 | S53: 0.062573393 | T53: 0.097632365 | U53: 0.27236094 | V53: 0.044020344 | W53: 0.00078457554 | X53: 0.0023609374
A55: Portfolio_Expected_Returns_3 | B55: =SUMPRODUCT(B31:X31,B53:X53)
A56: Total_Wealth_3 | B56: =SUM(B53:X53)
A57: Portfolio_Variance_3 | B57: =SUMPRODUCT(B53:X53,MMULT(B53:X53,B4:X26))
A59: Two-fund theorem check: phi = (0.08%-0.1%)/(0.08%-0.05%); z = phi*x1 + (1-phi)*x2
A60: phi | B60: =(0.0008-0.001)/(0.0008-0.0005)
A61: z (=phi*x1+(1-phi)*x2) | B61: {=$B$60*B34:X34+(1-$B$60)*B45:X45}
A62: x3 | B62: =B53 | C62: =C53 | D62: =D53 | E62: =E53 | F62: =F53 | G62: =G53 | H62: =H53 | I62: =I53 | ... X62: =X53
A63: Max |z - x3| (should be ~0 -> two-fund theorem holds, z = x3) | B63: {=MAX(ABS(B61:X61-B62:X62))}

Sheet Sharpe_Ratio_Q9-Q10
A1: Sharpe Portfolio Calculation--Cells in Yellow Are Not Optimal nor Correct, So You Need to Compute By Yourself
A3: COVARIANCE MATRIX | B3: IBM | C3: GE | D3: LLY | E3: F | F3: BAC | G3: KR | H3: ITUB | I3: GG | J3: SIRI | K3: ACB | L3: VALE | M3: PFE | N3: CTL | O3: T | P3: ECA | Q3: ABEV | R3: CVS | S3: MRVL | T3: CSCO | U3: MO | V3: BMY | W3: WFC | X3: HBAN
A4: IBM | B4: 0.000127 | C4: =_xlfn.COVARIANCE.S(Daily_Returns_Q1_Q2!B2:B503,Daily_Returns_Q1_Q2!C2:C503) | D4: 1.9e-05 | E4: 5.5e-05 | F4: 7e-05 | G4: 5e-06 | H4: 7.3e-05 | I4: 1.1e-05 | J4: 3.2e-05 | K4: 3.1e-05 | L4: 0.000104 | M4: 2.2e-05 | N4: 3.5e-05 | O4: 2.4e-05 | P4: 8.4e-05 | Q4: 4.6e-05 | R4: 2e-05 | S4: 5.8e-05 | T4: 4.7e-05 | U4: 1.6e-05 | V4: 1.4e-05 | W4: 5e-05 | X4: 6.9e-05
A5: GE | B5: =C4 | C5: 0.000139 | D5: 2.2e-05 | E5: 7e-05 | F5: 8.7e-05 | G5: 1.5e-05 | H5: 8.4e-05 | I5: -2.6e-05 | J5: 3.9e-05 | K5: -1.4e-05 | L5: 0.000137 | M5: 2.9e-05 | N5: 5.1e-05 | O5: 3.9e-05 | P5: 8.5e-05 | Q5: 4.8e-05 | R5: 3.9e-05 | S5: 5.1e-05 | T5: 4.1e-05 | U5: 2e-05 | V5: 3.2e-05 | W5: 6.2e-05 | X5: 7.6e-05
A6: LLY | B6: 1.9e-05 | C6: 2.2e-05 | D6: 0.000163 | E6: 3e-05 | F6: 4.1e-05 | G6: 2e-05 | H6: 3e-05 | I6: 1.1e-05 | J6: 2.6e-05 | K6: 1.1e-05 | L6: 5.1e-05 | M6: 5.3e-05 | N6: 3.3e-05 | O6: 2e-05 | P6: 1.9e-05 | Q6: 2.7e-05 | R6: 2.9e-05 | S6: 2.5e-05 | T6: 3.4e-05 | U6: 1.4e-05 | V6: 7.1e-05 | W6: 3.1e-05 | X6: 3e-05
A7: F | B7: 5.5e-05 | C7: 7e-05 | D7: 3e-05 | E7: 0.000204 | F7: 0.000127 | G7: 3.5e-05 | H7: 9.2e-05 | I7: -4e-06 | J7: 7.1e-05 | K7: 2.6e-05 | L7: 0.000193 | M7: 3.5e-05 | N7: 7.5e-05 | O7: 3.2e-05 | P7: 0.000152 | Q7: 5.1e-05 | R7: 3.3e-05 | S7: 8.9e-05 | T7: 6.5e-05 | U7: 1.1e-05 | V7: 5.5e-05 | W7: 9.4e-05 | X7: 0.000115
A8: BAC | B8: 7e-05 | C8: 8.7e-05 | D8: 4.1e-05 | E8: 0.000127 | F8: 0.000296 | G8: 5.8e-05 | H8: 0.000129 | I8: -0.000121 | J8: 8.5e-05 | K8: 4.4e-05 | L8: 0.000257 | M8: 5.3e-05 | N8: 7.4e-05 | O8: 1.9e-05 | P8: 0.000214 | Q8: 7.2e-05 | R8: 4.5e-05 | S8: 0.000103 | T8: 6.9e-05 | U8: -9e-06 | V8: 4e-05 | W8: 0.000175 | X8: 0.000233
A9: KR | B9: 5e-06 | C9: 1.5e-05 | D9: 2e-05 | E9: 3.5e-05 | F9: 5.8e-05 | G9: 0.000366 | H9: -1.6e-05 | I9: -2.4e-05 | J9: 3e-05 | K9: 4.2e-05 | L9: 1.9e-05 | M9: 2.1e-05 | N9: 6.5e-05 | O9: 1.5e-05 | P9: 4.9e-05 | Q9: 1.6e-05 | R9: 6.3e-05 | S9: 3.8e-05 | T9: 2.6e-05 | U9: 9e-06 | V9: 2.8e-05 | W9: 4.2e-05 | X9: 4.3e-05
A10: ITUB | B10: 7.3e-05 | C10: 8.4e-05 | D10: 3e-05 | E10: 9.2e-05 | F10: 0.000129 | G10: -1.6e-05 | H10: 0.000701 | I10: 0.00013 | J10: 7e-05 | K10: 9.9e-05 | L10: 0.000529 | M10: 1.2e-05 | N10: 0.000106 | O10: 5.2e-05 | P10: 0.000294 | Q10: 0.00034 | R10: 3.8e-05 | S10: 0.000127 | T10: 0.000113 | U10: 5e-05 | V10: 6.3e-05 | W10: 6.8e-05 | X10: 0.000106
A11: GG | B11: 1.1e-05 | C11: -2.6e-05 | D11: 1.1e-05 | E11: -4e-06 | F11: -0.000121 | G11: -2.4e-05 | H11: 0.00013 | I11: 0.000642 | J11: -3e-06 | K11: -5.8e-05 | L11: 0.000235 | M11: -1.7e-05 | N11: 5.4e-05 | O11: 3e-05 | P11: 0.000148 | Q11: 9e-05 | R11: -1.5e-05 | S11: 9e-06 | T11: 1.4e-05 | U11: 1.2e-05 | V11: 1.6e-05 | W11: -7.9e-05 | X11: -0.00011
A12: SIRI | B12: 3.2e-05 | C12: 3.9e-05 | D12: 2.6e-05 | E12: 7.1e-05 | F12: 8.5e-05 | G12: 3e-05 | H12: 7e-05 | I12: -3e-06 | J12: 0.000169 | K12: 5.2e-05 | L12: 0.000121 | M12: 2.1e-05 | N12: 6.1e-05 | O12: 2.9e-05 | P12: 9.4e-05 | Q12: 4.8e-05 | R12: 2e-05 | S12: 7.6e-05 | T12: 4.7e-05 | U12: 1.9e-05 | V12: 1.8e-05 | W12: 5.7e-05 | X12: 6.3e-05
A13: ACB | B13: 3.1e-05 | C13: -1.4e-05 | D13: 1.1e-05 | E13: 2.6e-05 | F13: 4.4e-05 | G13: 4.2e-05 | H13: 9.9e-05 | I13: -5.8e-05 | J13: 5.2e-05 | K13: 0.002376 | L13: 0.000164 | M13: 2e-05 | N13: 2.3e-05 | O13: -6e-06 | P13: 0.000149 | Q13: 0.000103 | R13: 3.6e-05 | S13: 6.6e-05 | T13: 4.5e-05 | U13: 1.9e-05 | V13: -1.8e-05 | W13: 2.5e-05 | X13: 5.7e-05
A14: VALE | B14: 0.000104 | C14: 0.000137 | D14: 5.1e-05 | E14: 0.000193 | F14: 0.000257 | G14: 1.9e-05 | H14: 0.000529 | I14: 0.000235 | J14: 0.000121 | K14: 0.000164 | L14: 0.001406 | M14: 3.9e-05 | N14: 0.000184 | O14: 5.8e-05 | P14: 0.000536 | Q14: 0.000326 | R14: 4.6e-05 | S14: 0.000174 | T14: 0.000129 | U14: 1.8e-05 | V14: 8.5e-05 | W14: 0.000159 | X14: 0.000218
A15: PFE | B15: 2.2e-05 | C15: 2.9e-05 | D15: 5.3e-05 | E15: 3.5e-05 | F15: 5.3e-05 | G15: 2.1e-05 | H15: 1.2e-05 | I15: -1.7e-05 | J15: 2.1e-05 | K15: 2e-05 | L15: 3.9e-05 | M15: 9.5e-05 | N15: 2.4e-05 | O15: 1.4e-05 | P15: 1e-05 | Q15: 2.1e-05 | R15: 3.9e-05 | S15: 2.8e-05 | T15: 2.8e-05 | U15: 4e-06 | V15: 5.6e-05 | W15: 4.6e-05 | X15: 5.2e-05
A16: CTL | B16: 3.5e-05 | C16: 5.1e-05 | D16: 3.3e-05 | E16: 7.5e-05 | F16: 7.4e-05 | G16: 6.5e-05 | H16: 0.000106 | I16: 5.4e-05 | J16: 6.1e-05 | K16: 2.3e-05 | L16: 0.000184 | M16: 2.4e-05 | N16: 0.000455 | O16: 5.9e-05 | P16: 0.000162 | Q16: 8.2e-05 | R16: 3e-05 | S16: 5.8e-05 | T16: 8.2e-05 | U16: 3.4e-05 | V16: 4e-05 | W16: 5.5e-05 | X16: 5.1e-05
A17: T | B17: 2.4e-05 | C17: 3.9e-05 | D17: 2e-05 | E17: 3.2e-05 | F17: 1.9e-05 | G17: 1.5e-05 | H17: 5.2e-05 | I17: 3e-05 | J17: 2.9e-05 | K17: -6e-06 | L17: 5.8e-05 | M17: 1.4e-05 | N17: 5.9e-05 | O17: 0.000105 | P17: 4.5e-05 | Q17: 3.7e-05 | R17: 1.9e-05 | S17: 1.3e-05 | T17: 2.4e-05 | U17: 3.4e-05 | V17: 1.1e-05 | W17: 2e-05 | X17: 2e-05
... A26: HBAN | B26: 6.9e-05 | C26: 7.6e-05 | D26: 3e-05 | E26: 0.000115 | F26: 0.000233 | G26: 4.3e-05 | H26: 0.000106 | I26: -0.00011 | J26: 6.3e-05 | K26: 5.7e-05 | L26: 0.000218 | M26: 5.2e-05 | N26: 5.1e-05 | O26: 2e-05 | P26: 0.000163 | Q26: 5.4e-05 | R26: 4.7e-05 | S26: 9.5e-05 | T26: 5.4e-05 | U26: -1e-05 | V26: 3.6e-05 | W26: 0.000165 | X26: 0.000295
A29: Risk_Free_Rate | B29: 0.0001
B31: IBM | C31: GE | D31: LLY | E31: F | F31: BAC | G31: KR | H31: ITUB | I31: GG | J31: SIRI | K31: ACB | L31: VALE | M31: PFE | N31: CTL | O31: T | P31: ECA | Q31: ABEV | R31: CVS | S31: MRVL | T31: CSCO | U31: MO | V31: BMY | W31: WFC | X31: HBAN
A32: Average_Daily_Returns | B32: 0.000241 | C32: =AVERAGE(Daily_Returns_Q1_Q2!C2:C503) | D32: 3.8e-05 | E32: -0.000223 | F32: 0.001167 | G32: -0.000807 | H32: 0.001658 | I32: 0.000147 | J32: 0.000608 | K32: 0.005781 | L32: 0.002696 | M32: 0.00025 | N32: -0.000815 | O32: 0.000247 | P32: 0.001902 | Q32: 0.000825 | R32: -0.000569 | S32: 0.001777 | T32: 0.00074 | U32: 0.000435 | V32: -0.000179 | W32: 0.000273 | X32: 0.000614
A33: Excess_Returns | B33: {=B32:X32-B29} | C33: -0.0001 | D33: -6.2e-05 | E33: -0.000323 | F33: 0.001067 | G33: -0.000907 | H33: 0.001558 | I33: 4.7e-05 | J33: 0.000508 | K33: 0.005681 | L33: 0.002596 | M33: 0.00015 | N33: -0.000915 | O33: 0.000147 | P33: 0.001802 | Q33: 0.000725 | R33: -0.000669 | S33: 0.001677 | T33: 0.00064 | U33: 0.000335 | V33: -0.000279 | W33: 0.000173 | X33: 0.000514
B35: IBM | C35: GE | D35: LLY | E35: F | F35: BAC | G35: KR | H35: ITUB | I35: GG | J35: SIRI | K35: ACB | L35: VALE | M35: PFE | N35: CTL | O35: T | P35: ECA | Q35: ABEV | R35: CVS | S35: MRVL | T35: CSCO | U35: MO | V35: BMY | W35: WFC | X35: HBAN
A36: Sharpe_Optimal_Solution | B36: -13.205646 | C36: -229.10989 | D36: -34.363742 | E36: -73.236469 | F36: 155.07454 | G36: -43.151135 | H36: 11.871068 | I36: -2.6703812 | J36: 9.0590061 | K36: 29.446545 | L36: 28.272008 | M36: 64.092888 | N36: -50.851954 | O36: 93.707825 | P36: 6.0853016 | Q36: -27.959197 | R36: -35.027744 | S36: 55.364894 | T36: 73.714367 | U36: 81.714131 | V36: -0.54994385 | W36: -54.578755 | X36: -29.615459
A37: Solution_Excess_Returns | B37: =SUMPRODUCT(B33:X33,B36:X36) | C37: = | D37: 1
A38: Solution_Variance | B38: =SUMPRODUCT(B36:X36,MMULT(B36:X36,B4:X26)) | C38: (Minimization)
A39: Potofolio_Allocation( Normalized Sharpe Solution) | B39: -0.9377503 | C39: -16.269395 | D39: -2.4402146 | E39: -5.2006181 | F39: 11.012047 | G39: -3.0642189 | H39: 0.8429802 | I39: -0.18962728 | J39: 0.64329196 | K39: 2.0910379 | L39: 2.0076326 | M39: 4.5513204 | N39: -3.6110642 | O39: 6.6543161 | P39: 0.43212528 | Q39: -1.9854194 | R39: -2.4873662 | S39: 3.9315341 | T39: 5.2345543 | U39: 5.802628 | V39: -0.039052237 | W39: -3.8757093 | X39: -2.1030327
A42: Portfolio_Expected_Returns | B42: =SUMPRODUCT(B39:X39,B32:X32)
A43: Total_Wealth | B43: =SUM(B39:X39)
A44: Portfolio_Variance | B44: =SUMPRODUCT(B39:X39,MMULT(B39:X39,B4:X26))
A45: Sharpe_Ratio | B45: =(B42-B29)/SQRT(B44)
A47: Q9 answer: Sharpe ratio (B45), rounded to 3 decimal places -> 0.260
A49: Q10: Can the Sharpe portfolio (row 39) be realized long-only?
A50: Most negative weight in row 39: | B50: =MIN(B39:X39)
A51: Long-only feasible? [Q10 answer] | B51: =IF(B50>=0,"Yes","No")

Sheet Efficient_Frontier_Q7-Q8
A1: Q7: Efficient frontier via two-fund theorem, z = phi*x1 + (1-phi)*x2, phi in [-2,2]
A2: x1, x2 pulled from Optimal_Portfolio_Q3-Q8!B34:X34 and !B45:X45. mu (mean returns) from Optimal_Portfolio_Q3-Q8!B31:X31. V (covariance) from !B4:X26.
A4: phi | B4: mean_return | C4: variance | E4: IBM | F4: GE | G4: LLY | H4: F | I4: BAC | J4: KR | K4: ITUB | L4: GG | M4: SIRI | N4: ACB | O4: VALE | P4: PFE | Q4: CTL | R4: T | S4: ECA | T4: ABEV | U4: CVS | V4: MRVL | W4: CSCO | X4: MO | Y4: BMY | Z4: WFC | AA4: HBAN
A5: -2 | B5: =SUMPRODUCT(E5:AA5,'Optimal_Portfolio_Q3-Q8'!B31:X31) | C5: =SUMPRODUCT(E5:AA5,MMULT(E5:AA5,'Optimal_Portfolio_Q3-Q8'!B4:X26)) | E5: =$A5*'Optimal_Portfolio_Q3-Q8'!B34+(1-$A5)*'Optimal_Portfolio_Q3-Q8'!B45 | F5: =$A5*'Optimal_Portfolio_Q3-Q8'!C34+(1-$A5)*'Optimal_Portfolio_Q3-Q8'!C45 | G5: =$A5*'Optimal_Portfolio_Q3-Q8'!D34+(1-$A5)*'Optimal_Portfolio_Q3-Q8'!D45 | H5: =$A5*'Optimal_Portfolio_Q3-Q8'!E34+(1-$A5)*'Optimal_Portfolio_Q3-Q8'!E45 | I5: =$A5*'Optimal_Portfolio_Q3-Q8'!F34+(1-$A5)*'Optimal_Portfolio_Q3-Q8'!F45 | J5: =$A5*'Optimal_Portfolio_Q3-Q8'!G34+(1-$A5)*'Optimal_Portfolio_Q3-Q8'!G45 | K5: =$A5*'Optimal_Portfolio_Q3-Q8'!H34+(1-$A5)*'Optimal_Portfolio_Q3-Q8'!H45 | L5: =$A5*'Optimal_Portfolio_Q3-Q8'!I34+(1-$A5)*'Optimal_Portfolio_Q3-Q8'!I45 | ... AA5: =$A5*'Optimal_Portfolio_Q3-Q8'!X34+(1-$A5)*'Optimal_Portfolio_Q3-Q8'!X45
A6: -1.9 | B6: =SUMPRODUCT(E6:AA6,'Optimal_Portfolio_Q3-Q8'!B31:X31) | C6: =SUMPRODUCT(E6:AA6,MMULT(E6:AA6,'Optimal_Portfolio_Q3-Q8'!B4:X26)) | E6: =$A6*'Optimal_Portfolio_Q3-Q8'!B34+(1-$A6)*'Optimal_Portfolio_Q3-Q8'!B45 | F6: =$A6*'Optimal_Portfolio_Q3-Q8'!C34+(1-$A6)*'Optimal_Portfolio_Q3-Q8'!C45 | G6: =$A6*'Optimal_Portfolio_Q3-Q8'!D34+(1-$A6)*'Optimal_Portfolio_Q3-Q8'!D45 | H6: =$A6*'Optimal_Portfolio_Q3-Q8'!E34+(1-$A6)*'Optimal_Portfolio_Q3-Q8'!E45 | I6: =$A6*'Optimal_Portfolio_Q3-Q8'!F34+(1-$A6)*'Optimal_Portfolio_Q3-Q8'!F45 | J6: =$A6*'Optimal_Portfolio_Q3-Q8'!G34+(1-$A6)*'Optimal_Portfolio_Q3-Q8'!G45 | K6: =$A6*'Optimal_Portfolio_Q3-Q8'!H34+(1-$A6)*'Optimal_Portfolio_Q3-Q8'!H45 | L6: =$A6*'Optimal_Portfolio_Q3-Q8'!I34+(1-$A6)*'Optimal_Portfolio_Q3-Q8'!I45 | ... AA6: =$A6*'Optimal_Portfolio_Q3-Q8'!X34+(1-$A6)*'Optimal_Portfolio_Q3-Q8'!X45
A7: -1.8 | B7: =SUMPRODUCT(E7:AA7,'Optimal_Portfolio_Q3-Q8'!B31:X31) | C7: =SUMPRODUCT(E7:AA7,MMULT(E7:AA7,'Optimal_Portfolio_Q3-Q8'!B4:X26)) | E7: =$A7*'Optimal_Portfolio_Q3-Q8'!B34+(1-$A7)*'Optimal_Portfolio_Q3-Q8'!B45 | F7: =$A7*'Optimal_Portfolio_Q3-Q8'!C34+(1-$A7)*'Optimal_Portfolio_Q3-Q8'!C45 | G7: =$A7*'Optimal_Portfolio_Q3-Q8'!D34+(1-$A7)*'Optimal_Portfolio_Q3-Q8'!D45 | H7: =$A7*'Optimal_Portfolio_Q3-Q8'!E34+(1-$A7)*'Optimal_Portfolio_Q3-Q8'!E45 | I7: =$A7*'Optimal_Portfolio_Q3-Q8'!F34+(1-$A7)*'Optimal_Portfolio_Q3-Q8'!F45 | J7: =$A7*'Optimal_Portfolio_Q3-Q8'!G34+(1-$A7)*'Optimal_Portfolio_Q3-Q8'!G45 | K7: =$A7*'Optimal_Portfolio_Q3-Q8'!H34+(1-$A7)*'Optimal_Portfolio_Q3-Q8'!H45 | L7: =$A7*'Optimal_Portfolio_Q3-Q8'!I34+(1-$A7)*'Optimal_Portfolio_Q3-Q8'!I45 | ... AA7: =$A7*'Optimal_Portfolio_Q3-Q8'!X34+(1-$A7)*'Optimal_Portfolio_Q3-Q8'!X45
A8: -1.7 | B8: =SUMPRODUCT(E8:AA8,'Optimal_Portfolio_Q3-Q8'!B31:X31) | C8: =SUMPRODUCT(E8:AA8,MMULT(E8:AA8,'Optimal_Portfolio_Q3-Q8'!B4:X26)) | E8: =$A8*'Optimal_Portfolio_Q3-Q8'!B34+(1-$A8)*'Optimal_Portfolio_Q3-Q8'!B45 | F8: =$A8*'Optimal_Portfolio_Q3-Q8'!C34+(1-$A8)*'Optimal_Portfolio_Q3-Q8'!C45 | G8: =$A8*'Optimal_Portfolio_Q3-Q8'!D34+(1-$A8)*'Optimal_Portfolio_Q3-Q8'!D45 | H8: =$A8*'Optimal_Portfolio_Q3-Q8'!E34+(1-$A8)*'Optimal_Portfolio_Q3-Q8'!E45 | I8: =$A8*'Optimal_Portfolio_Q3-Q8'!F34+(1-$A8)*'Optimal_Portfolio_Q3-Q8'!F45 | J8: =$A8*'Optimal_Portfolio_Q3-Q8'!G34+(1-$A8)*'Optimal_Portfolio_Q3-Q8'!G45 | K8: =$A8*'Optimal_Portfolio_Q3-Q8'!H34+(1-$A8)*'Optimal_Portfolio_Q3-Q8'!H45 | L8: =$A8*'Optimal_Portfolio_Q3-Q8'!I34+(1-$A8)*'Optimal_Portfolio_Q3-Q8'!I45 | ... AA8: =$A8*'Optimal_Portfolio_Q3-Q8'!X34+(1-$A8)*'Optimal_Portfolio_Q3-Q8'!X45
A9: -1.6 | B9: =SUMPRODUCT(E9:AA9,'Optimal_Portfolio_Q3-Q8'!B31:X31) | C9: =SUMPRODUCT(E9:AA9,MMULT(E9:AA9,'Optimal_Portfolio_Q3-Q8'!B4:X26)) | E9: =$A9*'Optimal_Portfolio_Q3-Q8'!B34+(1-$A9)*'Optimal_Portfolio_Q3-Q8'!B45 | F9: =$A9*'Optimal_Portfolio_Q3-Q8'!C34+(1-$A9)*'Optimal_Portfolio_Q3-Q8'!C45 | G9: =$A9*'Optimal_Portfolio_Q3-Q8'!D34+(1-$A9)*'Optimal_Portfolio_Q3-Q8'!D45 | H9: =$A9*'Optimal_Portfolio_Q3-Q8'!E34+(1-$A9)*'Optimal_Portfolio_Q3-Q8'!E45 | I9: =$A9*'Optimal_Portfolio_Q3-Q8'!F34+(1-$A9)*'Optimal_Portfolio_Q3-Q8'!F45 | J9: =$A9*'Optimal_Portfolio_Q3-Q8'!G34+(1-$A9)*'Optimal_Portfolio_Q3-Q8'!G45 | K9: =$A9*'Optimal_Portfolio_Q3-Q8'!H34+(1-$A9)*'Optimal_Portfolio_Q3-Q8'!H45 | L9: =$A9*'Optimal_Portfolio_Q3-Q8'!I34+(1-$A9)*'Optimal_Portfolio_Q3-Q8'!I45 | ... AA9: =$A9*'Optimal_Portfolio_Q3-Q8'!X34+(1-$A9)*'Optimal_Portfolio_Q3-Q8'!X45
A10: -1.5 | B10: =SUMPRODUCT(E10:AA10,'Optimal_Portfolio_Q3-Q8'!B31:X31) | C10: =SUMPRODUCT(E10:AA10,MMULT(E10:AA10,'Optimal_Portfolio_Q3-Q8'!B4:X26)) | E10: =$A10*'Optimal_Portfolio_Q3-Q8'!B34+(1-$A10)*'Optimal_Portfolio_Q3-Q8'!B45 | F10: =$A10*'Optimal_Portfolio_Q3-Q8'!C34+(1-$A10)*'Optimal_Portfolio_Q3-Q8'!C45 | G10: =$A10*'Optimal_Portfolio_Q3-Q8'!D34+(1-$A10)*'Optimal_Portfolio_Q3-Q8'!D45 | H10: =$A10*'Optimal_Portfolio_Q3-Q8'!E34+(1-$A10)*'Optimal_Portfolio_Q3-Q8'!E45 | I10: =$A10*'Optimal_Portfolio_Q3-Q8'!F34+(1-$A10)*'Optimal_Portfolio_Q3-Q8'!F45 | J10: =$A10*'Optimal_Portfolio_Q3-Q8'!G34+(1-$A10)*'Optimal_Portfolio_Q3-Q8'!G45 | K10: =$A10*'Optimal_Portfolio_Q3-Q8'!H34+(1-$A10)*'Optimal_Portfolio_Q3-Q8'!H45 | L10: =$A10*'Optimal_Portfolio_Q3-Q8'!I34+(1-$A10)*'Optimal_Portfolio_Q3-Q8'!I45 | ... AA10: =$A10*'Optimal_Portfolio_Q3-Q8'!X34+(1-$A10)*'Optimal_Portfolio_Q3-Q8'!X45
A11: -1.4 | B11: =SUMPRODUCT(E11:AA11,'Optimal_Portfolio_Q3-Q8'!B31:X31) | C11: =SUMPRODUCT(E11:AA11,MMULT(E11:AA11,'Optimal_Portfolio_Q3-Q8'!B4:X26)) | E11: =$A11*'Optimal_Portfolio_Q3-Q8'!B34+(1-$A11)*'Optimal_Portfolio_Q3-Q8'!B45 | F11: =$A11*'Optimal_Portfolio_Q3-Q8'!C34+(1-$A11)*'Optimal_Portfolio_Q3-Q8'!C45 | G11: =$A11*'Optimal_Portfolio_Q3-Q8'!D34+(1-$A11)*'Optimal_Portfolio_Q3-Q8'!D45 | H11: =$A11*'Optimal_Portfolio_Q3-Q8'!E34+(1-$A11)*'Optimal_Portfolio_Q3-Q8'!E45 | I11: =$A11*'Optimal_Portfolio_Q3-Q8'!F34+(1-$A11)*'Optimal_Portfolio_Q3-Q8'!F45 | J11: =$A11*'Optimal_Portfolio_Q3-Q8'!G34+(1-$A11)*'Optimal_Portfolio_Q3-Q8'!G45 | K11: =$A11*'Optimal_Portfolio_Q3-Q8'!H34+(1-$A11)*'Optimal_Portfolio_Q3-Q8'!H45 | L11: =$A11*'Optimal_Portfolio_Q3-Q8'!I34+(1-$A11)*'Optimal_Portfolio_Q3-Q8'!I45 | ... AA11: =$A11*'Optimal_Portfolio_Q3-Q8'!X34+(1-$A11)*'Optimal_Portfolio_Q3-Q8'!X45
A12: -1.3 | B12: =SUMPRODUCT(E12:AA12,'Optimal_Portfolio_Q3-Q8'!B31:X31) | C12: =SUMPRODUCT(E12:AA12,MMULT(E12:AA12,'Optimal_Portfolio_Q3-Q8'!B4:X26)) | E12: =$A12*'Optimal_Portfolio_Q3-Q8'!B34+(1-$A12)*'Optimal_Portfolio_Q3-Q8'!B45 | F12: =$A12*'Optimal_Portfolio_Q3-Q8'!C34+(1-$A12)*'Optimal_Portfolio_Q3-Q8'!C45 | G12: =$A12*'Optimal_Portfolio_Q3-Q8'!D34+(1-$A12)*'Optimal_Portfolio_Q3-Q8'!D45 | H12: =$A12*'Optimal_Portfolio_Q3-Q8'!E34+(1-$A12)*'Optimal_Portfolio_Q3-Q8'!E45 | I12: =$A12*'Optimal_Portfolio_Q3-Q8'!F34+(1-$A12)*'Optimal_Portfolio_Q3-Q8'!F45 | J12: =$A12*'Optimal_Portfolio_Q3-Q8'!G34+(1-$A12)*'Optimal_Portfolio_Q3-Q8'!G45 | K12: =$A12*'Optimal_Portfolio_Q3-Q8'!H34+(1-$A12)*'Optimal_Portfolio_Q3-Q8'!H45 | L12: =$A12*'Optimal_Portfolio_Q3-Q8'!I34+(1-$A12)*'Optimal_Portfolio_Q3-Q8'!I45 | ... AA12: =$A12*'Optimal_Portfolio_Q3-Q8'!X34+(1-$A12)*'Optimal_Portfolio_Q3-Q8'!X45
A13: -1.2 | B13: =SUMPRODUCT(E13:AA13,'Optimal_Portfolio_Q3-Q8'!B31:X31) | C13: =SUMPRODUCT(E13:AA13,MMULT(E13:AA13,'Optimal_Portfolio_Q3-Q8'!B4:X26)) | E13: =$A13*'Optimal_Portfolio_Q3-Q8'!B34+(1-$A13)*'Optimal_Portfolio_Q3-Q8'!B45 | F13: =$A13*'Optimal_Portfolio_Q3-Q8'!C34+(1-$A13)*'Optimal_Portfolio_Q3-Q8'!C45 | G13: =$A13*'Optimal_Portfolio_Q3-Q8'!D34+(1-$A13)*'Optimal_Portfolio_Q3-Q8'!D45 | H13: =$A13*'Optimal_Portfolio_Q3-Q8'!E34+(1-$A13)*'Optimal_Portfolio_Q3-Q8'!E45 | I13: =$A13*'Optimal_Portfolio_Q3-Q8'!F34+(1-$A13)*'Optimal_Portfolio_Q3-Q8'!F45 | J13: =$A13*'Optimal_Portfolio_Q3-Q8'!G34+(1-$A13)*'Optimal_Portfolio_Q3-Q8'!G45 | K13: =$A13*'Optimal_Portfolio_Q3-Q8'!H34+(1-$A13)*'Optimal_Portfolio_Q3-Q8'!H45 | L13: =$A13*'Optimal_Portfolio_Q3-Q8'!I34+(1-$A13)*'Optimal_Portfolio_Q3-Q8'!I45 | ... AA13: =$A13*'Optimal_Portfolio_Q3-Q8'!X34+(1-$A13)*'Optimal_Portfolio_Q3-Q8'!X45
A14: -1.1 | B14: =SUMPRODUCT(E14:AA14,'Optimal_Portfolio_Q3-Q8'!B31:X31) | C14: =SUMPRODUCT(E14:AA14,MMULT(E14:AA14,'Optimal_Portfolio_Q3-Q8'!B4:X26)) | E14: =$A14*'Optimal_Portfolio_Q3-Q8'!B34+(1-$A14)*'Optimal_Portfolio_Q3-Q8'!B45 | F14: =$A14*'Optimal_Portfolio_Q3-Q8'!C34+(1-$A14)*'Optimal_Portfolio_Q3-Q8'!C45 | G14: =$A14*'Optimal_Portfolio_Q3-Q8'!D34+(1-$A14)*'Optimal_Portfolio_Q3-Q8'!D45 | H14: =$A14*'Optimal_Portfolio_Q3-Q8'!E34+(1-$A14)*'Optimal_Portfolio_Q3-Q8'!E45 | I14: =$A14*'Optimal_Portfolio_Q3-Q8'!F34+(1-$A14)*'Optimal_Portfolio_Q3-Q8'!F45 | J14: =$A14*'Optimal_Portfolio_Q3-Q8'!G34+(1-$A14)*'Optimal_Portfolio_Q3-Q8'!G45 | K14: =$A14*'Optimal_Portfolio_Q3-Q8'!H34+(1-$A14)*'Optimal_Portfolio_Q3-Q8'!H45 | L14: =$A14*'Optimal_Portfolio_Q3-Q8'!I34+(1-$A14)*'Optimal_Portfolio_Q3-Q8'!I45 | ... AA14: =$A14*'Optimal_Portfolio_Q3-Q8'!X34+(1-$A14)*'Optimal_Portfolio_Q3-Q8'!X45
A15: -1 | B15: =SUMPRODUCT(E15:AA15,'Optimal_Portfolio_Q3-Q8'!B31:X31) | C15: =SUMPRODUCT(E15:AA15,MMULT(E15:AA15,'Optimal_Portfolio_Q3-Q8'!B4:X26)) | E15: =$A15*'Optimal_Portfolio_Q3-Q8'!B34+(1-$A15)*'Optimal_Portfolio_Q3-Q8'!B45 | F15: =$A15*'Optimal_Portfolio_Q3-Q8'!C34+(1-$A15)*'Optimal_Portfolio_Q3-Q8'!C45 | G15: =$A15*'Optimal_Portfolio_Q3-Q8'!D34+(1-$A15)*'Optimal_Portfolio_Q3-Q8'!D45 | H15: =$A15*'Optimal_Portfolio_Q3-Q8'!E34+(1-$A15)*'Optimal_Portfolio_Q3-Q8'!E45 | I15: =$A15*'Optimal_Portfolio_Q3-Q8'!F34+(1-$A15)*'Optimal_Portfolio_Q3-Q8'!F45 | J15: =$A15*'Optimal_Portfolio_Q3-Q8'!G34+(1-$A15)*'Optimal_Portfolio_Q3-Q8'!G45 | K15: =$A15*'Optimal_Portfolio_Q3-Q8'!H34+(1-$A15)*'Optimal_Portfolio_Q3-Q8'!H45 | L15: =$A15*'Optimal_Portfolio_Q3-Q8'!I34+(1-$A15)*'Optimal_Portfolio_Q3-Q8'!I45 | ... AA15: =$A15*'Optimal_Portfolio_Q3-Q8'!X34+(1-$A15)*'Optimal_Portfolio_Q3-Q8'!X45
A16: -0.9 | B16: =SUMPRODUCT(E16:AA16,'Optimal_Portfolio_Q3-Q8'!B31:X31) | C16: =SUMPRODUCT(E16:AA16,MMULT(E16:AA16,'Optimal_Portfolio_Q3-Q8'!B4:X26)) | E16: =$A16*'Optimal_Portfolio_Q3-Q8'!B34+(1-$A16)*'Optimal_Portfolio_Q3-Q8'!B45 | F16: =$A16*'Optimal_Portfolio_Q3-Q8'!C34+(1-$A16)*'Optimal_Portfolio_Q3-Q8'!C45 | G16: =$A16*'Optimal_Portfolio_Q3-Q8'!D34+(1-$A16)*'Optimal_Portfolio_Q3-Q8'!D45 | H16: =$A16*'Optimal_Portfolio_Q3-Q8'!E34+(1-$A16)*'Optimal_Portfolio_Q3-Q8'!E45 | I16: =$A16*'Optimal_Portfolio_Q3-Q8'!F34+(1-$A16)*'Optimal_Portfolio_Q3-Q8'!F45 | J16: =$A16*'Optimal_Portfolio_Q3-Q8'!G34+(1-$A16)*'Optimal_Portfolio_Q3-Q8'!G45 | K16: =$A16*'Optimal_Portfolio_Q3-Q8'!H34+(1-$A16)*'Optimal_Portfolio_Q3-Q8'!H45 | L16: =$A16*'Optimal_Portfolio_Q3-Q8'!I34+(1-$A16)*'Optimal_Portfolio_Q3-Q8'!I45 | ... AA16: =$A16*'Optimal_Portfolio_Q3-Q8'!X34+(1-$A16)*'Optimal_Portfolio_Q3-Q8'!X45
A17: -0.8 | B17: =SUMPRODUCT(E17:AA17,'Optimal_Portfolio_Q3-Q8'!B31:X31) | C17: =SUMPRODUCT(E17:AA17,MMULT(E17:AA17,'Optimal_Portfolio_Q3-Q8'!B4:X26)) | E17: =$A17*'Optimal_Portfolio_Q3-Q8'!B34+(1-$A17)*'Optimal_Portfolio_Q3-Q8'!B45 | F17: =$A17*'Optimal_Portfolio_Q3-Q8'!C34+(1-$A17)*'Optimal_Portfolio_Q3-Q8'!C45 | G17: =$A17*'Optimal_Portfolio_Q3-Q8'!D34+(1-$A17)*'Optimal_Portfolio_Q3-Q8'!D45 | H17: =$A17*'Optimal_Portfolio_Q3-Q8'!E34+(1-$A17)*'Optimal_Portfolio_Q3-Q8'!E45 | I17: =$A17*'Optimal_Portfolio_Q3-Q8'!F34+(1-$A17)*'Optimal_Portfolio_Q3-Q8'!F45 | J17: =$A17*'Optimal_Portfolio_Q3-Q8'!G34+(1-$A17)*'Optimal_Portfolio_Q3-Q8'!G45 | K17: =$A17*'Optimal_Portfolio_Q3-Q8'!H34+(1-$A17)*'Optimal_Portfolio_Q3-Q8'!H45 | L17: =$A17*'Optimal_Portfolio_Q3-Q8'!I34+(1-$A17)*'Optimal_Portfolio_Q3-Q8'!I45 | ... AA17: =$A17*'Optimal_Portfolio_Q3-Q8'!X34+(1-$A17)*'Optimal_Portfolio_Q3-Q8'!X45
A18: -0.7 | B18: =SUMPRODUCT(E18:AA18,'Optimal_Portfolio_Q3-Q8'!B31:X31) | C18: =SUMPRODUCT(E18:AA18,MMULT(E18:AA18,'Optimal_Portfolio_Q3-Q8'!B4:X26)) | E18: =$A18*'Optimal_Portfolio_Q3-Q8'!B34+(1-$A18)*'Optimal_Portfolio_Q3-Q8'!B45 | F18: =$A18*'Optimal_Portfolio_Q3-Q8'!C34+(1-$A18)*'Optimal_Portfolio_Q3-Q8'!C45 | G18: =$A18*'Optimal_Portfolio_Q3-Q8'!D34+(1-$A18)*'Optimal_Portfolio_Q3-Q8'!D45 | H18: =$A18*'Optimal_Portfolio_Q3-Q8'!E34+(1-$A18)*'Optimal_Portfolio_Q3-Q8'!E45 | I18: =$A18*'Optimal_Portfolio_Q3-Q8'!F34+(1-$A18)*'Optimal_Portfolio_Q3-Q8'!F45 | J18: =$A18*'Optimal_Portfolio_Q3-Q8'!G34+(1-$A18)*'Optimal_Portfolio_Q3-Q8'!G45 | K18: =$A18*'Optimal_Portfolio_Q3-Q8'!H34+(1-$A18)*'Optimal_Portfolio_Q3-Q8'!H45 | L18: =$A18*'Optimal_Portfolio_Q3-Q8'!I34+(1-$A18)*'Optimal_Portfolio_Q3-Q8'!I45 | ... AA18: =$A18*'Optimal_Portfolio_Q3-Q8'!X34+(1-$A18)*'Optimal_Portfolio_Q3-Q8'!X45
A19: -0.6 | B19: =SUMPRODUCT(E19:AA19,'Optimal_Portfolio_Q3-Q8'!B31:X31) | C19: =SUMPRODUCT(E19:AA19,MMULT(E19:AA19,'Optimal_Portfolio_Q3-Q8'!B4:X26)) | E19: =$A19*'Optimal_Portfolio_Q3-Q8'!B34+(1-$A19)*'Optimal_Portfolio_Q3-Q8'!B45 | F19: =$A19*'Optimal_Portfolio_Q3-Q8'!C34+(1-$A19)*'Optimal_Portfolio_Q3-Q8'!C45 | G19: =$A19*'Optimal_Portfolio_Q3-Q8'!D34+(1-$A19)*'Optimal_Portfolio_Q3-Q8'!D45 | H19: =$A19*'Optimal_Portfolio_Q3-Q8'!E34+(1-$A19)*'Optimal_Portfolio_Q3-Q8'!E45 | I19: =$A19*'Optimal_Portfolio_Q3-Q8'!F34+(1-$A19)*'Optimal_Portfolio_Q3-Q8'!F45 | J19: =$A19*'Optimal_Portfolio_Q3-Q8'!G34+(1-$A19)*'Optimal_Portfolio_Q3-Q8'!G45 | K19: =$A19*'Optimal_Portfolio_Q3-Q8'!H34+(1-$A19)*'Optimal_Portfolio_Q3-Q8'!H45 | L19: =$A19*'Optimal_Portfolio_Q3-Q8'!I34+(1-$A19)*'Optimal_Portfolio_Q3-Q8'!I45 | ... AA19: =$A19*'Optimal_Portfolio_Q3-Q8'!X34+(1-$A19)*'Optimal_Portfolio_Q3-Q8'!X45
A20: -0.5 | B20: =SUMPRODUCT(E20:AA20,'Optimal_Portfolio_Q3-Q8'!B31:X31) | C20: =SUMPRODUCT(E20:AA20,MMULT(E20:AA20,'Optimal_Portfolio_Q3-Q8'!B4:X26)) | E20: =$A20*'Optimal_Portfolio_Q3-Q8'!B34+(1-$A20)*'Optimal_Portfolio_Q3-Q8'!B45 | F20: =$A20*'Optimal_Portfolio_Q3-Q8'!C34+(1-$A20)*'Optimal_Portfolio_Q3-Q8'!C45 | G20: =$A20*'Optimal_Portfolio_Q3-Q8'!D34+(1-$A20)*'Optimal_Portfolio_Q3-Q8'!D45 | H20: =$A20*'Optimal_Portfolio_Q3-Q8'!E34+(1-$A20)*'Optimal_Portfolio_Q3-Q8'!E45 | I20: =$A20*'Optimal_Portfolio_Q3-Q8'!F34+(1-$A20)*'Optimal_Portfolio_Q3-Q8'!F45 | J20: =$A20*'Optimal_Portfolio_Q3-Q8'!G34+(1-$A20)*'Optimal_Portfolio_Q3-Q8'!G45 | K20: =$A20*'Optimal_Portfolio_Q3-Q8'!H34+(1-$A20)*'Optimal_Portfolio_Q3-Q8'!H45 | L20: =$A20*'Optimal_Portfolio_Q3-Q8'!I34+(1-$A20)*'Optimal_Portfolio_Q3-Q8'!I45 | ... AA20: =$A20*'Optimal_Portfolio_Q3-Q8'!X34+(1-$A20)*'Optimal_Portfolio_Q3-Q8'!X45
A21: -0.4 | B21: =SUMPRODUCT(E21:AA21,'Optimal_Portfolio_Q3-Q8'!B31:X31) | C21: =SUMPRODUCT(E21:AA21,MMULT(E21:AA21,'Optimal_Portfolio_Q3-Q8'!B4:X26)) | E21: =$A21*'Optimal_Portfolio_Q3-Q8'!B34+(1-$A21)*'Optimal_Portfolio_Q3-Q8'!B45 | F21: =$A21*'Optimal_Portfolio_Q3-Q8'!C34+(1-$A21)*'Optimal_Portfolio_Q3-Q8'!C45 | G21: =$A21*'Optimal_Portfolio_Q3-Q8'!D34+(1-$A21)*'Optimal_Portfolio_Q3-Q8'!D45 | H21: =$A21*'Optimal_Portfolio_Q3-Q8'!E34+(1-$A21)*'Optimal_Portfolio_Q3-Q8'!E45 | I21: =$A21*'Optimal_Portfolio_Q3-Q8'!F34+(1-$A21)*'Optimal_Portfolio_Q3-Q8'!F45 | J21: =$A21*'Optimal_Portfolio_Q3-Q8'!G34+(1-$A21)*'Optimal_Portfolio_Q3-Q8'!G45 | K21: =$A21*'Optimal_Portfolio_Q3-Q8'!H34+(1-$A21)*'Optimal_Portfolio_Q3-Q8'!H45 | L21: =$A21*'Optimal_Portfolio_Q3-Q8'!I34+(1-$A21)*'Optimal_Portfolio_Q3-Q8'!I45 | ... AA21: =$A21*'Optimal_Portfolio_Q3-Q8'!X34+(1-$A21)*'Optimal_Portfolio_Q3-Q8'!X45
A22: -0.3 | B22: =SUMPRODUCT(E22:AA22,'Optimal_Portfolio_Q3-Q8'!B31:X31) | C22: =SUMPRODUCT(E22:AA22,MMULT(E22:AA22,'Optimal_Portfolio_Q3-Q8'!B4:X26)) | E22: =$A22*'Optimal_Portfolio_Q3-Q8'!B34+(1-$A22)*'Optimal_Portfolio_Q3-Q8'!B45 | F22: =$A22*'Optimal_Portfolio_Q3-Q8'!C34+(1-$A22)*'Optimal_Portfolio_Q3-Q8'!C45 | G22: =$A22*'Optimal_Portfolio_Q3-Q8'!D34+(1-$A22)*'Optimal_Portfolio_Q3-Q8'!D45 | H22: =$A22*'Optimal_Portfolio_Q3-Q8'!E34+(1-$A22)*'Optimal_Portfolio_Q3-Q8'!E45 | I22: =$A22*'Optimal_Portfolio_Q3-Q8'!F34+(1-$A22)*'Optimal_Portfolio_Q3-Q8'!F45 | J22: =$A22*'Optimal_Portfolio_Q3-Q8'!G34+(1-$A22)*'Optimal_Portfolio_Q3-Q8'!G45 | K22: =$A22*'Optimal_Portfolio_Q3-Q8'!H34+(1-$A22)*'Optimal_Portfolio_Q3-Q8'!H45 | L22: =$A22*'Optimal_Portfolio_Q3-Q8'!I34+(1-$A22)*'Optimal_Portfolio_Q3-Q8'!I45 | ... AA22: =$A22*'Optimal_Portfolio_Q3-Q8'!X34+(1-$A22)*'Optimal_Portfolio_Q3-Q8'!X45
A23: -0.2 | B23: =SUMPRODUCT(E23:AA23,'Optimal_Portfolio_Q3-Q8'!B31:X31) | C23: =SUMPRODUCT(E23:AA23,MMULT(E23:AA23,'Optimal_Portfolio_Q3-Q8'!B4:X26)) | E23: =$A23*'Optimal_Portfolio_Q3-Q8'!B34+(1-$A23)*'Optimal_Portfolio_Q3-Q8'!B45 | F23: =$A23*'Optimal_Portfolio_Q3-Q8'!C34+(1-$A23)*'Optimal_Portfolio_Q3-Q8'!C45 | G23: =$A23*'Optimal_Portfolio_Q3-Q8'!D34+(1-$A23)*'Optimal_Portfolio_Q3-Q8'!D45 | H23: =$A23*'Optimal_Portfolio_Q3-Q8'!E34+(1-$A23)*'Optimal_Portfolio_Q3-Q8'!E45 | I23: =$A23*'Optimal_Portfolio_Q3-Q8'!F34+(1-$A23)*'Optimal_Portfolio_Q3-Q8'!F45 | J23: =$A23*'Optimal_Portfolio_Q3-Q8'!G34+(1-$A23)*'Optimal_Portfolio_Q3-Q8'!G45 | K23: =$A23*'Optimal_Portfolio_Q3-Q8'!H34+(1-$A23)*'Optimal_Portfolio_Q3-Q8'!H45 | L23: =$A23*'Optimal_Portfolio_Q3-Q8'!I34+(1-$A23)*'Optimal_Portfolio_Q3-Q8'!I45 | ... AA23: =$A23*'Optimal_Portfolio_Q3-Q8'!X34+(1-$A23)*'Optimal_Portfolio_Q3-Q8'!X45
A24: -0.1 | B24: =SUMPRODUCT(E24:AA24,'Optimal_Portfolio_Q3-Q8'!B31:X31) | C24: =SUMPRODUCT(E24:AA24,MMULT(E24:AA24,'Optimal_Portfolio_Q3-Q8'!B4:X26)) | E24: =$A24*'Optimal_Portfolio_Q3-Q8'!B34+(1-$A24)*'Optimal_Portfolio_Q3-Q8'!B45 | F24: =$A24*'Optimal_Portfolio_Q3-Q8'!C34+(1-$A24)*'Optimal_Portfolio_Q3-Q8'!C45 | G24: =$A24*'Optimal_Portfolio_Q3-Q8'!D34+(1-$A24)*'Optimal_Portfolio_Q3-Q8'!D45 | H24: =$A24*'Optimal_Portfolio_Q3-Q8'!E34+(1-$A24)*'Optimal_Portfolio_Q3-Q8'!E45 | I24: =$A24*'Optimal_Portfolio_Q3-Q8'!F34+(1-$A24)*'Optimal_Portfolio_Q3-Q8'!F45 | J24: =$A24*'Optimal_Portfolio_Q3-Q8'!G34+(1-$A24)*'Optimal_Portfolio_Q3-Q8'!G45 | K24: =$A24*'Optimal_Portfolio_Q3-Q8'!H34+(1-$A24)*'Optimal_Portfolio_Q3-Q8'!H45 | L24: =$A24*'Optimal_Portfolio_Q3-Q8'!I34+(1-$A24)*'Optimal_Portfolio_Q3-Q8'!I45 | ... AA24: =$A24*'Optimal_Portfolio_Q3-Q8'!X34+(1-$A24)*'Optimal_Portfolio_Q3-Q8'!X45
A25: 0 | B25: =SUMPRODUCT(E25:AA25,'Optimal_Portfolio_Q3-Q8'!B31:X31) | C25: =SUMPRODUCT(E25:AA25,MMULT(E25:AA25,'Optimal_Portfolio_Q3-Q8'!B4:X26)) | E25: =$A25*'Optimal_Portfolio_Q3-Q8'!B34+(1-$A25)*'Optimal_Portfolio_Q3-Q8'!B45 | F25: =$A25*'Optimal_Portfolio_Q3-Q8'!C34+(1-$A25)*'Optimal_Portfolio_Q3-Q8'!C45 | G25: =$A25*'Optimal_Portfolio_Q3-Q8'!D34+(1-$A25)*'Optimal_Portfolio_Q3-Q8'!D45 | H25: =$A25*'Optimal_Portfolio_Q3-Q8'!E34+(1-$A25)*'Optimal_Portfolio_Q3-Q8'!E45 | I25: =$A25*'Optimal_Portfolio_Q3-Q8'!F34+(1-$A25)*'Optimal_Portfolio_Q3-Q8'!F45 | J25: =$A25*'Optimal_Portfolio_Q3-Q8'!G34+(1-$A25)*'Optimal_Portfolio_Q3-Q8'!G45 | K25: =$A25*'Optimal_Portfolio_Q3-Q8'!H34+(1-$A25)*'Optimal_Portfolio_Q3-Q8'!H45 | L25: =$A25*'Optimal_Portfolio_Q3-Q8'!I34+(1-$A25)*'Optimal_Portfolio_Q3-Q8'!I45 | ... AA25: =$A25*'Optimal_Portfolio_Q3-Q8'!X34+(1-$A25)*'Optimal_Portfolio_Q3-Q8'!X45
A26: 0.1 | B26: =SUMPRODUCT(E26:AA26,'Optimal_Portfolio_Q3-Q8'!B31:X31) | C26: =SUMPRODUCT(E26:AA26,MMULT(E26:AA26,'Optimal_Portfolio_Q3-Q8'!B4:X26)) | E26: =$A26*'Optimal_Portfolio_Q3-Q8'!B34+(1-$A26)*'Optimal_Portfolio_Q3-Q8'!B45 | F26: =$A26*'Optimal_Portfolio_Q3-Q8'!C34+(1-$A26)*'Optimal_Portfolio_Q3-Q8'!C45 | G26: =$A26*'Optimal_Portfolio_Q3-Q8'!D34+(1-$A26)*'Optimal_Portfolio_Q3-Q8'!D45 | H26: =$A26*'Optimal_Portfolio_Q3-Q8'!E34+(1-$A26)*'Optimal_Portfolio_Q3-Q8'!E45 | I26: =$A26*'Optimal_Portfolio_Q3-Q8'!F34+(1-$A26)*'Optimal_Portfolio_Q3-Q8'!F45 | J26: =$A26*'Optimal_Portfolio_Q3-Q8'!G34+(1-$A26)*'Optimal_Portfolio_Q3-Q8'!G45 | K26: =$A26*'Optimal_Portfolio_Q3-Q8'!H34+(1-$A26)*'Optimal_Portfolio_Q3-Q8'!H45 | L26: =$A26*'Optimal_Portfolio_Q3-Q8'!I34+(1-$A26)*'Optimal_Portfolio_Q3-Q8'!I45 | ... AA26: =$A26*'Optimal_Portfolio_Q3-Q8'!X34+(1-$A26)*'Optimal_Portfolio_Q3-Q8'!X45
A27: 0.2 | B27: =SUMPRODUCT(E27:AA27,'Optimal_Portfolio_Q3-Q8'!B31:X31) | C27: =SUMPRODUCT(E27:AA27,MMULT(E27:AA27,'Optimal_Portfolio_Q3-Q8'!B4:X26)) | E27: =$A27*'Optimal_Portfolio_Q3-Q8'!B34+(1-$A27)*'Optimal_Portfolio_Q3-Q8'!B45 | F27: =$A27*'Optimal_Portfolio_Q3-Q8'!C34+(1-$A27)*'Optimal_Portfolio_Q3-Q8'!C45 | G27: =$A27*'Optimal_Portfolio_Q3-Q8'!D34+(1-$A27)*'Optimal_Portfolio_Q3-Q8'!D45 | H27: =$A27*'Optimal_Portfolio_Q3-Q8'!E34+(1-$A27)*'Optimal_Portfolio_Q3-Q8'!E45 | I27: =$A27*'Optimal_Portfolio_Q3-Q8'!F34+(1-$A27)*'Optimal_Portfolio_Q3-Q8'!F45 | J27: =$A27*'Optimal_Portfolio_Q3-Q8'!G34+(1-$A27)*'Optimal_Portfolio_Q3-Q8'!G45 | K27: =$A27*'Optimal_Portfolio_Q3-Q8'!H34+(1-$A27)*'Optimal_Portfolio_Q3-Q8'!H45 | L27: =$A27*'Optimal_Portfolio_Q3-Q8'!I34+(1-$A27)*'Optimal_Portfolio_Q3-Q8'!I45 | ... AA27: =$A27*'Optimal_Portfolio_Q3-Q8'!X34+(1-$A27)*'Optimal_Portfolio_Q3-Q8'!X45
A28: 0.3 | B28: =SUMPRODUCT(E28:AA28,'Optimal_Portfolio_Q3-Q8'!B31:X31) | C28: =SUMPRODUCT(E28:AA28,MMULT(E28:AA28,'Optimal_Portfolio_Q3-Q8'!B4:X26)) | E28: =$A28*'Optimal_Portfolio_Q3-Q8'!B34+(1-$A28)*'Optimal_Portfolio_Q3-Q8'!B45 | F28: =$A28*'Optimal_Portfolio_Q3-Q8'!C34+(1-$A28)*'Optimal_Portfolio_Q3-Q8'!C45 | G28: =$A28*'Optimal_Portfolio_Q3-Q8'!D34+(1-$A28)*'Optimal_Portfolio_Q3-Q8'!D45 | H28: =$A28*'Optimal_Portfolio_Q3-Q8'!E34+(1-$A28)*'Optimal_Portfolio_Q3-Q8'!E45 | I28: =$A28*'Optimal_Portfolio_Q3-Q8'!F34+(1-$A28)*'Optimal_Portfolio_Q3-Q8'!F45 | J28: =$A28*'Optimal_Portfolio_Q3-Q8'!G34+(1-$A28)*'Optimal_Portfolio_Q3-Q8'!G45 | K28: =$A28*'Optimal_Portfolio_Q3-Q8'!H34+(1-$A28)*'Optimal_Portfolio_Q3-Q8'!H45 | L28: =$A28*'Optimal_Portfolio_Q3-Q8'!I34+(1-$A28)*'Optimal_Portfolio_Q3-Q8'!I45 | ... AA28: =$A28*'Optimal_Portfolio_Q3-Q8'!X34+(1-$A28)*'Optimal_Portfolio_Q3-Q8'!X45
A29: 0.4 | B29: =SUMPRODUCT(E29:AA29,'Optimal_Portfolio_Q3-Q8'!B31:X31) | C29: =SUMPRODUCT(E29:AA29,MMULT(E29:AA29,'Optimal_Portfolio_Q3-Q8'!B4:X26)) | E29: =$A29*'Optimal_Portfolio_Q3-Q8'!B34+(1-$A29)*'Optimal_Portfolio_Q3-Q8'!B45 | F29: =$A29*'Optimal_Portfolio_Q3-Q8'!C34+(1-$A29)*'Optimal_Portfolio_Q3-Q8'!C45 | G29: =$A29*'Optimal_Portfolio_Q3-Q8'!D34+(1-$A29)*'Optimal_Portfolio_Q3-Q8'!D45 | H29: =$A29*'Optimal_Portfolio_Q3-Q8'!E34+(1-$A29)*'Optimal_Portfolio_Q3-Q8'!E45 | I29: =$A29*'Optimal_Portfolio_Q3-Q8'!F34+(1-$A29)*'Optimal_Portfolio_Q3-Q8'!F45 | J29: =$A29*'Optimal_Portfolio_Q3-Q8'!G34+(1-$A29)*'Optimal_Portfolio_Q3-Q8'!G45 | K29: =$A29*'Optimal_Portfolio_Q3-Q8'!H34+(1-$A29)*'Optimal_Portfolio_Q3-Q8'!H45 | L29: =$A29*'Optimal_Portfolio_Q3-Q8'!I34+(1-$A29)*'Optimal_Portfolio_Q3-Q8'!I45 | ... AA29: =$A29*'Optimal_Portfolio_Q3-Q8'!X34+(1-$A29)*'Optimal_Portfolio_Q3-Q8'!X45
A30: 0.5 | B30: =SUMPRODUCT(E30:AA30,'Optimal_Portfolio_Q3-Q8'!B31:X31) | C30: =SUMPRODUCT(E30:AA30,MMULT(E30:AA30,'Optimal_Portfolio_Q3-Q8'!B4:X26)) | E30: =$A30*'Optimal_Portfolio_Q3-Q8'!B34+(1-$A30)*'Optimal_Portfolio_Q3-Q8'!B45 | F30: =$A30*'Optimal_Portfolio_Q3-Q8'!C34+(1-$A30)*'Optimal_Portfolio_Q3-Q8'!C45 | G30: =$A30*'Optimal_Portfolio_Q3-Q8'!D34+(1-$A30)*'Optimal_Portfolio_Q3-Q8'!D45 | H30: =$A30*'Optimal_Portfolio_Q3-Q8'!E34+(1-$A30)*'Optimal_Portfolio_Q3-Q8'!E45 | I30: =$A30*'Optimal_Portfolio_Q3-Q8'!F34+(1-$A30)*'Optimal_Portfolio_Q3-Q8'!F45 | J30: =$A30*'Optimal_Portfolio_Q3-Q8'!G34+(1-$A30)*'Optimal_Portfolio_Q3-Q8'!G45 | K30: =$A30*'Optimal_Portfolio_Q3-Q8'!H34+(1-$A30)*'Optimal_Portfolio_Q3-Q8'!H45 | L30: =$A30*'Optimal_Portfolio_Q3-Q8'!I34+(1-$A30)*'Optimal_Portfolio_Q3-Q8'!I45 | ... AA30: =$A30*'Optimal_Portfolio_Q3-Q8'!X34+(1-$A30)*'Optimal_Portfolio_Q3-Q8'!X45
A31: 0.6 | B31: =SUMPRODUCT(E31:AA31,'Optimal_Portfolio_Q3-Q8'!B31:X31) | C31: =SUMPRODUCT(E31:AA31,MMULT(E31:AA31,'Optimal_Portfolio_Q3-Q8'!B4:X26)) | E31: =$A31*'Optimal_Portfolio_Q3-Q8'!B34+(1-$A31)*'Optimal_Portfolio_Q3-Q8'!B45 | F31: =$A31*'Optimal_Portfolio_Q3-Q8'!C34+(1-$A31)*'Optimal_Portfolio_Q3-Q8'!C45 | G31: =$A31*'Optimal_Portfolio_Q3-Q8'!D34+(1-$A31)*'Optimal_Portfolio_Q3-Q8'!D45 | H31: =$A31*'Optimal_Portfolio_Q3-Q8'!E34+(1-$A31)*'Optimal_Portfolio_Q3-Q8'!E45 | I31: =$A31*'Optimal_Portfolio_Q3-Q8'!F34+(1-$A31)*'Optimal_Portfolio_Q3-Q8'!F45 | J31: =$A31*'Optimal_Portfolio_Q3-Q8'!G34+(1-$A31)*'Optimal_Portfolio_Q3-Q8'!G45 | K31: =$A31*'Optimal_Portfolio_Q3-Q8'!H34+(1-$A31)*'Optimal_Portfolio_Q3-Q8'!H45 | L31: =$A31*'Optimal_Portfolio_Q3-Q8'!I34+(1-$A31)*'Optimal_Portfolio_Q3-Q8'!I45 | ... AA31: =$A31*'Optimal_Portfolio_Q3-Q8'!X34+(1-$A31)*'Optimal_Portfolio_Q3-Q8'!X45
A32: 0.7 | B32: =SUMPRODUCT(E32:AA32,'Optimal_Portfolio_Q3-Q8'!B31:X31) | C32: =SUMPRODUCT(E32:AA32,MMULT(E32:AA32,'Optimal_Portfolio_Q3-Q8'!B4:X26)) | E32: =$A32*'Optimal_Portfolio_Q3-Q8'!B34+(1-$A32)*'Optimal_Portfolio_Q3-Q8'!B45 | F32: =$A32*'Optimal_Portfolio_Q3-Q8'!C34+(1-$A32)*'Optimal_Portfolio_Q3-Q8'!C45 | G32: =$A32*'Optimal_Portfolio_Q3-Q8'!D34+(1-$A32)*'Optimal_Portfolio_Q3-Q8'!D45 | H32: =$A32*'Optimal_Portfolio_Q3-Q8'!E34+(1-$A32)*'Optimal_Portfolio_Q3-Q8'!E45 | I32: =$A32*'Optimal_Portfolio_Q3-Q8'!F34+(1-$A32)*'Optimal_Portfolio_Q3-Q8'!F45 | J32: =$A32*'Optimal_Portfolio_Q3-Q8'!G34+(1-$A32)*'Optimal_Portfolio_Q3-Q8'!G45 | K32: =$A32*'Optimal_Portfolio_Q3-Q8'!H34+(1-$A32)*'Optimal_Portfolio_Q3-Q8'!H45 | L32: =$A32*'Optimal_Portfolio_Q3-Q8'!I34+(1-$A32)*'Optimal_Portfolio_Q3-Q8'!I45 | ... AA32: =$A32*'Optimal_Portfolio_Q3-Q8'!X34+(1-$A32)*'Optimal_Portfolio_Q3-Q8'!X45
A33: 0.8 | B33: =SUMPRODUCT(E33:AA33,'Optimal_Portfolio_Q3-Q8'!B31:X31) | C33: =SUMPRODUCT(E33:AA33,MMULT(E33:AA33,'Optimal_Portfolio_Q3-Q8'!B4:X26)) | E33: =$A33*'Optimal_Portfolio_Q3-Q8'!B34+(1-$A33)*'Optimal_Portfolio_Q3-Q8'!B45 | F33: =$A33*'Optimal_Portfolio_Q3-Q8'!C34+(1-$A33)*'Optimal_Portfolio_Q3-Q8'!C45 | G33: =$A33*'Optimal_Portfolio_Q3-Q8'!D34+(1-$A33)*'Optimal_Portfolio_Q3-Q8'!D45 | H33: =$A33*'Optimal_Portfolio_Q3-Q8'!E34+(1-$A33)*'Optimal_Portfolio_Q3-Q8'!E45 | I33: =$A33*'Optimal_Portfolio_Q3-Q8'!F34+(1-$A33)*'Optimal_Portfolio_Q3-Q8'!F45 | J33: =$A33*'Optimal_Portfolio_Q3-Q8'!G34+(1-$A33)*'Optimal_Portfolio_Q3-Q8'!G45 | K33: =$A33*'Optimal_Portfolio_Q3-Q8'!H34+(1-$A33)*'Optimal_Portfolio_Q3-Q8'!H45 | L33: =$A33*'Optimal_Portfolio_Q3-Q8'!I34+(1-$A33)*'Optimal_Portfolio_Q3-Q8'!I45 | ... AA33: =$A33*'Optimal_Portfolio_Q3-Q8'!X34+(1-$A33)*'Optimal_Portfolio_Q3-Q8'!X45
A34: 0.9 | B34: =SUMPRODUCT(E34:AA34,'Optimal_Portfolio_Q3-Q8'!B31:X31) | C34: =SUMPRODUCT(E34:AA34,MMULT(E34:AA34,'Optimal_Portfolio_Q3-Q8'!B4:X26)) | E34: =$A34*'Optimal_Portfolio_Q3-Q8'!B34+(1-$A34)*'Optimal_Portfolio_Q3-Q8'!B45 | F34: =$A34*'Optimal_Portfolio_Q3-Q8'!C34+(1-$A34)*'Optimal_Portfolio_Q3-Q8'!C45 | G34: =$A34*'Optimal_Portfolio_Q3-Q8'!D34+(1-$A34)*'Optimal_Portfolio_Q3-Q8'!D45 | H34: =$A34*'Optimal_Portfolio_Q3-Q8'!E34+(1-$A34)*'Optimal_Portfolio_Q3-Q8'!E45 | I34: =$A34*'Optimal_Portfolio_Q3-Q8'!F34+(1-$A34)*'Optimal_Portfolio_Q3-Q8'!F45 | J34: =$A34*'Optimal_Portfolio_Q3-Q8'!G34+(1-$A34)*'Optimal_Portfolio_Q3-Q8'!G45 | K34: =$A34*'Optimal_Portfolio_Q3-Q8'!H34+(1-$A34)*'Optimal_Portfolio_Q3-Q8'!H45 | L34: =$A34*'Optimal_Portfolio_Q3-Q8'!I34+(1-$A34)*'Optimal_Portfolio_Q3-Q8'!I45 | ... AA34: =$A34*'Optimal_Portfolio_Q3-Q8'!X34+(1-$A34)*'Optimal_Portfolio_Q3-Q8'!X45
A35: 1 | B35: =SUMPRODUCT(E35:AA35,'Optimal_Portfolio_Q3-Q8'!B31:X31) | C35: =SUMPRODUCT(E35:AA35,MMULT(E35:AA35,'Optimal_Portfolio_Q3-Q8'!B4:X26)) | E35: =$A35*'Optimal_Portfolio_Q3-Q8'!B34+(1-$A35)*'Optimal_Portfolio_Q3-Q8'!B45 | F35: =$A35*'Optimal_Portfolio_Q3-Q8'!C34+(1-$A35)*'Optimal_Portfolio_Q3-Q8'!C45 | G35: =$A35*'Optimal_Portfolio_Q3-Q8'!D34+(1-$A35)*'Optimal_Portfolio_Q3-Q8'!D45 | H35: =$A35*'Optimal_Portfolio_Q3-Q8'!E34+(1-$A35)*'Optimal_Portfolio_Q3-Q8'!E45 | I35: =$A35*'Optimal_Portfolio_Q3-Q8'!F34+(1-$A35)*'Optimal_Portfolio_Q3-Q8'!F45 | J35: =$A35*'Optimal_Portfolio_Q3-Q8'!G34+(1-$A35)*'Optimal_Portfolio_Q3-Q8'!G45 | K35: =$A35*'Optimal_Portfolio_Q3-Q8'!H34+(1-$A35)*'Optimal_Portfolio_Q3-Q8'!H45 | L35: =$A35*'Optimal_Portfolio_Q3-Q8'!I34+(1-$A35)*'Optimal_Portfolio_Q3-Q8'!I45 | ... AA35: =$A35*'Optimal_Portfolio_Q3-Q8'!X34+(1-$A35)*'Optimal_Portfolio_Q3-Q8'!X45
A36: 1.1 | B36: =SUMPRODUCT(E36:AA36,'Optimal_Portfolio_Q3-Q8'!B31:X31) | C36: =SUMPRODUCT(E36:AA36,MMULT(E36:AA36,'Optimal_Portfolio_Q3-Q8'!B4:X26)) | E36: =$A36*'Optimal_Portfolio_Q3-Q8'!B34+(1-$A36)*'Optimal_Portfolio_Q3-Q8'!B45 | F36: =$A36*'Optimal_Portfolio_Q3-Q8'!C34+(1-$A36)*'Optimal_Portfolio_Q3-Q8'!C45 | G36: =$A36*'Optimal_Portfolio_Q3-Q8'!D34+(1-$A36)*'Optimal_Portfolio_Q3-Q8'!D45 | H36: =$A36*'Optimal_Portfolio_Q3-Q8'!E34+(1-$A36)*'Optimal_Portfolio_Q3-Q8'!E45 | I36: =$A36*'Optimal_Portfolio_Q3-Q8'!F34+(1-$A36)*'Optimal_Portfolio_Q3-Q8'!F45 | J36: =$A36*'Optimal_Portfolio_Q3-Q8'!G34+(1-$A36)*'Optimal_Portfolio_Q3-Q8'!G45 | K36: =$A36*'Optimal_Portfolio_Q3-Q8'!H34+(1-$A36)*'Optimal_Portfolio_Q3-Q8'!H45 | L36: =$A36*'Optimal_Portfolio_Q3-Q8'!I34+(1-$A36)*'Optimal_Portfolio_Q3-Q8'!I45 | ... AA36: =$A36*'Optimal_Portfolio_Q3-Q8'!X34+(1-$A36)*'Optimal_Portfolio_Q3-Q8'!X45
A37: 1.2 | B37: =SUMPRODUCT(E37:AA37,'Optimal_Portfolio_Q3-Q8'!B31:X31) | C37: =SUMPRODUCT(E37:AA37,MMULT(E37:AA37,'Optimal_Portfolio_Q3-Q8'!B4:X26)) | E37: =$A37*'Optimal_Portfolio_Q3-Q8'!B34+(1-$A37)*'Optimal_Portfolio_Q3-Q8'!B45 | F37: =$A37*'Optimal_Portfolio_Q3-Q8'!C34+(1-$A37)*'Optimal_Portfolio_Q3-Q8'!C45 | G37: =$A37*'Optimal_Portfolio_Q3-Q8'!D34+(1-$A37)*'Optimal_Portfolio_Q3-Q8'!D45 | H37: =$A37*'Optimal_Portfolio_Q3-Q8'!E34+(1-$A37)*'Optimal_Portfolio_Q3-Q8'!E45 | I37: =$A37*'Optimal_Portfolio_Q3-Q8'!F34+(1-$A37)*'Optimal_Portfolio_Q3-Q8'!F45 | J37: =$A37*'Optimal_Portfolio_Q3-Q8'!G34+(1-$A37)*'Optimal_Portfolio_Q3-Q8'!G45 | K37: =$A37*'Optimal_Portfolio_Q3-Q8'!H34+(1-$A37)*'Optimal_Portfolio_Q3-Q8'!H45 | L37: =$A37*'Optimal_Portfolio_Q3-Q8'!I34+(1-$A37)*'Optimal_Portfolio_Q3-Q8'!I45 | ... AA37: =$A37*'Optimal_Portfolio_Q3-Q8'!X34+(1-$A37)*'Optimal_Portfolio_Q3-Q8'!X45
A38: 1.3 | B38: =SUMPRODUCT(E38:AA38,'Optimal_Portfolio_Q3-Q8'!B31:X31) | C38: =SUMPRODUCT(E38:AA38,MMULT(E38:AA38,'Optimal_Portfolio_Q3-Q8'!B4:X26)) | E38: =$A38*'Optimal_Portfolio_Q3-Q8'!B34+(1-$A38)*'Optimal_Portfolio_Q3-Q8'!B45 | F38: =$A38*'Optimal_Portfolio_Q3-Q8'!C34+(1-$A38)*'Optimal_Portfolio_Q3-Q8'!C45 | G38: =$A38*'Optimal_Portfolio_Q3-Q8'!D34+(1-$A38)*'Optimal_Portfolio_Q3-Q8'!D45 | H38: =$A38*'Optimal_Portfolio_Q3-Q8'!E34+(1-$A38)*'Optimal_Portfolio_Q3-Q8'!E45 | I38: =$A38*'Optimal_Portfolio_Q3-Q8'!F34+(1-$A38)*'Optimal_Portfolio_Q3-Q8'!F45 | J38: =$A38*'Optimal_Portfolio_Q3-Q8'!G34+(1-$A38)*'Optimal_Portfolio_Q3-Q8'!G45 | K38: =$A38*'Optimal_Portfolio_Q3-Q8'!H34+(1-$A38)*'Optimal_Portfolio_Q3-Q8'!H45 | L38: =$A38*'Optimal_Portfolio_Q3-Q8'!I34+(1-$A38)*'Optimal_Portfolio_Q3-Q8'!I45 | ... AA38: =$A38*'Optimal_Portfolio_Q3-Q8'!X34+(1-$A38)*'Optimal_Portfolio_Q3-Q8'!X45
A39: 1.4 | B39: =SUMPRODUCT(E39:AA39,'Optimal_Portfolio_Q3-Q8'!B31:X31) | C39: =SUMPRODUCT(E39:AA39,MMULT(E39:AA39,'Optimal_Portfolio_Q3-Q8'!B4:X26)) | E39: =$A39*'Optimal_Portfolio_Q3-Q8'!B34+(1-$A39)*'Optimal_Portfolio_Q3-Q8'!B45 | F39: =$A39*'Optimal_Portfolio_Q3-Q8'!C34+(1-$A39)*'Optimal_Portfolio_Q3-Q8'!C45 | G39: =$A39*'Optimal_Portfolio_Q3-Q8'!D34+(1-$A39)*'Optimal_Portfolio_Q3-Q8'!D45 | H39: =$A39*'Optimal_Portfolio_Q3-Q8'!E34+(1-$A39)*'Optimal_Portfolio_Q3-Q8'!E45 | I39: =$A39*'Optimal_Portfolio_Q3-Q8'!F34+(1-$A39)*'Optimal_Portfolio_Q3-Q8'!F45 | J39: =$A39*'Optimal_Portfolio_Q3-Q8'!G34+(1-$A39)*'Optimal_Portfolio_Q3-Q8'!G45 | K39: =$A39*'Optimal_Portfolio_Q3-Q8'!H34+(1-$A39)*'Optimal_Portfolio_Q3-Q8'!H45 | L39: =$A39*'Optimal_Portfolio_Q3-Q8'!I34+(1-$A39)*'Optimal_Portfolio_Q3-Q8'!I45 | ... AA39: =$A39*'Optimal_Portfolio_Q3-Q8'!X34+(1-$A39)*'Optimal_Portfolio_Q3-Q8'!X45
A40: 1.5 | B40: =SUMPRODUCT(E40:AA40,'Optimal_Portfolio_Q3-Q8'!B31:X31) | C40: =SUMPRODUCT(E40:AA40,MMULT(E40:AA40,'Optimal_Portfolio_Q3-Q8'!B4:X26)) | E40: =$A40*'Optimal_Portfolio_Q3-Q8'!B34+(1-$A40)*'Optimal_Portfolio_Q3-Q8'!B45 | F40: =$A40*'Optimal_Portfolio_Q3-Q8'!C34+(1-$A40)*'Optimal_Portfolio_Q3-Q8'!C45 | G40: =$A40*'Optimal_Portfolio_Q3-Q8'!D34+(1-$A40)*'Optimal_Portfolio_Q3-Q8'!D45 | H40: =$A40*'Optimal_Portfolio_Q3-Q8'!E34+(1-$A40)*'Optimal_Portfolio_Q3-Q8'!E45 | I40: =$A40*'Optimal_Portfolio_Q3-Q8'!F34+(1-$A40)*'Optimal_Portfolio_Q3-Q8'!F45 | J40: =$A40*'Optimal_Portfolio_Q3-Q8'!G34+(1-$A40)*'Optimal_Portfolio_Q3-Q8'!G45 | K40: =$A40*'Optimal_Portfolio_Q3-Q8'!H34+(1-$A40)*'Optimal_Portfolio_Q3-Q8'!H45 | L40: =$A40*'Optimal_Portfolio_Q3-Q8'!I34+(1-$A40)*'Optimal_Portfolio_Q3-Q8'!I45 | ... AA40: =$A40*'Optimal_Portfolio_Q3-Q8'!X34+(1-$A40)*'Optimal_Portfolio_Q3-Q8'!X45
A41: 1.6 | B41: =SUMPRODUCT(E41:AA41,'Optimal_Portfolio_Q3-Q8'!B31:X31) | C41: =SUMPRODUCT(E41:AA41,MMULT(E41:AA41,'Optimal_Portfolio_Q3-Q8'!B4:X26)) | E41: =$A41*'Optimal_Portfolio_Q3-Q8'!B34+(1-$A41)*'Optimal_Portfolio_Q3-Q8'!B45 | F41: =$A41*'Optimal_Portfolio_Q3-Q8'!C34+(1-$A41)*'Optimal_Portfolio_Q3-Q8'!C45 | G41: =$A41*'Optimal_Portfolio_Q3-Q8'!D34+(1-$A41)*'Optimal_Portfolio_Q3-Q8'!D45 | H41: =$A41*'Optimal_Portfolio_Q3-Q8'!E34+(1-$A41)*'Optimal_Portfolio_Q3-Q8'!E45 | I41: =$A41*'Optimal_Portfolio_Q3-Q8'!F34+(1-$A41)*'Optimal_Portfolio_Q3-Q8'!F45 | J41: =$A41*'Optimal_Portfolio_Q3-Q8'!G34+(1-$A41)*'Optimal_Portfolio_Q3-Q8'!G45 | K41: =$A41*'Optimal_Portfolio_Q3-Q8'!H34+(1-$A41)*'Optimal_Portfolio_Q3-Q8'!H45 | L41: =$A41*'Optimal_Portfolio_Q3-Q8'!I34+(1-$A41)*'Optimal_Portfolio_Q3-Q8'!I45 | ... AA41: =$A41*'Optimal_Portfolio_Q3-Q8'!X34+(1-$A41)*'Optimal_Portfolio_Q3-Q8'!X45
A42: 1.7 | B42: =SUMPRODUCT(E42:AA42,'Optimal_Portfolio_Q3-Q8'!B31:X31) | C42: =SUMPRODUCT(E42:AA42,MMULT(E42:AA42,'Optimal_Portfolio_Q3-Q8'!B4:X26)) | E42: =$A42*'Optimal_Portfolio_Q3-Q8'!B34+(1-$A42)*'Optimal_Portfolio_Q3-Q8'!B45 | F42: =$A42*'Optimal_Portfolio_Q3-Q8'!C34+(1-$A42)*'Optimal_Portfolio_Q3-Q8'!C45 | G42: =$A42*'Optimal_Portfolio_Q3-Q8'!D34+(1-$A42)*'Optimal_Portfolio_Q3-Q8'!D45 | H42: =$A42*'Optimal_Portfolio_Q3-Q8'!E34+(1-$A42)*'Optimal_Portfolio_Q3-Q8'!E45 | I42: =$A42*'Optimal_Portfolio_Q3-Q8'!F34+(1-$A42)*'Optimal_Portfolio_Q3-Q8'!F45 | J42: =$A42*'Optimal_Portfolio_Q3-Q8'!G34+(1-$A42)*'Optimal_Portfolio_Q3-Q8'!G45 | K42: =$A42*'Optimal_Portfolio_Q3-Q8'!H34+(1-$A42)*'Optimal_Portfolio_Q3-Q8'!H45 | L42: =$A42*'Optimal_Portfolio_Q3-Q8'!I34+(1-$A42)*'Optimal_Portfolio_Q3-Q8'!I45 | ... AA42: =$A42*'Optimal_Portfolio_Q3-Q8'!X34+(1-$A42)*'Optimal_Portfolio_Q3-Q8'!X45
A43: 1.8 | B43: =SUMPRODUCT(E43:AA43,'Optimal_Portfolio_Q3-Q8'!B31:X31) | C43: =SUMPRODUCT(E43:AA43,MMULT(E43:AA43,'Optimal_Portfolio_Q3-Q8'!B4:X26)) | E43: =$A43*'Optimal_Portfolio_Q3-Q8'!B34+(1-$A43)*'Optimal_Portfolio_Q3-Q8'!B45 | F43: =$A43*'Optimal_Portfolio_Q3-Q8'!C34+(1-$A43)*'Optimal_Portfolio_Q3-Q8'!C45 | G43: =$A43*'Optimal_Portfolio_Q3-Q8'!D34+(1-$A43)*'Optimal_Portfolio_Q3-Q8'!D45 | H43: =$A43*'Optimal_Portfolio_Q3-Q8'!E34+(1-$A43)*'Optimal_Portfolio_Q3-Q8'!E45 | I43: =$A43*'Optimal_Portfolio_Q3-Q8'!F34+(1-$A43)*'Optimal_Portfolio_Q3-Q8'!F45 | J43: =$A43*'Optimal_Portfolio_Q3-Q8'!G34+(1-$A43)*'Optimal_Portfolio_Q3-Q8'!G45 | K43: =$A43*'Optimal_Portfolio_Q3-Q8'!H34+(1-$A43)*'Optimal_Portfolio_Q3-Q8'!H45 | L43: =$A43*'Optimal_Portfolio_Q3-Q8'!I34+(1-$A43)*'Optimal_Portfolio_Q3-Q8'!I45 | ... AA43: =$A43*'Optimal_Portfolio_Q3-Q8'!X34+(1-$A43)*'Optimal_Portfolio_Q3-Q8'!X45
A44: 1.9 | B44: =SUMPRODUCT(E44:AA44,'Optimal_Portfolio_Q3-Q8'!B31:X31) | C44: =SUMPRODUCT(E44:AA44,MMULT(E44:AA44,'Optimal_Portfolio_Q3-Q8'!B4:X26)) | E44: =$A44*'Optimal_Portfolio_Q3-Q8'!B34+(1-$A44)*'Optimal_Portfolio_Q3-Q8'!B45 | F44: =$A44*'Optimal_Portfolio_Q3-Q8'!C34+(1-$A44)*'Optimal_Portfolio_Q3-Q8'!C45 | G44: =$A44*'Optimal_Portfolio_Q3-Q8'!D34+(1-$A44)*'Optimal_Portfolio_Q3-Q8'!D45 | H44: =$A44*'Optimal_Portfolio_Q3-Q8'!E34+(1-$A44)*'Optimal_Portfolio_Q3-Q8'!E45 | I44: =$A44*'Optimal_Portfolio_Q3-Q8'!F34+(1-$A44)*'Optimal_Portfolio_Q3-Q8'!F45 | J44: =$A44*'Optimal_Portfolio_Q3-Q8'!G34+(1-$A44)*'Optimal_Portfolio_Q3-Q8'!G45 | K44: =$A44*'Optimal_Portfolio_Q3-Q8'!H34+(1-$A44)*'Optimal_Portfolio_Q3-Q8'!H45 | L44: =$A44*'Optimal_Portfolio_Q3-Q8'!I34+(1-$A44)*'Optimal_Portfolio_Q3-Q8'!I45 | ... AA44: =$A44*'Optimal_Portfolio_Q3-Q8'!X34+(1-$A44)*'Optimal_Portfolio_Q3-Q8'!X45
A45: 2 | B45: =SUMPRODUCT(E45:AA45,'Optimal_Portfolio_Q3-Q8'!B31:X31) | C45: =SUMPRODUCT(E45:AA45,MMULT(E45:AA45,'Optimal_Portfolio_Q3-Q8'!B4:X26)) | E45: =$A45*'Optimal_Portfolio_Q3-Q8'!B34+(1-$A45)*'Optimal_Portfolio_Q3-Q8'!B45 | F45: =$A45*'Optimal_Portfolio_Q3-Q8'!C34+(1-$A45)*'Optimal_Portfolio_Q3-Q8'!C45 | G45: =$A45*'Optimal_Portfolio_Q3-Q8'!D34+(1-$A45)*'Optimal_Portfolio_Q3-Q8'!D45 | H45: =$A45*'Optimal_Portfolio_Q3-Q8'!E34+(1-$A45)*'Optimal_Portfolio_Q3-Q8'!E45 | I45: =$A45*'Optimal_Portfolio_Q3-Q8'!F34+(1-$A45)*'Optimal_Portfolio_Q3-Q8'!F45 | J45: =$A45*'Optimal_Portfolio_Q3-Q8'!G34+(1-$A45)*'Optimal_Portfolio_Q3-Q8'!G45 | K45: =$A45*'Optimal_Portfolio_Q3-Q8'!H34+(1-$A45)*'Optimal_Portfolio_Q3-Q8'!H45 | L45: =$A45*'Optimal_Portfolio_Q3-Q8'!I34+(1-$A45)*'Optimal_Portfolio_Q3-Q8'!I45 | ... AA45: =$A45*'Optimal_Portfolio_Q3-Q8'!X34+(1-$A45)*'Optimal_Portfolio_Q3-Q8'!X45
A48: Exact solve: phi on the frontier where variance = 0.00004 (quadratic: a*phi^2+b*phi+(c-target)=0)
A49: a = (x1-x2)^T V (x1-x2) | B49: {=SUMPRODUCT(('Optimal_Portfolio_Q3-Q8'!B34:X34-'Optimal_Portfolio_Q3-Q8'!B45:X45),MMULT(('Optimal_Portfolio_Q3-Q8'!B34:X34-'Optimal_Portfolio_Q3-Q8'!B45:X45),'Optimal_Portfolio_Q3-Q8'!B4:X26))}
A50: b = 2 * x2^T V (x1-x2) | B50: {=2*SUMPRODUCT('Optimal_Portfolio_Q3-Q8'!B45:X45,MMULT(('Optimal_Portfolio_Q3-Q8'!B34:X34-'Optimal_Portfolio_Q3-Q8'!B45:X45),'Optimal_Portfolio_Q3-Q8'!B4:X26))}
A51: c = x2^T V x2 | B51: {=SUMPRODUCT('Optimal_Portfolio_Q3-Q8'!B45:X45,MMULT('Optimal_Portfolio_Q3-Q8'!B45:X45,'Optimal_Portfolio_Q3-Q8'!B4:X26))}
A52: target variance | B52: 4e-05
A53: phi* (root giving the efficient/upper branch) | B53: =(-B50-SQRT(B50^2-4*B49*(B51-B52)))/(2*B49)
A54: z* = phi* * x1 + (1-phi*) * x2 | B54: {=$B$53*'Optimal_Portfolio_Q3-Q8'!B34:X34+(1-$B$53)*'Optimal_Portfolio_Q3-Q8'!B45:X45}
A55: mean return of z* [Q7 answer] | B55: {=SUMPRODUCT(B54:X54,'Optimal_Portfolio_Q3-Q8'!B31:X31)}
A56: variance of z* (sanity check, should be 0.00004) | B56: {=SUMPRODUCT(B54:X54,MMULT(B54:X54,'Optimal_Portfolio_Q3-Q8'!B4:X26))}
A59: Q8: which portfolios are achievable? (approximate coordinates read off the plotted points)
A60: For any target return r on this frontier line, phi(r) = (0.0008 - r) / 0.0003, and the minimum variance for that return is var_min(r) = a*phi(r)^2 + b*phi(r) + c. A point is achievable only if its variance >= var_min(its return).
A62: Portfolio | B62: Return (approx.) | C62: Variance (approx.) | D62: var_min(return) | E62: Achievable?
A63: A | B63: 0.0005 | C63: 3.95e-05 | D63: =$B$49*((0.0008-B63)/0.0003)^2+$B$50*((0.0008-B63)/0.0003)+$B$51 | E63: =IF(C63>=D63,"Achievable","NOT achievable")
A64: C | B64: 0.0008 | C64: 3.78e-05 | D64: =$B$49*((0.0008-B64)/0.0003)^2+$B$50*((0.0008-B64)/0.0003)+$B$51 | E64: =IF(C64>=D64,"Achievable","NOT achievable")
A65: B | B65: 0.0009 | C65: 4.62e-05 | D65: =$B$49*((0.0008-B65)/0.0003)^2+$B$50*((0.0008-B65)/0.0003)+$B$51 | E65: =IF(C65>=D65,"Achievable","NOT achievable")
A66: D | B66: 0.0013 | C66: 4.78e-05 | D66: =$B$49*((0.0008-B66)/0.0003)^2+$B$50*((0.0008-B66)/0.0003)+$B$51 | E66: =IF(C66>=D66,"Achievable","NOT achievable")

Sheet Returns_2018
A1: date | B1: IBM | C1: GE | D1: LLY | E1: F | F1: BAC | G1: KR | H1: ITUB | I1: GG | J1: SIRI | K1: ACB | L1: VALE | M1: PFE | N1: CTL | O1: T | P1: ECA | Q1: ABEV | R1: CVS | S1: MRVL | T1: CSCO | U1: MO | V1: BMY | W1: WFC | X1: HBAN
A2: 2018-01-02 | B2: 0.027116872 | C2: 0.00941054 | D2: 0.0054175034 | E2: 0.0078678912 | F2: -0.0033500997 | G2: -0.016028798 | H2: 0.013216038 | I2: 0.0082862738 | J2: 0 | K2: 0.17650306 | L2: 0.0062451351 | M2: 0.0073821379 | N2: -0.019136561 | O2: -0.023363692 | P2: 0.0058139642 | Q2: 0.0060331949 | R2: -0.0043620531 | S2: 0.030607784 | T2: 0.0079456413 | U2: -0.0036821243 | V2: 0.00081518283 | W2: 0.0076641421 | X2: 0.0081855766
A3: 2018-01-03 | B3: 0.020051213 | C3: 0.020720504 | D3: 0.0044532742 | E3: 0.01709438 | F3: 0.013002393 | G3: -0.031737146 | H3: 0.012323398 | I3: 0.0044910569 | J3: 0.019011961 | K3: -0.079085367 | L3: -0.0015576683 | M3: 0.0021769214 | N3: -0.0064611451 | O3: 0.009253165 | P3: -0.024203596 | Q3: -0.0015049256 | R3: 0.026024531 | S3: 0.022463168 | T3: -0.0046058549 | U3: -0.0039807617 | V3: 0.0063358085 | W3: 0.012430549 | X3: 0.0087927595
A4: 2018-01-04 | B4: 0.0048737475 | C4: 0.00053949513 | D4: 0.012203104 | E4: 0.016807139 | F4: 0.0046265578 | G4: 0.01252319 | H4: 0.01217348 | I4: 0.0022379519 | J4: 0.0037593994 | K4: 0.01519496 | L4: 0.020062419 | M4: 0.0019008748 | N4: 0.0017663053 | O4: 0.0036774244 | P4: -0.0089485968 | Q4: 0.004507928 | R4: 0.04324153 | S4: -0.017669059 | T4: 0.0137546 | U4: 0.0028450173 | V4: 0.0022646304 | W4: 0.0067156978 | X4: 0.0087160566
A5: 2018-01-05 | B5: 0.0060129995 | C5: -0.014122994 | D5: -0.0050955808 | E5: -0.0037950855 | F5: -0.0069478884 | G5: 0.023513459 | H5: -0.01361544 | I5: 0.0081632852 | J5: -0.0037593994 | K5: 0.052776712 | L5: 0.017418051 | M5: -0.011185489 | N5: 0.01343868 | O5: 0.0028799761 | P5: -0.0030007495 | Q5: -0.0075245187 | R5: -0.0087057307 | S5: 0.0073641258 | T5: 0.010318447 | U5: -0.0012792834 | V5: 0.00032310918 | W5: -0.011379225 | X5: -0.0020046605
A6: 2018-01-08 | B6: 0.0021998213 | C6: 0.015201112 | D6: -0.00081305187 | E6: -0.0053373894 | F6: 0.0049677074 | G6: -0.0071761649 | H6: -0.013072069 | I6: 0 | J6: 0 | K6: -0.022056433 | L6: -0.006024109 | M6: -0.0010980214 | N6: -0.040870279 | O6: -0.020069285 | P6: 0.024491014 | Q6: -0.0060606189 | R6: -0.0010291292 | S6: -0.00086357768 | T6: -0.0062790614 | U6: -0.010580566 | V6: -0.0009696409 | W6: 0.003539785 | X6: 0.01855585
A7: 2018-01-09 | B7: 0.0021340263 | C7: 0.019739287 | D7: 0.00046469467 | E7: -0.0038299696 | F7: 0.0092075225 | G7: 0.0078909775 | H7: 0.0029197074 | I7: 0.017582924 | J7: 0.046006273 | K7: -0.027896683 | L7: -0.0068208036 | M7: 0.0016465803 | N7: 0.055275599 | O7: -0.023479765 | P7: 0.011661928 | Q7: 0.0045489403 | R7: -0.0032231059 | S7: -0.00043206867 | T7: 0.005527683 | U7: 0.010296119 | V7: 0.0025835611 | W7: 0.013718522 | X7: 0.016281702
A8: 2018-01-10 | B8: 0.00012183612 | C8: 0.0047430838 | D8: 0.0033625276 | E8: 0.0099275437 | F8: 0.0035942078 | G8: 0.0032102811 | H8: 0.03015301 | I8: 0.0093964667 | J8: -0.010850006 | K8: -0.087353231 | L8: 0.022557362 | M8: 0.0024647459 | N8: -0.0005722592 | O8: -0.0038303574 | P8: 0.01724179 | Q8: 0.02391741 | R8: 0.020197468 | S8: 0.00043206867 | T8: 0.004749381 | U8: 0 | V8: 0.0073908258 | W8: -0.0017442423 | X8: 0.0096433132
A9: 2018-01-11 | B9: -0.0064764543 | C9: -0.013764113 | D9: 0.0068063245 | E9: 0.0053050292 | F9: 0.017138679 | G9: 0.0021344536 | H9: -0.0014154271 | I9: 0.031861156 | J9: -0.0036429878 | K9: -0.16101175 | L9: 0.0059303306 | M9: -0.00054720814 | N9: -0.0063163405 | O9: 0.01144744 | P9: -0.0042826918 | Q9: -0.014881213 | R9: -0.0030418005 | S9: 0.029370085 | T9: 0.019019975 | U9: -0.0097213103 | V9: 0.0054278573 | W9: -0.0073271926 | X9: 0.013977373
A10: 2018-01-12 | B10: 0.0043426883 | C10: -0.029756083 | D10: -0.019621021 | E10: -0.0098746842 | F10: 0.0016017699 | G10: 0.0039014276 | H10: 0.012667394 | I10: 0.069968001 | J10: -0.018416709 | K10: 0.14758871 | L10: -0.026967901 | M10: 0.0016406227 | N10: -0.0011527642 | O10: -0.0048899934 | P10: -0.038648612 | Q10: 0.011922634 | R10: 0.0083429084 | S10: -0.010965957 | T10: -0.0081071078 | U10: -0.0099618589 | V10: -0.04710401 | W10: -0.00079966797 | X10: -0.01078349
A11: 2018-01-16 | B11: 0.028874113 | C11: -0.048378406 | D11: 0.010728945 | E11: -0.072816972 | F11: -0.0019224442 | G11: 0.014757825 | H11: 0.015955875 | I11: -0.045870489 | J11: 0.011090676 | K11: 0.030708676 | L11: 0.013574892 | M11: 0.015722792 | N11: 0.0051768969 | O11: 0.0035339782 | P11: 0.010355148 | Q11: 0.004434628 | R11: 0.00075497119 | S11: 0.00042400801 | T11: 0.016149111 | U11: 0.017689443 | V11: 0.031701766 | W11: 0.021839783 | X11: 0.0050890646
A12: 2018-01-17 | B12: 0.0027829679 | C12: -0.034000887 | D12: -0.0045340936 | E12: -0.0090722775 | F12: 0.0095755356 | G12: 0.013511357 | H12: 0.0020626124 | I12: -0.021313936 | J12: 0.0054995067 | K12: 0.053770095 | L12: 0 | M12: -0.0051233393 | N12: -0.0051768969 | O12: 0.008108235 | P12: -0.014079561 | Q12: -0.002954209 | R12: -0.0018885939 | S12: 0.0042301408 | T12: 0.0024242066 | U12: -0.0017121241 | V12: -0.00032336098 | W12: 0.0010951999 | X12: -0.015990107
A13: 2018-01-18 | B13: -0.040730842 | C13: -0.0308835 | D13: -0.003852691 | E13: -0.00581636 | F13: 0.0075949661 | G13: 0.022457557 | H13: 0.014996858 | I13: -0.0048764045 | J13: 0.023488003 | K13: 0.02844151 | L13: 0.00074872899 | M13: -0.0013527136 | N13: -0.0017316418 | O13: 0.0016137055 | P13: 0.0066939748 | Q13: 0.014684537 | R13: 0.0064066815 | S13: -0.00042221781 | T13: -0.00024211942 | U13: 0.015444926 | V13: 0.0072516142 | W13: 0.0042131677 | X13: 0.019157686
... A251: 2018-12-28 | B251: 0.0056462382 | C251: 0.007957632 | D251: 0.01322222 | E251: -0.020699296 | F251: 0.010197927 | G251: -0.0029048649 | H251: 0.011001253 | I251: 0.013354088 | J251: -0.0017497384 | K251: -0.053005533 | L251: 0.012972263 | M251: 0.015933888 | N251: -0.0078896424 | O251: 0.0028070836 | P251: -0.0068965723 | Q251: 0.0051150957 | R251: 0.0050492679 | S251: 0.033922908 | T251: 0.013008345 | U251: 0.010175098 | V251: 0.020210578 | W251: 0.0065317683 | X251: 0.0025199285

Sheet Analysis_2018
A1: Q1: Average daily returns and covariance matrix (2018 data)
A3: COVARIANCE MATRIX | B3: IBM | C3: GE | D3: LLY | E3: F | F3: BAC | G3: KR | H3: ITUB | I3: GG | J3: SIRI | K3: ACB | L3: VALE | M3: PFE | N3: CTL | O3: T | P3: ECA | Q3: ABEV | R3: CVS | S3: MRVL | T3: CSCO | U3: MO | V3: BMY | W3: WFC | X3: HBAN
A4: IBM | B4: =_xlfn.COVARIANCE.S(Returns_2018!B2:B251,Returns_2018!B2:B251) | C4: =_xlfn.COVARIANCE.S(Returns_2018!B2:B251,Returns_2018!C2:C251) | D4: =_xlfn.COVARIANCE.S(Returns_2018!B2:B251,Returns_2018!D2:D251) | E4: =_xlfn.COVARIANCE.S(Returns_2018!B2:B251,Returns_2018!E2:E251) | F4: =_xlfn.COVARIANCE.S(Returns_2018!B2:B251,Returns_2018!F2:F251) | G4: =_xlfn.COVARIANCE.S(Returns_2018!B2:B251,Returns_2018!G2:G251) | H4: =_xlfn.COVARIANCE.S(Returns_2018!B2:B251,Returns_2018!H2:H251) | I4: =_xlfn.COVARIANCE.S(Returns_2018!B2:B251,Returns_2018!I2:I251) | J4: =_xlfn.COVARIANCE.S(Returns_2018!B2:B251,Returns_2018!J2:J251) | K4: =_xlfn.COVARIANCE.S(Returns_2018!B2:B251,Returns_2018!K2:K251) | L4: =_xlfn.COVARIANCE.S(Returns_2018!B2:B251,Returns_2018!L2:L251) | M4: =_xlfn.COVARIANCE.S(Returns_2018!B2:B251,Returns_2018!M2:M251) | N4: =_xlfn.COVARIANCE.S(Returns_2018!B2:B251,Returns_2018!N2:N251) | O4: =_xlfn.COVARIANCE.S(Returns_2018!B2:B251,Returns_2018!O2:O251) | P4: =_xlfn.COVARIANCE.S(Returns_2018!B2:B251,Returns_2018!P2:P251) | Q4: =_xlfn.COVARIANCE.S(Returns_2018!B2:B251,Returns_2018!Q2:Q251) | R4: =_xlfn.COVARIANCE.S(Returns_2018!B2:B251,Returns_2018!R2:R251) | S4: =_xlfn.COVARIANCE.S(Returns_2018!B2:B251,Returns_2018!S2:S251) | T4: =_xlfn.COVARIANCE.S(Returns_2018!B2:B251,Returns_2018!T2:T251) | U4: =_xlfn.COVARIANCE.S(Returns_2018!B2:B251,Returns_2018!U2:U251) | V4: =_xlfn.COVARIANCE.S(Returns_2018!B2:B251,Returns_2018!V2:V251) | W4: =_xlfn.COVARIANCE.S(Returns_2018!B2:B251,Returns_2018!W2:W251) | X4: =_xlfn.COVARIANCE.S(Returns_2018!B2:B251,Returns_2018!X2:X251)
A5: GE | B5: =_xlfn.COVARIANCE.S(Returns_2018!C2:C251,Returns_2018!B2:B251) | C5: =_xlfn.COVARIANCE.S(Returns_2018!C2:C251,Returns_2018!C2:C251) | D5: =_xlfn.COVARIANCE.S(Returns_2018!C2:C251,Returns_2018!D2:D251) | E5: =_xlfn.COVARIANCE.S(Returns_2018!C2:C251,Returns_2018!E2:E251) | F5: =_xlfn.COVARIANCE.S(Returns_2018!C2:C251,Returns_2018!F2:F251) | G5: =_xlfn.COVARIANCE.S(Returns_2018!C2:C251,Returns_2018!G2:G251) | H5: =_xlfn.COVARIANCE.S(Returns_2018!C2:C251,Returns_2018!H2:H251) | I5: =_xlfn.COVARIANCE.S(Returns_2018!C2:C251,Returns_2018!I2:I251) | J5: =_xlfn.COVARIANCE.S(Returns_2018!C2:C251,Returns_2018!J2:J251) | K5: =_xlfn.COVARIANCE.S(Returns_2018!C2:C251,Returns_2018!K2:K251) | L5: =_xlfn.COVARIANCE.S(Returns_2018!C2:C251,Returns_2018!L2:L251) | M5: =_xlfn.COVARIANCE.S(Returns_2018!C2:C251,Returns_2018!M2:M251) | N5: =_xlfn.COVARIANCE.S(Returns_2018!C2:C251,Returns_2018!N2:N251) | O5: =_xlfn.COVARIANCE.S(Returns_2018!C2:C251,Returns_2018!O2:O251) | P5: =_xlfn.COVARIANCE.S(Returns_2018!C2:C251,Returns_2018!P2:P251) | Q5: =_xlfn.COVARIANCE.S(Returns_2018!C2:C251,Returns_2018!Q2:Q251) | R5: =_xlfn.COVARIANCE.S(Returns_2018!C2:C251,Returns_2018!R2:R251) | S5: =_xlfn.COVARIANCE.S(Returns_2018!C2:C251,Returns_2018!S2:S251) | T5: =_xlfn.COVARIANCE.S(Returns_2018!C2:C251,Returns_2018!T2:T251) | U5: =_xlfn.COVARIANCE.S(Returns_2018!C2:C251,Returns_2018!U2:U251) | V5: =_xlfn.COVARIANCE.S(Returns_2018!C2:C251,Returns_2018!V2:V251) | W5: =_xlfn.COVARIANCE.S(Returns_2018!C2:C251,Returns_2018!W2:W251) | X5: =_xlfn.COVARIANCE.S(Returns_2018!C2:C251,Returns_2018!X2:X251)
A6: LLY | B6: =_xlfn.COVARIANCE.S(Returns_2018!D2:D251,Returns_2018!B2:B251) | C6: =_xlfn.COVARIANCE.S(Returns_2018!D2:D251,Returns_2018!C2:C251) | D6: =_xlfn.COVARIANCE.S(Returns_2018!D2:D251,Returns_2018!D2:D251) | E6: =_xlfn.COVARIANCE.S(Returns_2018!D2:D251,Returns_2018!E2:E251) | F6: =_xlfn.COVARIANCE.S(Returns_2018!D2:D251,Returns_2018!F2:F251) | G6: =_xlfn.COVARIANCE.S(Returns_2018!D2:D251,Returns_2018!G2:G251) | H6: =_xlfn.COVARIANCE.S(Returns_2018!D2:D251,Returns_2018!H2:H251) | I6: =_xlfn.COVARIANCE.S(Returns_2018!D2:D251,Returns_2018!I2:I251) | J6: =_xlfn.COVARIANCE.S(Returns_2018!D2:D251,Returns_2018!J2:J251) | K6: =_xlfn.COVARIANCE.S(Returns_2018!D2:D251,Returns_2018!K2:K251) | L6: =_xlfn.COVARIANCE.S(Returns_2018!D2:D251,Returns_2018!L2:L251) | M6: =_xlfn.COVARIANCE.S(Returns_2018!D2:D251,Returns_2018!M2:M251) | N6: =_xlfn.COVARIANCE.S(Returns_2018!D2:D251,Returns_2018!N2:N251) | O6: =_xlfn.COVARIANCE.S(Returns_2018!D2:D251,Returns_2018!O2:O251) | P6: =_xlfn.COVARIANCE.S(Returns_2018!D2:D251,Returns_2018!P2:P251) | Q6: =_xlfn.COVARIANCE.S(Returns_2018!D2:D251,Returns_2018!Q2:Q251) | R6: =_xlfn.COVARIANCE.S(Returns_2018!D2:D251,Returns_2018!R2:R251) | S6: =_xlfn.COVARIANCE.S(Returns_2018!D2:D251,Returns_2018!S2:S251) | T6: =_xlfn.COVARIANCE.S(Returns_2018!D2:D251,Returns_2018!T2:T251) | U6: =_xlfn.COVARIANCE.S(Returns_2018!D2:D251,Returns_2018!U2:U251) | V6: =_xlfn.COVARIANCE.S(Returns_2018!D2:D251,Returns_2018!V2:V251) | W6: =_xlfn.COVARIANCE.S(Returns_2018!D2:D251,Returns_2018!W2:W251) | X6: =_xlfn.COVARIANCE.S(Returns_2018!D2:D251,Returns_2018!X2:X251)
A7: F | B7: =_xlfn.COVARIANCE.S(Returns_2018!E2:E251,Returns_2018!B2:B251) | C7: =_xlfn.COVARIANCE.S(Returns_2018!E2:E251,Returns_2018!C2:C251) | D7: =_xlfn.COVARIANCE.S(Returns_2018!E2:E251,Returns_2018!D2:D251) | E7: =_xlfn.COVARIANCE.S(Returns_2018!E2:E251,Returns_2018!E2:E251) | F7: =_xlfn.COVARIANCE.S(Returns_2018!E2:E251,Returns_2018!F2:F251) | G7: =_xlfn.COVARIANCE.S(Returns_2018!E2:E251,Returns_2018!G2:G251) | H7: =_xlfn.COVARIANCE.S(Returns_2018!E2:E251,Returns_2018!H2:H251) | I7: =_xlfn.COVARIANCE.S(Returns_2018!E2:E251,Returns_2018!I2:I251) | J7: =_xlfn.COVARIANCE.S(Returns_2018!E2:E251,Returns_2018!J2:J251) | K7: =_xlfn.COVARIANCE.S(Returns_2018!E2:E251,Returns_2018!K2:K251) | L7: =_xlfn.COVARIANCE.S(Returns_2018!E2:E251,Returns_2018!L2:L251) | M7: =_xlfn.COVARIANCE.S(Returns_2018!E2:E251,Returns_2018!M2:M251) | N7: =_xlfn.COVARIANCE.S(Returns_2018!E2:E251,Returns_2018!N2:N251) | O7: =_xlfn.COVARIANCE.S(Returns_2018!E2:E251,Returns_2018!O2:O251) | P7: =_xlfn.COVARIANCE.S(Returns_2018!E2:E251,Returns_2018!P2:P251) | Q7: =_xlfn.COVARIANCE.S(Returns_2018!E2:E251,Returns_2018!Q2:Q251) | R7: =_xlfn.COVARIANCE.S(Returns_2018!E2:E251,Returns_2018!R2:R251) | S7: =_xlfn.COVARIANCE.S(Returns_2018!E2:E251,Returns_2018!S2:S251) | T7: =_xlfn.COVARIANCE.S(Returns_2018!E2:E251,Returns_2018!T2:T251) | U7: =_xlfn.COVARIANCE.S(Returns_2018!E2:E251,Returns_2018!U2:U251) | V7: =_xlfn.COVARIANCE.S(Returns_2018!E2:E251,Returns_2018!V2:V251) | W7: =_xlfn.COVARIANCE.S(Returns_2018!E2:E251,Returns_2018!W2:W251) | X7: =_xlfn.COVARIANCE.S(Returns_2018!E2:E251,Returns_2018!X2:X251)
A8: BAC | B8: =_xlfn.COVARIANCE.S(Returns_2018!F2:F251,Returns_2018!B2:B251) | C8: =_xlfn.COVARIANCE.S(Returns_2018!F2:F251,Returns_2018!C2:C251) | D8: =_xlfn.COVARIANCE.S(Returns_2018!F2:F251,Returns_2018!D2:D251) | E8: =_xlfn.COVARIANCE.S(Returns_2018!F2:F251,Returns_2018!E2:E251) | F8: =_xlfn.COVARIANCE.S(Returns_2018!F2:F251,Returns_2018!F2:F251) | G8: =_xlfn.COVARIANCE.S(Returns_2018!F2:F251,Returns_2018!G2:G251) | H8: =_xlfn.COVARIANCE.S(Returns_2018!F2:F251,Returns_2018!H2:H251) | I8: =_xlfn.COVARIANCE.S(Returns_2018!F2:F251,Returns_2018!I2:I251) | J8: =_xlfn.COVARIANCE.S(Returns_2018!F2:F251,Returns_2018!J2:J251) | K8: =_xlfn.COVARIANCE.S(Returns_2018!F2:F251,Returns_2018!K2:K251) | L8: =_xlfn.COVARIANCE.S(Returns_2018!F2:F251,Returns_2018!L2:L251) | M8: =_xlfn.COVARIANCE.S(Returns_2018!F2:F251,Returns_2018!M2:M251) | N8: =_xlfn.COVARIANCE.S(Returns_2018!F2:F251,Returns_2018!N2:N251) | O8: =_xlfn.COVARIANCE.S(Returns_2018!F2:F251,Returns_2018!O2:O251) | P8: =_xlfn.COVARIANCE.S(Returns_2018!F2:F251,Returns_2018!P2:P251) | Q8: =_xlfn.COVARIANCE.S(Returns_2018!F2:F251,Returns_2018!Q2:Q251) | R8: =_xlfn.COVARIANCE.S(Returns_2018!F2:F251,Returns_2018!R2:R251) | S8: =_xlfn.COVARIANCE.S(Returns_2018!F2:F251,Returns_2018!S2:S251) | T8: =_xlfn.COVARIANCE.S(Returns_2018!F2:F251,Returns_2018!T2:T251) | U8: =_xlfn.COVARIANCE.S(Returns_2018!F2:F251,Returns_2018!U2:U251) | V8: =_xlfn.COVARIANCE.S(Returns_2018!F2:F251,Returns_2018!V2:V251) | W8: =_xlfn.COVARIANCE.S(Returns_2018!F2:F251,Returns_2018!W2:W251) | X8: =_xlfn.COVARIANCE.S(Returns_2018!F2:F251,Returns_2018!X2:X251)
A9: KR | B9: =_xlfn.COVARIANCE.S(Returns_2018!G2:G251,Returns_2018!B2:B251) | C9: =_xlfn.COVARIANCE.S(Returns_2018!G2:G251,Returns_2018!C2:C251) | D9: =_xlfn.COVARIANCE.S(Returns_2018!G2:G251,Returns_2018!D2:D251) | E9: =_xlfn.COVARIANCE.S(Returns_2018!G2:G251,Returns_2018!E2:E251) | F9: =_xlfn.COVARIANCE.S(Returns_2018!G2:G251,Returns_2018!F2:F251) | G9: =_xlfn.COVARIANCE.S(Returns_2018!G2:G251,Returns_2018!G2:G251) | H9: =_xlfn.COVARIANCE.S(Returns_2018!G2:G251,Returns_2018!H2:H251) | I9: =_xlfn.COVARIANCE.S(Returns_2018!G2:G251,Returns_2018!I2:I251) | J9: =_xlfn.COVARIANCE.S(Returns_2018!G2:G251,Returns_2018!J2:J251) | K9: =_xlfn.COVARIANCE.S(Returns_2018!G2:G251,Returns_2018!K2:K251) | L9: =_xlfn.COVARIANCE.S(Returns_2018!G2:G251,Returns_2018!L2:L251) | M9: =_xlfn.COVARIANCE.S(Returns_2018!G2:G251,Returns_2018!M2:M251) | N9: =_xlfn.COVARIANCE.S(Returns_2018!G2:G251,Returns_2018!N2:N251) | O9: =_xlfn.COVARIANCE.S(Returns_2018!G2:G251,Returns_2018!O2:O251) | P9: =_xlfn.COVARIANCE.S(Returns_2018!G2:G251,Returns_2018!P2:P251) | Q9: =_xlfn.COVARIANCE.S(Returns_2018!G2:G251,Returns_2018!Q2:Q251) | R9: =_xlfn.COVARIANCE.S(Returns_2018!G2:G251,Returns_2018!R2:R251) | S9: =_xlfn.COVARIANCE.S(Returns_2018!G2:G251,Returns_2018!S2:S251) | T9: =_xlfn.COVARIANCE.S(Returns_2018!G2:G251,Returns_2018!T2:T251) | U9: =_xlfn.COVARIANCE.S(Returns_2018!G2:G251,Returns_2018!U2:U251) | V9: =_xlfn.COVARIANCE.S(Returns_2018!G2:G251,Returns_2018!V2:V251) | W9: =_xlfn.COVARIANCE.S(Returns_2018!G2:G251,Returns_2018!W2:W251) | X9: =_xlfn.COVARIANCE.S(Returns_2018!G2:G251,Returns_2018!X2:X251)
A10: ITUB | B10: =_xlfn.COVARIANCE.S(Returns_2018!H2:H251,Returns_2018!B2:B251) | C10: =_xlfn.COVARIANCE.S(Returns_2018!H2:H251,Returns_2018!C2:C251) | D10: =_xlfn.COVARIANCE.S(Returns_2018!H2:H251,Returns_2018!D2:D251) | E10: =_xlfn.COVARIANCE.S(Returns_2018!H2:H251,Returns_2018!E2:E251) | F10: =_xlfn.COVARIANCE.S(Returns_2018!H2:H251,Returns_2018!F2:F251) | G10: =_xlfn.COVARIANCE.S(Returns_2018!H2:H251,Returns_2018!G2:G251) | H10: =_xlfn.COVARIANCE.S(Returns_2018!H2:H251,Returns_2018!H2:H251) | I10: =_xlfn.COVARIANCE.S(Returns_2018!H2:H251,Returns_2018!I2:I251) | J10: =_xlfn.COVARIANCE.S(Returns_2018!H2:H251,Returns_2018!J2:J251) | K10: =_xlfn.COVARIANCE.S(Returns_2018!H2:H251,Returns_2018!K2:K251) | L10: =_xlfn.COVARIANCE.S(Returns_2018!H2:H251,Returns_2018!L2:L251) | M10: =_xlfn.COVARIANCE.S(Returns_2018!H2:H251,Returns_2018!M2:M251) | N10: =_xlfn.COVARIANCE.S(Returns_2018!H2:H251,Returns_2018!N2:N251) | O10: =_xlfn.COVARIANCE.S(Returns_2018!H2:H251,Returns_2018!O2:O251) | P10: =_xlfn.COVARIANCE.S(Returns_2018!H2:H251,Returns_2018!P2:P251) | Q10: =_xlfn.COVARIANCE.S(Returns_2018!H2:H251,Returns_2018!Q2:Q251) | R10: =_xlfn.COVARIANCE.S(Returns_2018!H2:H251,Returns_2018!R2:R251) | S10: =_xlfn.COVARIANCE.S(Returns_2018!H2:H251,Returns_2018!S2:S251) | T10: =_xlfn.COVARIANCE.S(Returns_2018!H2:H251,Returns_2018!T2:T251) | U10: =_xlfn.COVARIANCE.S(Returns_2018!H2:H251,Returns_2018!U2:U251) | V10: =_xlfn.COVARIANCE.S(Returns_2018!H2:H251,Returns_2018!V2:V251) | W10: =_xlfn.COVARIANCE.S(Returns_2018!H2:H251,Returns_2018!W2:W251) | X10: =_xlfn.COVARIANCE.S(Returns_2018!H2:H251,Returns_2018!X2:X251)
A11: GG | B11: =_xlfn.COVARIANCE.S(Returns_2018!I2:I251,Returns_2018!B2:B251) | C11: =_xlfn.COVARIANCE.S(Returns_2018!I2:I251,Returns_2018!C2:C251) | D11: =_xlfn.COVARIANCE.S(Returns_2018!I2:I251,Returns_2018!D2:D251) | E11: =_xlfn.COVARIANCE.S(Returns_2018!I2:I251,Returns_2018!E2:E251) | F11: =_xlfn.COVARIANCE.S(Returns_2018!I2:I251,Returns_2018!F2:F251) | G11: =_xlfn.COVARIANCE.S(Returns_2018!I2:I251,Returns_2018!G2:G251) | H11: =_xlfn.COVARIANCE.S(Returns_2018!I2:I251,Returns_2018!H2:H251) | I11: =_xlfn.COVARIANCE.S(Returns_2018!I2:I251,Returns_2018!I2:I251) | J11: =_xlfn.COVARIANCE.S(Returns_2018!I2:I251,Returns_2018!J2:J251) | K11: =_xlfn.COVARIANCE.S(Returns_2018!I2:I251,Returns_2018!K2:K251) | L11: =_xlfn.COVARIANCE.S(Returns_2018!I2:I251,Returns_2018!L2:L251) | M11: =_xlfn.COVARIANCE.S(Returns_2018!I2:I251,Returns_2018!M2:M251) | N11: =_xlfn.COVARIANCE.S(Returns_2018!I2:I251,Returns_2018!N2:N251) | O11: =_xlfn.COVARIANCE.S(Returns_2018!I2:I251,Returns_2018!O2:O251) | P11: =_xlfn.COVARIANCE.S(Returns_2018!I2:I251,Returns_2018!P2:P251) | Q11: =_xlfn.COVARIANCE.S(Returns_2018!I2:I251,Returns_2018!Q2:Q251) | R11: =_xlfn.COVARIANCE.S(Returns_2018!I2:I251,Returns_2018!R2:R251) | S11: =_xlfn.COVARIANCE.S(Returns_2018!I2:I251,Returns_2018!S2:S251) | T11: =_xlfn.COVARIANCE.S(Returns_2018!I2:I251,Returns_2018!T2:T251) | U11: =_xlfn.COVARIANCE.S(Returns_2018!I2:I251,Returns_2018!U2:U251) | V11: =_xlfn.COVARIANCE.S(Returns_2018!I2:I251,Returns_2018!V2:V251) | W11: =_xlfn.COVARIANCE.S(Returns_2018!I2:I251,Returns_2018!W2:W251) | X11: =_xlfn.COVARIANCE.S(Returns_2018!I2:I251,Returns_2018!X2:X251)
A12: SIRI | B12: =_xlfn.COVARIANCE.S(Returns_2018!J2:J251,Returns_2018!B2:B251) | C12: =_xlfn.COVARIANCE.S(Returns_2018!J2:J251,Returns_2018!C2:C251) | D12: =_xlfn.COVARIANCE.S(Returns_2018!J2:J251,Returns_2018!D2:D251) | E12: =_xlfn.COVARIANCE.S(Returns_2018!J2:J251,Returns_2018!E2:E251) | F12: =_xlfn.COVARIANCE.S(Returns_2018!J2:J251,Returns_2018!F2:F251) | G12: =_xlfn.COVARIANCE.S(Returns_2018!J2:J251,Returns_2018!G2:G251) | H12: =_xlfn.COVARIANCE.S(Returns_2018!J2:J251,Returns_2018!H2:H251) | I12: =_xlfn.COVARIANCE.S(Returns_2018!J2:J251,Returns_2018!I2:I251) | J12: =_xlfn.COVARIANCE.S(Returns_2018!J2:J251,Returns_2018!J2:J251) | K12: =_xlfn.COVARIANCE.S(Returns_2018!J2:J251,Returns_2018!K2:K251) | L12: =_xlfn.COVARIANCE.S(Returns_2018!J2:J251,Returns_2018!L2:L251) | M12: =_xlfn.COVARIANCE.S(Returns_2018!J2:J251,Returns_2018!M2:M251) | N12: =_xlfn.COVARIANCE.S(Returns_2018!J2:J251,Returns_2018!N2:N251) | O12: =_xlfn.COVARIANCE.S(Returns_2018!J2:J251,Returns_2018!O2:O251) | P12: =_xlfn.COVARIANCE.S(Returns_2018!J2:J251,Returns_2018!P2:P251) | Q12: =_xlfn.COVARIANCE.S(Returns_2018!J2:J251,Returns_2018!Q2:Q251) | R12: =_xlfn.COVARIANCE.S(Returns_2018!J2:J251,Returns_2018!R2:R251) | S12: =_xlfn.COVARIANCE.S(Returns_2018!J2:J251,Returns_2018!S2:S251) | T12: =_xlfn.COVARIANCE.S(Returns_2018!J2:J251,Returns_2018!T2:T251) | U12: =_xlfn.COVARIANCE.S(Returns_2018!J2:J251,Returns_2018!U2:U251) | V12: =_xlfn.COVARIANCE.S(Returns_2018!J2:J251,Returns_2018!V2:V251) | W12: =_xlfn.COVARIANCE.S(Returns_2018!J2:J251,Returns_2018!W2:W251) | X12: =_xlfn.COVARIANCE.S(Returns_2018!J2:J251,Returns_2018!X2:X251)
A13: ACB | B13: =_xlfn.COVARIANCE.S(Returns_2018!K2:K251,Returns_2018!B2:B251) | C13: =_xlfn.COVARIANCE.S(Returns_2018!K2:K251,Returns_2018!C2:C251) | D13: =_xlfn.COVARIANCE.S(Returns_2018!K2:K251,Returns_2018!D2:D251) | E13: =_xlfn.COVARIANCE.S(Returns_2018!K2:K251,Returns_2018!E2:E251) | F13: =_xlfn.COVARIANCE.S(Returns_2018!K2:K251,Returns_2018!F2:F251) | G13: =_xlfn.COVARIANCE.S(Returns_2018!K2:K251,Returns_2018!G2:G251) | H13: =_xlfn.COVARIANCE.S(Returns_2018!K2:K251,Returns_2018!H2:H251) | I13: =_xlfn.COVARIANCE.S(Returns_2018!K2:K251,Returns_2018!I2:I251) | J13: =_xlfn.COVARIANCE.S(Returns_2018!K2:K251,Returns_2018!J2:J251) | K13: =_xlfn.COVARIANCE.S(Returns_2018!K2:K251,Returns_2018!K2:K251) | L13: =_xlfn.COVARIANCE.S(Returns_2018!K2:K251,Returns_2018!L2:L251) | M13: =_xlfn.COVARIANCE.S(Returns_2018!K2:K251,Returns_2018!M2:M251) | N13: =_xlfn.COVARIANCE.S(Returns_2018!K2:K251,Returns_2018!N2:N251) | O13: =_xlfn.COVARIANCE.S(Returns_2018!K2:K251,Returns_2018!O2:O251) | P13: =_xlfn.COVARIANCE.S(Returns_2018!K2:K251,Returns_2018!P2:P251) | Q13: =_xlfn.COVARIANCE.S(Returns_2018!K2:K251,Returns_2018!Q2:Q251) | R13: =_xlfn.COVARIANCE.S(Returns_2018!K2:K251,Returns_2018!R2:R251) | S13: =_xlfn.COVARIANCE.S(Returns_2018!K2:K251,Returns_2018!S2:S251) | T13: =_xlfn.COVARIANCE.S(Returns_2018!K2:K251,Returns_2018!T2:T251) | U13: =_xlfn.COVARIANCE.S(Returns_2018!K2:K251,Returns_2018!U2:U251) | V13: =_xlfn.COVARIANCE.S(Returns_2018!K2:K251,Returns_2018!V2:V251) | W13: =_xlfn.COVARIANCE.S(Returns_2018!K2:K251,Returns_2018!W2:W251) | X13: =_xlfn.COVARIANCE.S(Returns_2018!K2:K251,Returns_2018!X2:X251)
A14: VALE | B14: =_xlfn.COVARIANCE.S(Returns_2018!L2:L251,Returns_2018!B2:B251) | C14: =_xlfn.COVARIANCE.S(Returns_2018!L2:L251,Returns_2018!C2:C251) | D14: =_xlfn.COVARIANCE.S(Returns_2018!L2:L251,Returns_2018!D2:D251) | E14: =_xlfn.COVARIANCE.S(Returns_2018!L2:L251,Returns_2018!E2:E251) | F14: =_xlfn.COVARIANCE.S(Returns_2018!L2:L251,Returns_2018!F2:F251) | G14: =_xlfn.COVARIANCE.S(Returns_2018!L2:L251,Returns_2018!G2:G251) | H14: =_xlfn.COVARIANCE.S(Returns_2018!L2:L251,Returns_2018!H2:H251) | I14: =_xlfn.COVARIANCE.S(Returns_2018!L2:L251,Returns_2018!I2:I251) | J14: =_xlfn.COVARIANCE.S(Returns_2018!L2:L251,Returns_2018!J2:J251) | K14: =_xlfn.COVARIANCE.S(Returns_2018!L2:L251,Returns_2018!K2:K251) | L14: =_xlfn.COVARIANCE.S(Returns_2018!L2:L251,Returns_2018!L2:L251) | M14: =_xlfn.COVARIANCE.S(Returns_2018!L2:L251,Returns_2018!M2:M251) | N14: =_xlfn.COVARIANCE.S(Returns_2018!L2:L251,Returns_2018!N2:N251) | O14: =_xlfn.COVARIANCE.S(Returns_2018!L2:L251,Returns_2018!O2:O251) | P14: =_xlfn.COVARIANCE.S(Returns_2018!L2:L251,Returns_2018!P2:P251) | Q14: =_xlfn.COVARIANCE.S(Returns_2018!L2:L251,Returns_2018!Q2:Q251) | R14: =_xlfn.COVARIANCE.S(Returns_2018!L2:L251,Returns_2018!R2:R251) | S14: =_xlfn.COVARIANCE.S(Returns_2018!L2:L251,Returns_2018!S2:S251) | T14: =_xlfn.COVARIANCE.S(Returns_2018!L2:L251,Returns_2018!T2:T251) | U14: =_xlfn.COVARIANCE.S(Returns_2018!L2:L251,Returns_2018!U2:U251) | V14: =_xlfn.COVARIANCE.S(Returns_2018!L2:L251,Returns_2018!V2:V251) | W14: =_xlfn.COVARIANCE.S(Returns_2018!L2:L251,Returns_2018!W2:W251) | X14: =_xlfn.COVARIANCE.S(Returns_2018!L2:L251,Returns_2018!X2:X251)
A15: PFE | B15: =_xlfn.COVARIANCE.S(Returns_2018!M2:M251,Returns_2018!B2:B251) | C15: =_xlfn.COVARIANCE.S(Returns_2018!M2:M251,Returns_2018!C2:C251) | D15: =_xlfn.COVARIANCE.S(Returns_2018!M2:M251,Returns_2018!D2:D251) | E15: =_xlfn.COVARIANCE.S(Returns_2018!M2:M251,Returns_2018!E2:E251) | F15: =_xlfn.COVARIANCE.S(Returns_2018!M2:M251,Returns_2018!F2:F251) | G15: =_xlfn.COVARIANCE.S(Returns_2018!M2:M251,Returns_2018!G2:G251) | H15: =_xlfn.COVARIANCE.S(Returns_2018!M2:M251,Returns_2018!H2:H251) | I15: =_xlfn.COVARIANCE.S(Returns_2018!M2:M251,Returns_2018!I2:I251) | J15: =_xlfn.COVARIANCE.S(Returns_2018!M2:M251,Returns_2018!J2:J251) | K15: =_xlfn.COVARIANCE.S(Returns_2018!M2:M251,Returns_2018!K2:K251) | L15: =_xlfn.COVARIANCE.S(Returns_2018!M2:M251,Returns_2018!L2:L251) | M15: =_xlfn.COVARIANCE.S(Returns_2018!M2:M251,Returns_2018!M2:M251) | N15: =_xlfn.COVARIANCE.S(Returns_2018!M2:M251,Returns_2018!N2:N251) | O15: =_xlfn.COVARIANCE.S(Returns_2018!M2:M251,Returns_2018!O2:O251) | P15: =_xlfn.COVARIANCE.S(Returns_2018!M2:M251,Returns_2018!P2:P251) | Q15: =_xlfn.COVARIANCE.S(Returns_2018!M2:M251,Returns_2018!Q2:Q251) | R15: =_xlfn.COVARIANCE.S(Returns_2018!M2:M251,Returns_2018!R2:R251) | S15: =_xlfn.COVARIANCE.S(Returns_2018!M2:M251,Returns_2018!S2:S251) | T15: =_xlfn.COVARIANCE.S(Returns_2018!M2:M251,Returns_2018!T2:T251) | U15: =_xlfn.COVARIANCE.S(Returns_2018!M2:M251,Returns_2018!U2:U251) | V15: =_xlfn.COVARIANCE.S(Returns_2018!M2:M251,Returns_2018!V2:V251) | W15: =_xlfn.COVARIANCE.S(Returns_2018!M2:M251,Returns_2018!W2:W251) | X15: =_xlfn.COVARIANCE.S(Returns_2018!M2:M251,Returns_2018!X2:X251)
A16: CTL | B16: =_xlfn.COVARIANCE.S(Returns_2018!N2:N251,Returns_2018!B2:B251) | C16: =_xlfn.COVARIANCE.S(Returns_2018!N2:N251,Returns_2018!C2:C251) | D16: =_xlfn.COVARIANCE.S(Returns_2018!N2:N251,Returns_2018!D2:D251) | E16: =_xlfn.COVARIANCE.S(Returns_2018!N2:N251,Returns_2018!E2:E251) | F16: =_xlfn.COVARIANCE.S(Returns_2018!N2:N251,Returns_2018!F2:F251) | G16: =_xlfn.COVARIANCE.S(Returns_2018!N2:N251,Returns_2018!G2:G251) | H16: =_xlfn.COVARIANCE.S(Returns_2018!N2:N251,Returns_2018!H2:H251) | I16: =_xlfn.COVARIANCE.S(Returns_2018!N2:N251,Returns_2018!I2:I251) | J16: =_xlfn.COVARIANCE.S(Returns_2018!N2:N251,Returns_2018!J2:J251) | K16: =_xlfn.COVARIANCE.S(Returns_2018!N2:N251,Returns_2018!K2:K251) | L16: =_xlfn.COVARIANCE.S(Returns_2018!N2:N251,Returns_2018!L2:L251) | M16: =_xlfn.COVARIANCE.S(Returns_2018!N2:N251,Returns_2018!M2:M251) | N16: =_xlfn.COVARIANCE.S(Returns_2018!N2:N251,Returns_2018!N2:N251) | O16: =_xlfn.COVARIANCE.S(Returns_2018!N2:N251,Returns_2018!O2:O251) | P16: =_xlfn.COVARIANCE.S(Returns_2018!N2:N251,Returns_2018!P2:P251) | Q16: =_xlfn.COVARIANCE.S(Returns_2018!N2:N251,Returns_2018!Q2:Q251) | R16: =_xlfn.COVARIANCE.S(Returns_2018!N2:N251,Returns_2018!R2:R251) | S16: =_xlfn.COVARIANCE.S(Returns_2018!N2:N251,Returns_2018!S2:S251) | T16: =_xlfn.COVARIANCE.S(Returns_2018!N2:N251,Returns_2018!T2:T251) | U16: =_xlfn.COVARIANCE.S(Returns_2018!N2:N251,Returns_2018!U2:U251) | V16: =_xlfn.COVARIANCE.S(Returns_2018!N2:N251,Returns_2018!V2:V251) | W16: =_xlfn.COVARIANCE.S(Returns_2018!N2:N251,Returns_2018!W2:W251) | X16: =_xlfn.COVARIANCE.S(Returns_2018!N2:N251,Returns_2018!X2:X251)
A17: T | B17: =_xlfn.COVARIANCE.S(Returns_2018!O2:O251,Returns_2018!B2:B251) | C17: =_xlfn.COVARIANCE.S(Returns_2018!O2:O251,Returns_2018!C2:C251) | D17: =_xlfn.COVARIANCE.S(Returns_2018!O2:O251,Returns_2018!D2:D251) | E17: =_xlfn.COVARIANCE.S(Returns_2018!O2:O251,Returns_2018!E2:E251) | F17: =_xlfn.COVARIANCE.S(Returns_2018!O2:O251,Returns_2018!F2:F251) | G17: =_xlfn.COVARIANCE.S(Returns_2018!O2:O251,Returns_2018!G2:G251) | H17: =_xlfn.COVARIANCE.S(Returns_2018!O2:O251,Returns_2018!H2:H251) | I17: =_xlfn.COVARIANCE.S(Returns_2018!O2:O251,Returns_2018!I2:I251) | J17: =_xlfn.COVARIANCE.S(Returns_2018!O2:O251,Returns_2018!J2:J251) | K17: =_xlfn.COVARIANCE.S(Returns_2018!O2:O251,Returns_2018!K2:K251) | L17: =_xlfn.COVARIANCE.S(Returns_2018!O2:O251,Returns_2018!L2:L251) | M17: =_xlfn.COVARIANCE.S(Returns_2018!O2:O251,Returns_2018!M2:M251) | N17: =_xlfn.COVARIANCE.S(Returns_2018!O2:O251,Returns_2018!N2:N251) | O17: =_xlfn.COVARIANCE.S(Returns_2018!O2:O251,Returns_2018!O2:O251) | P17: =_xlfn.COVARIANCE.S(Returns_2018!O2:O251,Returns_2018!P2:P251) | Q17: =_xlfn.COVARIANCE.S(Returns_2018!O2:O251,Returns_2018!Q2:Q251) | R17: =_xlfn.COVARIANCE.S(Returns_2018!O2:O251,Returns_2018!R2:R251) | S17: =_xlfn.COVARIANCE.S(Returns_2018!O2:O251,Returns_2018!S2:S251) | T17: =_xlfn.COVARIANCE.S(Returns_2018!O2:O251,Returns_2018!T2:T251) | U17: =_xlfn.COVARIANCE.S(Returns_2018!O2:O251,Returns_2018!U2:U251) | V17: =_xlfn.COVARIANCE.S(Returns_2018!O2:O251,Returns_2018!V2:V251) | W17: =_xlfn.COVARIANCE.S(Returns_2018!O2:O251,Returns_2018!W2:W251) | X17: =_xlfn.COVARIANCE.S(Returns_2018!O2:O251,Returns_2018!X2:X251)
A18: ECA | B18: =_xlfn.COVARIANCE.S(Returns_2018!P2:P251,Returns_2018!B2:B251) | C18: =_xlfn.COVARIANCE.S(Returns_2018!P2:P251,Returns_2018!C2:C251) | D18: =_xlfn.COVARIANCE.S(Returns_2018!P2:P251,Returns_2018!D2:D251) | E18: =_xlfn.COVARIANCE.S(Returns_2018!P2:P251,Returns_2018!E2:E251) | F18: =_xlfn.COVARIANCE.S(Returns_2018!P2:P251,Returns_2018!F2:F251) | G18: =_xlfn.COVARIANCE.S(Returns_2018!P2:P251,Returns_2018!G2:G251) | H18: =_xlfn.COVARIANCE.S(Returns_2018!P2:P251,Returns_2018!H2:H251) | I18: =_xlfn.COVARIANCE.S(Returns_2018!P2:P251,Returns_2018!I2:I251) | J18: =_xlfn.COVARIANCE.S(Returns_2018!P2:P251,Returns_2018!J2:J251) | K18: =_xlfn.COVARIANCE.S(Returns_2018!P2:P251,Returns_2018!K2:K251) | L18: =_xlfn.COVARIANCE.S(Returns_2018!P2:P251,Returns_2018!L2:L251) | M18: =_xlfn.COVARIANCE.S(Returns_2018!P2:P251,Returns_2018!M2:M251) | N18: =_xlfn.COVARIANCE.S(Returns_2018!P2:P251,Returns_2018!N2:N251) | O18: =_xlfn.COVARIANCE.S(Returns_2018!P2:P251,Returns_2018!O2:O251) | P18: =_xlfn.COVARIANCE.S(Returns_2018!P2:P251,Returns_2018!P2:P251) | Q18: =_xlfn.COVARIANCE.S(Returns_2018!P2:P251,Returns_2018!Q2:Q251) | R18: =_xlfn.COVARIANCE.S(Returns_2018!P2:P251,Returns_2018!R2:R251) | S18: =_xlfn.COVARIANCE.S(Returns_2018!P2:P251,Returns_2018!S2:S251) | T18: =_xlfn.COVARIANCE.S(Returns_2018!P2:P251,Returns_2018!T2:T251) | U18: =_xlfn.COVARIANCE.S(Returns_2018!P2:P251,Returns_2018!U2:U251) | V18: =_xlfn.COVARIANCE.S(Returns_2018!P2:P251,Returns_2018!V2:V251) | W18: =_xlfn.COVARIANCE.S(Returns_2018!P2:P251,Returns_2018!W2:W251) | X18: =_xlfn.COVARIANCE.S(Returns_2018!P2:P251,Returns_2018!X2:X251)
A19: ABEV | B19: =_xlfn.COVARIANCE.S(Returns_2018!Q2:Q251,Returns_2018!B2:B251) | C19: =_xlfn.COVARIANCE.S(Returns_2018!Q2:Q251,Returns_2018!C2:C251) | D19: =_xlfn.COVARIANCE.S(Returns_2018!Q2:Q251,Returns_2018!D2:D251) | E19: =_xlfn.COVARIANCE.S(Returns_2018!Q2:Q251,Returns_2018!E2:E251) | F19: =_xlfn.COVARIANCE.S(Returns_2018!Q2:Q251,Returns_2018!F2:F251) | G19: =_xlfn.COVARIANCE.S(Returns_2018!Q2:Q251,Returns_2018!G2:G251) | H19: =_xlfn.COVARIANCE.S(Returns_2018!Q2:Q251,Returns_2018!H2:H251) | I19: =_xlfn.COVARIANCE.S(Returns_2018!Q2:Q251,Returns_2018!I2:I251) | J19: =_xlfn.COVARIANCE.S(Returns_2018!Q2:Q251,Returns_2018!J2:J251) | K19: =_xlfn.COVARIANCE.S(Returns_2018!Q2:Q251,Returns_2018!K2:K251) | L19: =_xlfn.COVARIANCE.S(Returns_2018!Q2:Q251,Returns_2018!L2:L251) | M19: =_xlfn.COVARIANCE.S(Returns_2018!Q2:Q251,Returns_2018!M2:M251) | N19: =_xlfn.COVARIANCE.S(Returns_2018!Q2:Q251,Returns_2018!N2:N251) | O19: =_xlfn.COVARIANCE.S(Returns_2018!Q2:Q251,Returns_2018!O2:O251) | P19: =_xlfn.COVARIANCE.S(Returns_2018!Q2:Q251,Returns_2018!P2:P251) | Q19: =_xlfn.COVARIANCE.S(Returns_2018!Q2:Q251,Returns_2018!Q2:Q251) | R19: =_xlfn.COVARIANCE.S(Returns_2018!Q2:Q251,Returns_2018!R2:R251) | S19: =_xlfn.COVARIANCE.S(Returns_2018!Q2:Q251,Returns_2018!S2:S251) | T19: =_xlfn.COVARIANCE.S(Returns_2018!Q2:Q251,Returns_2018!T2:T251) | U19: =_xlfn.COVARIANCE.S(Returns_2018!Q2:Q251,Returns_2018!U2:U251) | V19: =_xlfn.COVARIANCE.S(Returns_2018!Q2:Q251,Returns_2018!V2:V251) | W19: =_xlfn.COVARIANCE.S(Returns_2018!Q2:Q251,Returns_2018!W2:W251) | X19: =_xlfn.COVARIANCE.S(Returns_2018!Q2:Q251,Returns_2018!X2:X251)
A20: CVS | B20: =_xlfn.COVARIANCE.S(Returns_2018!R2:R251,Returns_2018!B2:B251) | C20: =_xlfn.COVARIANCE.S(Returns_2018!R2:R251,Returns_2018!C2:C251) | D20: =_xlfn.COVARIANCE.S(Returns_2018!R2:R251,Returns_2018!D2:D251) | E20: =_xlfn.COVARIANCE.S(Returns_2018!R2:R251,Returns_2018!E2:E251) | F20: =_xlfn.COVARIANCE.S(Returns_2018!R2:R251,Returns_2018!F2:F251) | G20: =_xlfn.COVARIANCE.S(Returns_2018!R2:R251,Returns_2018!G2:G251) | H20: =_xlfn.COVARIANCE.S(Returns_2018!R2:R251,Returns_2018!H2:H251) | I20: =_xlfn.COVARIANCE.S(Returns_2018!R2:R251,Returns_2018!I2:I251) | J20: =_xlfn.COVARIANCE.S(Returns_2018!R2:R251,Returns_2018!J2:J251) | K20: =_xlfn.COVARIANCE.S(Returns_2018!R2:R251,Returns_2018!K2:K251) | L20: =_xlfn.COVARIANCE.S(Returns_2018!R2:R251,Returns_2018!L2:L251) | M20: =_xlfn.COVARIANCE.S(Returns_2018!R2:R251,Returns_2018!M2:M251) | N20: =_xlfn.COVARIANCE.S(Returns_2018!R2:R251,Returns_2018!N2:N251) | O20: =_xlfn.COVARIANCE.S(Returns_2018!R2:R251,Returns_2018!O2:O251) | P20: =_xlfn.COVARIANCE.S(Returns_2018!R2:R251,Returns_2018!P2:P251) | Q20: =_xlfn.COVARIANCE.S(Returns_2018!R2:R251,Returns_2018!Q2:Q251) | R20: =_xlfn.COVARIANCE.S(Returns_2018!R2:R251,Returns_2018!R2:R251) | S20: =_xlfn.COVARIANCE.S(Returns_2018!R2:R251,Returns_2018!S2:S251) | T20: =_xlfn.COVARIANCE.S(Returns_2018!R2:R251,Returns_2018!T2:T251) | U20: =_xlfn.COVARIANCE.S(Returns_2018!R2:R251,Returns_2018!U2:U251) | V20: =_xlfn.COVARIANCE.S(Returns_2018!R2:R251,Returns_2018!V2:V251) | W20: =_xlfn.COVARIANCE.S(Returns_2018!R2:R251,Returns_2018!W2:W251) | X20: =_xlfn.COVARIANCE.S(Returns_2018!R2:R251,Returns_2018!X2:X251)
A21: MRVL | B21: =_xlfn.COVARIANCE.S(Returns_2018!S2:S251,Returns_2018!B2:B251) | C21: =_xlfn.COVARIANCE.S(Returns_2018!S2:S251,Returns_2018!C2:C251) | D21: =_xlfn.COVARIANCE.S(Returns_2018!S2:S251,Returns_2018!D2:D251) | E21: =_xlfn.COVARIANCE.S(Returns_2018!S2:S251,Returns_2018!E2:E251) | F21: =_xlfn.COVARIANCE.S(Returns_2018!S2:S251,Returns_2018!F2:F251) | G21: =_xlfn.COVARIANCE.S(Returns_2018!S2:S251,Returns_2018!G2:G251) | H21: =_xlfn.COVARIANCE.S(Returns_2018!S2:S251,Returns_2018!H2:H251) | I21: =_xlfn.COVARIANCE.S(Returns_2018!S2:S251,Returns_2018!I2:I251) | J21: =_xlfn.COVARIANCE.S(Returns_2018!S2:S251,Returns_2018!J2:J251) | K21: =_xlfn.COVARIANCE.S(Returns_2018!S2:S251,Returns_2018!K2:K251) | L21: =_xlfn.COVARIANCE.S(Returns_2018!S2:S251,Returns_2018!L2:L251) | M21: =_xlfn.COVARIANCE.S(Returns_2018!S2:S251,Returns_2018!M2:M251) | N21: =_xlfn.COVARIANCE.S(Returns_2018!S2:S251,Returns_2018!N2:N251) | O21: =_xlfn.COVARIANCE.S(Returns_2018!S2:S251,Returns_2018!O2:O251) | P21: =_xlfn.COVARIANCE.S(Returns_2018!S2:S251,Returns_2018!P2:P251) | Q21: =_xlfn.COVARIANCE.S(Returns_2018!S2:S251,Returns_2018!Q2:Q251) | R21: =_xlfn.COVARIANCE.S(Returns_2018!S2:S251,Returns_2018!R2:R251) | S21: =_xlfn.COVARIANCE.S(Returns_2018!S2:S251,Returns_2018!S2:S251) | T21: =_xlfn.COVARIANCE.S(Returns_2018!S2:S251,Returns_2018!T2:T251) | U21: =_xlfn.COVARIANCE.S(Returns_2018!S2:S251,Returns_2018!U2:U251) | V21: =_xlfn.COVARIANCE.S(Returns_2018!S2:S251,Returns_2018!V2:V251) | W21: =_xlfn.COVARIANCE.S(Returns_2018!S2:S251,Returns_2018!W2:W251) | X21: =_xlfn.COVARIANCE.S(Returns_2018!S2:S251,Returns_2018!X2:X251)
A22: CSCO | B22: =_xlfn.COVARIANCE.S(Returns_2018!T2:T251,Returns_2018!B2:B251) | C22: =_xlfn.COVARIANCE.S(Returns_2018!T2:T251,Returns_2018!C2:C251) | D22: =_xlfn.COVARIANCE.S(Returns_2018!T2:T251,Returns_2018!D2:D251) | E22: =_xlfn.COVARIANCE.S(Returns_2018!T2:T251,Returns_2018!E2:E251) | F22: =_xlfn.COVARIANCE.S(Returns_2018!T2:T251,Returns_2018!F2:F251) | G22: =_xlfn.COVARIANCE.S(Returns_2018!T2:T251,Returns_2018!G2:G251) | H22: =_xlfn.COVARIANCE.S(Returns_2018!T2:T251,Returns_2018!H2:H251) | I22: =_xlfn.COVARIANCE.S(Returns_2018!T2:T251,Returns_2018!I2:I251) | J22: =_xlfn.COVARIANCE.S(Returns_2018!T2:T251,Returns_2018!J2:J251) | K22: =_xlfn.COVARIANCE.S(Returns_2018!T2:T251,Returns_2018!K2:K251) | L22: =_xlfn.COVARIANCE.S(Returns_2018!T2:T251,Returns_2018!L2:L251) | M22: =_xlfn.COVARIANCE.S(Returns_2018!T2:T251,Returns_2018!M2:M251) | N22: =_xlfn.COVARIANCE.S(Returns_2018!T2:T251,Returns_2018!N2:N251) | O22: =_xlfn.COVARIANCE.S(Returns_2018!T2:T251,Returns_2018!O2:O251) | P22: =_xlfn.COVARIANCE.S(Returns_2018!T2:T251,Returns_2018!P2:P251) | Q22: =_xlfn.COVARIANCE.S(Returns_2018!T2:T251,Returns_2018!Q2:Q251) | R22: =_xlfn.COVARIANCE.S(Returns_2018!T2:T251,Returns_2018!R2:R251) | S22: =_xlfn.COVARIANCE.S(Returns_2018!T2:T251,Returns_2018!S2:S251) | T22: =_xlfn.COVARIANCE.S(Returns_2018!T2:T251,Returns_2018!T2:T251) | U22: =_xlfn.COVARIANCE.S(Returns_2018!T2:T251,Returns_2018!U2:U251) | V22: =_xlfn.COVARIANCE.S(Returns_2018!T2:T251,Returns_2018!V2:V251) | W22: =_xlfn.COVARIANCE.S(Returns_2018!T2:T251,Returns_2018!W2:W251) | X22: =_xlfn.COVARIANCE.S(Returns_2018!T2:T251,Returns_2018!X2:X251)
A23: MO | B23: =_xlfn.COVARIANCE.S(Returns_2018!U2:U251,Returns_2018!B2:B251) | C23: =_xlfn.COVARIANCE.S(Returns_2018!U2:U251,Returns_2018!C2:C251) | D23: =_xlfn.COVARIANCE.S(Returns_2018!U2:U251,Returns_2018!D2:D251) | E23: =_xlfn.COVARIANCE.S(Returns_2018!U2:U251,Returns_2018!E2:E251) | F23: =_xlfn.COVARIANCE.S(Returns_2018!U2:U251,Returns_2018!F2:F251) | G23: =_xlfn.COVARIANCE.S(Returns_2018!U2:U251,Returns_2018!G2:G251) | H23: =_xlfn.COVARIANCE.S(Returns_2018!U2:U251,Returns_2018!H2:H251) | I23: =_xlfn.COVARIANCE.S(Returns_2018!U2:U251,Returns_2018!I2:I251) | J23: =_xlfn.COVARIANCE.S(Returns_2018!U2:U251,Returns_2018!J2:J251) | K23: =_xlfn.COVARIANCE.S(Returns_2018!U2:U251,Returns_2018!K2:K251) | L23: =_xlfn.COVARIANCE.S(Returns_2018!U2:U251,Returns_2018!L2:L251) | M23: =_xlfn.COVARIANCE.S(Returns_2018!U2:U251,Returns_2018!M2:M251) | N23: =_xlfn.COVARIANCE.S(Returns_2018!U2:U251,Returns_2018!N2:N251) | O23: =_xlfn.COVARIANCE.S(Returns_2018!U2:U251,Returns_2018!O2:O251) | P23: =_xlfn.COVARIANCE.S(Returns_2018!U2:U251,Returns_2018!P2:P251) | Q23: =_xlfn.COVARIANCE.S(Returns_2018!U2:U251,Returns_2018!Q2:Q251) | R23: =_xlfn.COVARIANCE.S(Returns_2018!U2:U251,Returns_2018!R2:R251) | S23: =_xlfn.COVARIANCE.S(Returns_2018!U2:U251,Returns_2018!S2:S251) | T23: =_xlfn.COVARIANCE.S(Returns_2018!U2:U251,Returns_2018!T2:T251) | U23: =_xlfn.COVARIANCE.S(Returns_2018!U2:U251,Returns_2018!U2:U251) | V23: =_xlfn.COVARIANCE.S(Returns_2018!U2:U251,Returns_2018!V2:V251) | W23: =_xlfn.COVARIANCE.S(Returns_2018!U2:U251,Returns_2018!W2:W251) | X23: =_xlfn.COVARIANCE.S(Returns_2018!U2:U251,Returns_2018!X2:X251)
A24: BMY | B24: =_xlfn.COVARIANCE.S(Returns_2018!V2:V251,Returns_2018!B2:B251) | C24: =_xlfn.COVARIANCE.S(Returns_2018!V2:V251,Returns_2018!C2:C251) | D24: =_xlfn.COVARIANCE.S(Returns_2018!V2:V251,Returns_2018!D2:D251) | E24: =_xlfn.COVARIANCE.S(Returns_2018!V2:V251,Returns_2018!E2:E251) | F24: =_xlfn.COVARIANCE.S(Returns_2018!V2:V251,Returns_2018!F2:F251) | G24: =_xlfn.COVARIANCE.S(Returns_2018!V2:V251,Returns_2018!G2:G251) | H24: =_xlfn.COVARIANCE.S(Returns_2018!V2:V251,Returns_2018!H2:H251) | I24: =_xlfn.COVARIANCE.S(Returns_2018!V2:V251,Returns_2018!I2:I251) | J24: =_xlfn.COVARIANCE.S(Returns_2018!V2:V251,Returns_2018!J2:J251) | K24: =_xlfn.COVARIANCE.S(Returns_2018!V2:V251,Returns_2018!K2:K251) | L24: =_xlfn.COVARIANCE.S(Returns_2018!V2:V251,Returns_2018!L2:L251) | M24: =_xlfn.COVARIANCE.S(Returns_2018!V2:V251,Returns_2018!M2:M251) | N24: =_xlfn.COVARIANCE.S(Returns_2018!V2:V251,Returns_2018!N2:N251) | O24: =_xlfn.COVARIANCE.S(Returns_2018!V2:V251,Returns_2018!O2:O251) | P24: =_xlfn.COVARIANCE.S(Returns_2018!V2:V251,Returns_2018!P2:P251) | Q24: =_xlfn.COVARIANCE.S(Returns_2018!V2:V251,Returns_2018!Q2:Q251) | R24: =_xlfn.COVARIANCE.S(Returns_2018!V2:V251,Returns_2018!R2:R251) | S24: =_xlfn.COVARIANCE.S(Returns_2018!V2:V251,Returns_2018!S2:S251) | T24: =_xlfn.COVARIANCE.S(Returns_2018!V2:V251,Returns_2018!T2:T251) | U24: =_xlfn.COVARIANCE.S(Returns_2018!V2:V251,Returns_2018!U2:U251) | V24: =_xlfn.COVARIANCE.S(Returns_2018!V2:V251,Returns_2018!V2:V251) | W24: =_xlfn.COVARIANCE.S(Returns_2018!V2:V251,Returns_2018!W2:W251) | X24: =_xlfn.COVARIANCE.S(Returns_2018!V2:V251,Returns_2018!X2:X251)
A25: WFC | B25: =_xlfn.COVARIANCE.S(Returns_2018!W2:W251,Returns_2018!B2:B251) | C25: =_xlfn.COVARIANCE.S(Returns_2018!W2:W251,Returns_2018!C2:C251) | D25: =_xlfn.COVARIANCE.S(Returns_2018!W2:W251,Returns_2018!D2:D251) | E25: =_xlfn.COVARIANCE.S(Returns_2018!W2:W251,Returns_2018!E2:E251) | F25: =_xlfn.COVARIANCE.S(Returns_2018!W2:W251,Returns_2018!F2:F251) | G25: =_xlfn.COVARIANCE.S(Returns_2018!W2:W251,Returns_2018!G2:G251) | H25: =_xlfn.COVARIANCE.S(Returns_2018!W2:W251,Returns_2018!H2:H251) | I25: =_xlfn.COVARIANCE.S(Returns_2018!W2:W251,Returns_2018!I2:I251) | J25: =_xlfn.COVARIANCE.S(Returns_2018!W2:W251,Returns_2018!J2:J251) | K25: =_xlfn.COVARIANCE.S(Returns_2018!W2:W251,Returns_2018!K2:K251) | L25: =_xlfn.COVARIANCE.S(Returns_2018!W2:W251,Returns_2018!L2:L251) | M25: =_xlfn.COVARIANCE.S(Returns_2018!W2:W251,Returns_2018!M2:M251) | N25: =_xlfn.COVARIANCE.S(Returns_2018!W2:W251,Returns_2018!N2:N251) | O25: =_xlfn.COVARIANCE.S(Returns_2018!W2:W251,Returns_2018!O2:O251) | P25: =_xlfn.COVARIANCE.S(Returns_2018!W2:W251,Returns_2018!P2:P251) | Q25: =_xlfn.COVARIANCE.S(Returns_2018!W2:W251,Returns_2018!Q2:Q251) | R25: =_xlfn.COVARIANCE.S(Returns_2018!W2:W251,Returns_2018!R2:R251) | S25: =_xlfn.COVARIANCE.S(Returns_2018!W2:W251,Returns_2018!S2:S251) | T25: =_xlfn.COVARIANCE.S(Returns_2018!W2:W251,Returns_2018!T2:T251) | U25: =_xlfn.COVARIANCE.S(Returns_2018!W2:W251,Returns_2018!U2:U251) | V25: =_xlfn.COVARIANCE.S(Returns_2018!W2:W251,Returns_2018!V2:V251) | W25: =_xlfn.COVARIANCE.S(Returns_2018!W2:W251,Returns_2018!W2:W251) | X25: =_xlfn.COVARIANCE.S(Returns_2018!W2:W251,Returns_2018!X2:X251)
A26: HBAN | B26: =_xlfn.COVARIANCE.S(Returns_2018!X2:X251,Returns_2018!B2:B251) | C26: =_xlfn.COVARIANCE.S(Returns_2018!X2:X251,Returns_2018!C2:C251) | D26: =_xlfn.COVARIANCE.S(Returns_2018!X2:X251,Returns_2018!D2:D251) | E26: =_xlfn.COVARIANCE.S(Returns_2018!X2:X251,Returns_2018!E2:E251) | F26: =_xlfn.COVARIANCE.S(Returns_2018!X2:X251,Returns_2018!F2:F251) | G26: =_xlfn.COVARIANCE.S(Returns_2018!X2:X251,Returns_2018!G2:G251) | H26: =_xlfn.COVARIANCE.S(Returns_2018!X2:X251,Returns_2018!H2:H251) | I26: =_xlfn.COVARIANCE.S(Returns_2018!X2:X251,Returns_2018!I2:I251) | J26: =_xlfn.COVARIANCE.S(Returns_2018!X2:X251,Returns_2018!J2:J251) | K26: =_xlfn.COVARIANCE.S(Returns_2018!X2:X251,Returns_2018!K2:K251) | L26: =_xlfn.COVARIANCE.S(Returns_2018!X2:X251,Returns_2018!L2:L251) | M26: =_xlfn.COVARIANCE.S(Returns_2018!X2:X251,Returns_2018!M2:M251) | N26: =_xlfn.COVARIANCE.S(Returns_2018!X2:X251,Returns_2018!N2:N251) | O26: =_xlfn.COVARIANCE.S(Returns_2018!X2:X251,Returns_2018!O2:O251) | P26: =_xlfn.COVARIANCE.S(Returns_2018!X2:X251,Returns_2018!P2:P251) | Q26: =_xlfn.COVARIANCE.S(Returns_2018!X2:X251,Returns_2018!Q2:Q251) | R26: =_xlfn.COVARIANCE.S(Returns_2018!X2:X251,Returns_2018!R2:R251) | S26: =_xlfn.COVARIANCE.S(Returns_2018!X2:X251,Returns_2018!S2:S251) | T26: =_xlfn.COVARIANCE.S(Returns_2018!X2:X251,Returns_2018!T2:T251) | U26: =_xlfn.COVARIANCE.S(Returns_2018!X2:X251,Returns_2018!U2:U251) | V26: =_xlfn.COVARIANCE.S(Returns_2018!X2:X251,Returns_2018!V2:V251) | W26: =_xlfn.COVARIANCE.S(Returns_2018!X2:X251,Returns_2018!W2:W251) | X26: =_xlfn.COVARIANCE.S(Returns_2018!X2:X251,Returns_2018!X2:X251)
A29: Average_Daily_Returns | B29: =AVERAGE(Returns_2018!B2:B251) | C29: =AVERAGE(Returns_2018!C2:C251) | D29: =AVERAGE(Returns_2018!D2:D251) | E29: =AVERAGE(Returns_2018!E2:E251) | F29: =AVERAGE(Returns_2018!F2:F251) | G29: =AVERAGE(Returns_2018!G2:G251) | H29: =AVERAGE(Returns_2018!H2:H251) | I29: =AVERAGE(Returns_2018!I2:I251) | ... X29: =AVERAGE(Returns_2018!X2:X251)
A31: Risk_Free_Rate | B31: 0.0001
A34: Q2: Global minimum-variance (GMV) portfolio and the efficient frontier
A35: GMV weights (closed form: Vinv*1 / (1'Vinv*1)), written as solved values
A36: GMV_Weights | B36: 0.061174092 | C36: 0.02180796 | D36: 0.093182934 | E36: 0.053837557 | F36: -0.084039941 | G36: 0.0633717 | H36: -0.029994025 | I36: 0.15237711 | J36: 0.14332745 | K36: 0.0060110756 | L36: -0.021016668 | M36: 0.18633722 | N36: -0.053803639 | O36: 0.079984504 | P36: -0.017989995 | Q36: 0.048452687 | R36: -0.015131597 | S36: -0.0041697855 | T36: -0.053134436 | U36: 0.14285377 | V36: 0.04381523 | W36: 0.056499644 | X36: 0.12624715
A38: GMV_Mean_Return | B38: =SUMPRODUCT(B36:X36,B29:X29)
A39: GMV_Variance | B39: =SUMPRODUCT(B36:X36,MMULT(B36:X36,B4:X26))
A42: Frontier sweep: for each target return, closed-form min-variance weights (solved values)
A44: target_return | B44: variance | C44: IBM | D44: GE | E44: LLY | F44: F | G44: BAC | H44: KR | I44: ITUB | J44: GG | K44: SIRI | L44: ACB | M44: VALE | N44: PFE | O44: CTL | P44: T | Q44: ECA | R44: ABEV | S44: CVS | T44: MRVL | U44: CSCO | V44: MO | W44: BMY | X44: WFC | Y44: HBAN
A45: -0.00061620575 | B45: =SUMPRODUCT(C45:Y45,MMULT(C45:Y45,$B$4:$X$26)) | C45: 0.061174092 | D45: 0.02180796 | E45: 0.093182934 | F45: 0.053837557 | G45: -0.084039941 | H45: 0.0633717 | I45: -0.029994025 | J45: 0.15237711 | K45: 0.14332745 | L45: 0.0060110756 | M45: -0.021016668 | N45: 0.18633722 | O45: -0.053803639 | P45: 0.079984504 | Q45: -0.017989995 | R45: 0.048452687 | S45: -0.015131597 | T45: -0.0041697855 | U45: -0.053134436 | V45: 0.14285377 | W45: 0.04381523 | X45: 0.056499644 | Y45: 0.12624715
A46: -0.00057823737 | B46: =SUMPRODUCT(C46:Y46,MMULT(C46:Y46,$B$4:$X$26)) | C46: 0.059819962 | D46: 0.020520874 | E46: 0.096792999 | F46: 0.052506698 | G46: -0.082907648 | H46: 0.063794596 | I46: -0.028766013 | J46: 0.15314933 | K46: 0.1461976 | L46: 0.0058144648 | M46: -0.019699093 | N46: 0.1901767 | O46: -0.053584122 | P46: 0.078971378 | Q46: -0.019337134 | R46: 0.044737183 | S46: -0.015769802 | T46: -0.0055692684 | U46: -0.051053976 | V46: 0.14171329 | W46: 0.041955007 | X46: 0.053961408 | Y46: 0.12657556
A47: -0.00054026898 | B47: =SUMPRODUCT(C47:Y47,MMULT(C47:Y47,$B$4:$X$26)) | C47: 0.058465831 | D47: 0.019233788 | E47: 0.10040306 | F47: 0.05117584 | G47: -0.081775354 | H47: 0.064217492 | I47: -0.027538 | J47: 0.15392156 | K47: 0.14906775 | L47: 0.005617854 | M47: -0.018381518 | N47: 0.19401619 | O47: -0.053364605 | P47: 0.077958251 | Q47: -0.020684272 | R47: 0.041021679 | S47: -0.016408007 | T47: -0.0069687513 | U47: -0.048973516 | V47: 0.1405728 | W47: 0.040094783 | X47: 0.051423172 | Y47: 0.12690397
A48: -0.00050230059 | B48: =SUMPRODUCT(C48:Y48,MMULT(C48:Y48,$B$4:$X$26)) | C48: 0.057111701 | D48: 0.017946702 | E48: 0.10401313 | F48: 0.049844982 | G48: -0.08064306 | H48: 0.064640388 | I48: -0.026309987 | J48: 0.15469378 | K48: 0.1519379 | L48: 0.0054212432 | M48: -0.017063944 | N48: 0.19785567 | O48: -0.053145088 | P48: 0.076945125 | Q48: -0.02203141 | R48: 0.037306175 | S48: -0.017046213 | T48: -0.0083682341 | U48: -0.046893056 | V48: 0.13943232 | W48: 0.03823456 | X48: 0.048884937 | Y48: 0.12723237
A49: -0.00046433221 | B49: =SUMPRODUCT(C49:Y49,MMULT(C49:Y49,$B$4:$X$26)) | C49: 0.055757571 | D49: 0.016659616 | E49: 0.10762319 | F49: 0.048514124 | G49: -0.079510766 | H49: 0.065063284 | I49: -0.025081974 | J49: 0.15546601 | K49: 0.15480805 | L49: 0.0052246324 | M49: -0.015746369 | N49: 0.20169516 | O49: -0.052925572 | P49: 0.075931999 | Q49: -0.023378548 | R49: 0.033590672 | S49: -0.017684418 | T49: -0.009767717 | U49: -0.044812596 | V49: 0.13829183 | W49: 0.036374337 | X49: 0.046346701 | Y49: 0.12756078
A50: -0.00042636382 | B50: =SUMPRODUCT(C50:Y50,MMULT(C50:Y50,$B$4:$X$26)) | C50: 0.05440344 | D50: 0.01537253 | E50: 0.11123326 | F50: 0.047183265 | G50: -0.078378473 | H50: 0.065486181 | I50: -0.023853961 | J50: 0.15623824 | K50: 0.1576782 | L50: 0.0050280216 | M50: -0.014428794 | N50: 0.20553464 | O50: -0.052706055 | P50: 0.074918872 | Q50: -0.024725686 | R50: 0.029875168 | S50: -0.018322623 | T50: -0.0111672 | U50: -0.042732136 | V50: 0.13715135 | W50: 0.034514113 | X50: 0.043808465 | Y50: 0.12788918
A51: -0.00038839544 | B51: =SUMPRODUCT(C51:Y51,MMULT(C51:Y51,$B$4:$X$26)) | C51: 0.05304931 | D51: 0.014085444 | E51: 0.11484332 | F51: 0.045852407 | G51: -0.077246179 | H51: 0.065909077 | I51: -0.022625949 | J51: 0.15701046 | K51: 0.16054835 | L51: 0.0048314109 | M51: -0.01311122 | N51: 0.20937413 | O51: -0.052486538 | P51: 0.073905746 | Q51: -0.026072824 | R51: 0.026159664 | S51: -0.018960829 | T51: -0.012566683 | U51: -0.040651676 | V51: 0.13601087 | W51: 0.03265389 | X51: 0.041270229 | Y51: 0.12821759
A52: -0.00035042705 | B52: =SUMPRODUCT(C52:Y52,MMULT(C52:Y52,$B$4:$X$26)) | C52: 0.05169518 | D52: 0.012798358 | E52: 0.11845339 | F52: 0.044521549 | G52: -0.076113885 | H52: 0.066331973 | I52: -0.021397936 | J52: 0.15778269 | K52: 0.1634185 | L52: 0.0046348001 | M52: -0.011793645 | N52: 0.21321361 | O52: -0.052267022 | P52: 0.07289262 | Q52: -0.027419962 | R52: 0.02244416 | S52: -0.019599034 | T52: -0.013966166 | U52: -0.038571215 | V52: 0.13487038 | W52: 0.030793666 | X52: 0.038731993 | Y52: 0.128546
A53: -0.00031245867 | B53: =SUMPRODUCT(C53:Y53,MMULT(C53:Y53,$B$4:$X$26)) | C53: 0.050341049 | D53: 0.011511272 | E53: 0.12206345 | F53: 0.04319069 | G53: -0.074981591 | H53: 0.066754869 | I53: -0.020169923 | J53: 0.15855492 | K53: 0.16628865 | L53: 0.0044381893 | M53: -0.01047607 | N53: 0.21705309 | O53: -0.052047505 | P53: 0.071879494 | Q53: -0.0287671 | R53: 0.018728656 | S53: -0.020237239 | T53: -0.015365649 | U53: -0.036490755 | V53: 0.1337299 | W53: 0.028933443 | X53: 0.036193757 | Y53: 0.1288744
A54: -0.00027449028 | B54: =SUMPRODUCT(C54:Y54,MMULT(C54:Y54,$B$4:$X$26)) | C54: 0.048986919 | D54: 0.010224186 | E54: 0.12567352 | F54: 0.041859832 | G54: -0.073849298 | H54: 0.067177765 | I54: -0.01894191 | J54: 0.15932714 | K54: 0.1691588 | L54: 0.0042415785 | M54: -0.0091584957 | N54: 0.22089258 | O54: -0.051827988 | P54: 0.070866367 | Q54: -0.030114238 | R54: 0.015013152 | S54: -0.020875444 | T54: -0.016765131 | U54: -0.034410295 | V54: 0.13258941 | W54: 0.02707322 | X54: 0.033655521 | Y54: 0.12920281
A55: -0.00023652189 | B55: =SUMPRODUCT(C55:Y55,MMULT(C55:Y55,$B$4:$X$26)) | C55: 0.047632789 | D55: 0.0089371001 | E55: 0.12928358 | F55: 0.040528974 | G55: -0.072717004 | H55: 0.067600662 | I55: -0.017713897 | J55: 0.16009937 | K55: 0.17202895 | L55: 0.0040449677 | M55: -0.0078409211 | N55: 0.22473206 | O55: -0.051608472 | P55: 0.069853241 | Q55: -0.031461377 | R55: 0.011297648 | S55: -0.02151365 | T55: -0.018164614 | U55: -0.032329835 | V55: 0.13144893 | W55: 0.025212996 | X55: 0.031117285 | Y55: 0.12953121
A56: -0.00019855351 | B56: =SUMPRODUCT(C56:Y56,MMULT(C56:Y56,$B$4:$X$26)) | C56: 0.046278659 | D56: 0.0076500141 | E56: 0.13289365 | F56: 0.039198115 | G56: -0.07158471 | H56: 0.068023558 | I56: -0.016485885 | J56: 0.16087159 | K56: 0.1748991 | L56: 0.0038483569 | M56: -0.0065233464 | N56: 0.22857155 | O56: -0.051388955 | P56: 0.068840115 | Q56: -0.032808515 | R56: 0.0075821439 | S56: -0.022151855 | T56: -0.019564097 | U56: -0.030249375 | V56: 0.13030844 | W56: 0.023352773 | X56: 0.028579049 | Y56: 0.12985962
... A104: 0.001623929 | B104: =SUMPRODUCT(C104:Y104,MMULT(C104:Y104,$B$4:$X$26)) | C104: -0.018719596 | D104: -0.054130115 | E104: 0.30617677 | F104: -0.024683083 | G104: -0.017234609 | H104: 0.088322575 | I104: 0.04245873 | J104: 0.19793846 | K104: 0.31266628 | L104: -0.0055889607 | M104: 0.056720237 | N104: 0.41286679 | O104: -0.040852153 | P104: 0.020210053 | Q104: -0.097471144 | R104: -0.17076205 | S104: -0.052785709 | T104: -0.086739275 | U104: 0.069612713 | V104: 0.075565209 | W104: -0.06593795 | X104: -0.093256274 | Y104: 0.1456231
A107: Q3: Sharpe-optimal (tangency) portfolio and the Capital Market Line
A108: Sharpe_Optimal_Solution (raw, satisfies (mu-rf)'x=1) -- solved values | B108: -38.199344 | C108: -33.723135 | D108: 83.607842 | E108: -37.095743 | F108: 34.280959 | G108: 6.0625813 | H108: 32.828881 | I108: 8.4628156 | J108: 61.545917 | K108: -5.3420589 | L108: 34.428934 | M108: 82.715669 | N108: 9.3144224 | O108: -31.013778 | P108: -32.393087 | Q108: -96.318883 | R108: -14.876059 | S108: -34.684614 | T108: 55.782648 | U108: -38.669512 | V108: -49.614708 | W108: -67.464524 | X108: -0.77204134
A109: Portfolio_Allocation (rescaled to sum to 1) -- solved values | B109: 0.53698415 | C109: 0.47406021 | D109: -1.1753104 | E109: 0.52147038 | F109: -0.48190178 | G109: -0.085224241 | H109: -0.46148931 | I109: -0.11896534 | J109: -0.86517669 | K109: 0.075095556 | L109: -0.48398192 | M109: -1.1627687 | N109: -0.13093673 | O109: 0.43597364 | P109: 0.45536317 | Q109: 1.3539948 | R109: 0.20911898 | S109: 0.48757612 | T109: -0.78416 | U109: 0.54359349 | V109: 0.6974547 | W109: 0.94837702 | X109: 0.010852908
A111: Sum of raw (pre-budget) weights, 1'x_raw | B111: =SUM(B108:X108)
A112: Portfolio_Expected_Return | B112: =SUMPRODUCT(B109:X109,B29:X29)
A113: Total_Wealth (should be 1) | B113: =SUM(B109:X109)
A114: Portfolio_Variance | B114: =SUMPRODUCT(B109:X109,MMULT(B109:X109,B4:X26))
A115: Sharpe_Ratio [Q3/Q9-style answer] | B115: =(B112-B31)/SQRT(B114)
A117: Q4: Compare risk-free rate and Sharpe-optimal portfolio return
A118: Risk_Free_Rate | B118: =B31
A119: Sharpe_Optimal_Return | B119: =B112
A120: Sharpe_Optimal_Volatility (vs. 0 for risk-free) | B120: =SQRT(B114)
A121: Return lower than rf? | B121: =IF(B119<B118,"Yes -- lower return, and risk is always higher than 0","No")
A123: Q5 (see notebook for full discussion): lower return + higher risk than cash is NOT arbitrage -- arbitrage requires ZERO risk. This portfolio has variance B114 > 0.
A124: Q6 (see notebook for full discussion): sample covariance is a fairly reliable input; sample mean is extremely noisy at daily frequency (see t-stat table in the notebook) -- the main source of estimation error in this optimization.

Sheet FF3_Factors_2018
A1: date | B1: Mkt-RF | C1: SMB | D1: HML | E1: RMW | F1: CMA | G1: RF
A2: 2018-01-02 | B2: 0.0085 | C2: 0.003 | D2: -0.0023 | E2: -0.0049 | F2: 0.0021 | G2: 5e-05
A3: 2018-01-03 | B3: 0.0059 | C3: -0.0048 | D3: -0.002 | E3: -0.0074 | F3: -0.0007 | G3: 5e-05
A4: 2018-01-04 | B4: 0.0042 | C4: -0.0023 | D4: 0.0025 | E4: -0.0002 | F4: 0.003 | G4: 5e-05
A5: 2018-01-05 | B5: 0.0066 | C5: -0.0036 | D5: -0.0026 | E5: 0.0039 | F5: -0.0037 | G5: 5e-05
A6: 2018-01-08 | B6: 0.0019 | C6: -0.0021 | D6: 0.0005 | E6: -0.0009 | F6: 0.0003 | G6: 5e-05
A7: 2018-01-09 | B7: 0.0015 | C7: -0.0036 | D7: -0.0005 | E7: -0.0011 | F7: -0.0006 | G7: 5e-05
A8: 2018-01-10 | B8: -0.0007 | C8: 0.0014 | D8: 0.0059 | E8: -0.0035 | F8: 0.0001 | G8: 5e-05
A9: 2018-01-11 | B9: 0.0087 | C9: 0.0111 | D9: 0.0031 | E9: -0.0022 | F9: 0.0047 | G9: 5e-05
A10: 2018-01-12 | B10: 0.0066 | C10: -0.0031 | D10: 0.0016 | E10: -0.001 | F10: 0.0015 | G10: 5e-05
A11: 2018-01-16 | B11: -0.0049 | C11: -0.01 | D11: -0.0001 | E11: 0.0043 | F11: -0.0033 | G11: 5e-05
A12: 2018-01-17 | B12: 0.0095 | C12: -0.0007 | D12: -0.0012 | E12: -0.001 | F12: -0.0003 | G12: 5e-05
A13: 2018-01-18 | B13: -0.0018 | C13: -0.0044 | D13: -0.0025 | E13: 0.003 | F13: -0.0029 | G13: 5e-05
... A251: 2018-12-28 | B251: -0.0003 | C251: 0.0074 | D251: 0.0023 | E251: -0.0035 | F251: -0.0007 | G251: 0.0001

Sheet FF3_Model_2018
A1: Bonus: Fama-French 3-factor model — fine-tuning expected returns (2018 data)
A3: Factor premia (average realized factor return, 2018)
A4: Mkt-RF premium | B4: =AVERAGE(FF3_Factors_2018!B2:B251)
A5: SMB premium | B5: =AVERAGE(FF3_Factors_2018!C2:C251)
A6: HML premium | B6: =AVERAGE(FF3_Factors_2018!D2:D251)
A7: Average risk-free rate (RF) | B7: =AVERAGE(FF3_Factors_2018!G2:G251)
A9: Ticker | B9: alpha | C9: beta_mkt | D9: beta_smb | E9: beta_hml | F9: R2 | G9: ff3_implied_mean | H9: raw_historical_mean
A10: IBM | B10: {=INDEX(LINEST(Returns_2018!B2:B251-FF3_Factors_2018!$G$2:$G$251,FF3_Factors_2018!$B$2:$D$251,TRUE,TRUE),1,4)} | C10: {=INDEX(LINEST(Returns_2018!B2:B251-FF3_Factors_2018!$G$2:$G$251,FF3_Factors_2018!$B$2:$D$251,TRUE,TRUE),1,3)} | D10: {=INDEX(LINEST(Returns_2018!B2:B251-FF3_Factors_2018!$G$2:$G$251,FF3_Factors_2018!$B$2:$D$251,TRUE,TRUE),1,2)} | E10: {=INDEX(LINEST(Returns_2018!B2:B251-FF3_Factors_2018!$G$2:$G$251,FF3_Factors_2018!$B$2:$D$251,TRUE,TRUE),1,1)} | F10: {=INDEX(LINEST(Returns_2018!B2:B251-FF3_Factors_2018!$G$2:$G$251,FF3_Factors_2018!$B$2:$D$251,TRUE,TRUE),3,1)} | G10: =$B$7+C10*$B$4+D10*$B$5+E10*$B$6 | H10: =AVERAGE(Returns_2018!B2:B251)
A11: GE | B11: {=INDEX(LINEST(Returns_2018!C2:C251-FF3_Factors_2018!$G$2:$G$251,FF3_Factors_2018!$B$2:$D$251,TRUE,TRUE),1,4)} | C11: {=INDEX(LINEST(Returns_2018!C2:C251-FF3_Factors_2018!$G$2:$G$251,FF3_Factors_2018!$B$2:$D$251,TRUE,TRUE),1,3)} | D11: {=INDEX(LINEST(Returns_2018!C2:C251-FF3_Factors_2018!$G$2:$G$251,FF3_Factors_2018!$B$2:$D$251,TRUE,TRUE),1,2)} | E11: {=INDEX(LINEST(Returns_2018!C2:C251-FF3_Factors_2018!$G$2:$G$251,FF3_Factors_2018!$B$2:$D$251,TRUE,TRUE),1,1)} | F11: {=INDEX(LINEST(Returns_2018!C2:C251-FF3_Factors_2018!$G$2:$G$251,FF3_Factors_2018!$B$2:$D$251,TRUE,TRUE),3,1)} | G11: =$B$7+C11*$B$4+D11*$B$5+E11*$B$6 | H11: =AVERAGE(Returns_2018!C2:C251)
A12: LLY | B12: {=INDEX(LINEST(Returns_2018!D2:D251-FF3_Factors_2018!$G$2:$G$251,FF3_Factors_2018!$B$2:$D$251,TRUE,TRUE),1,4)} | C12: {=INDEX(LINEST(Returns_2018!D2:D251-FF3_Factors_2018!$G$2:$G$251,FF3_Factors_2018!$B$2:$D$251,TRUE,TRUE),1,3)} | D12: {=INDEX(LINEST(Returns_2018!D2:D251-FF3_Factors_2018!$G$2:$G$251,FF3_Factors_2018!$B$2:$D$251,TRUE,TRUE),1,2)} | E12: {=INDEX(LINEST(Returns_2018!D2:D251-FF3_Factors_2018!$G$2:$G$251,FF3_Factors_2018!$B$2:$D$251,TRUE,TRUE),1,1)} | F12: {=INDEX(LINEST(Returns_2018!D2:D251-FF3_Factors_2018!$G$2:$G$251,FF3_Factors_2018!$B$2:$D$251,TRUE,TRUE),3,1)} | G12: =$B$7+C12*$B$4+D12*$B$5+E12*$B$6 | H12: =AVERAGE(Returns_2018!D2:D251)
A13: F | B13: {=INDEX(LINEST(Returns_2018!E2:E251-FF3_Factors_2018!$G$2:$G$251,FF3_Factors_2018!$B$2:$D$251,TRUE,TRUE),1,4)} | C13: {=INDEX(LINEST(Returns_2018!E2:E251-FF3_Factors_2018!$G$2:$G$251,FF3_Factors_2018!$B$2:$D$251,TRUE,TRUE),1,3)} | D13: {=INDEX(LINEST(Returns_2018!E2:E251-FF3_Factors_2018!$G$2:$G$251,FF3_Factors_2018!$B$2:$D$251,TRUE,TRUE),1,2)} | E13: {=INDEX(LINEST(Returns_2018!E2:E251-FF3_Factors_2018!$G$2:$G$251,FF3_Factors_2018!$B$2:$D$251,TRUE,TRUE),1,1)} | F13: {=INDEX(LINEST(Returns_2018!E2:E251-FF3_Factors_2018!$G$2:$G$251,FF3_Factors_2018!$B$2:$D$251,TRUE,TRUE),3,1)} | G13: =$B$7+C13*$B$4+D13*$B$5+E13*$B$6 | H13: =AVERAGE(Returns_2018!E2:E251)
A14: BAC | B14: {=INDEX(LINEST(Returns_2018!F2:F251-FF3_Factors_2018!$G$2:$G$251,FF3_Factors_2018!$B$2:$D$251,TRUE,TRUE),1,4)} | C14: {=INDEX(LINEST(Returns_2018!F2:F251-FF3_Factors_2018!$G$2:$G$251,FF3_Factors_2018!$B$2:$D$251,TRUE,TRUE),1,3)} | D14: {=INDEX(LINEST(Returns_2018!F2:F251-FF3_Factors_2018!$G$2:$G$251,FF3_Factors_2018!$B$2:$D$251,TRUE,TRUE),1,2)} | E14: {=INDEX(LINEST(Returns_2018!F2:F251-FF3_Factors_2018!$G$2:$G$251,FF3_Factors_2018!$B$2:$D$251,TRUE,TRUE),1,1)} | F14: {=INDEX(LINEST(Returns_2018!F2:F251-FF3_Factors_2018!$G$2:$G$251,FF3_Factors_2018!$B$2:$D$251,TRUE,TRUE),3,1)} | G14: =$B$7+C14*$B$4+D14*$B$5+E14*$B$6 | H14: =AVERAGE(Returns_2018!F2:F251)
A15: KR | B15: {=INDEX(LINEST(Returns_2018!G2:G251-FF3_Factors_2018!$G$2:$G$251,FF3_Factors_2018!$B$2:$D$251,TRUE,TRUE),1,4)} | C15: {=INDEX(LINEST(Returns_2018!G2:G251-FF3_Factors_2018!$G$2:$G$251,FF3_Factors_2018!$B$2:$D$251,TRUE,TRUE),1,3)} | D15: {=INDEX(LINEST(Returns_2018!G2:G251-FF3_Factors_2018!$G$2:$G$251,FF3_Factors_2018!$B$2:$D$251,TRUE,TRUE),1,2)} | E15: {=INDEX(LINEST(Returns_2018!G2:G251-FF3_Factors_2018!$G$2:$G$251,FF3_Factors_2018!$B$2:$D$251,TRUE,TRUE),1,1)} | F15: {=INDEX(LINEST(Returns_2018!G2:G251-FF3_Factors_2018!$G$2:$G$251,FF3_Factors_2018!$B$2:$D$251,TRUE,TRUE),3,1)} | G15: =$B$7+C15*$B$4+D15*$B$5+E15*$B$6 | H15: =AVERAGE(Returns_2018!G2:G251)
A16: ITUB | B16: {=INDEX(LINEST(Returns_2018!H2:H251-FF3_Factors_2018!$G$2:$G$251,FF3_Factors_2018!$B$2:$D$251,TRUE,TRUE),1,4)} | C16: {=INDEX(LINEST(Returns_2018!H2:H251-FF3_Factors_2018!$G$2:$G$251,FF3_Factors_2018!$B$2:$D$251,TRUE,TRUE),1,3)} | D16: {=INDEX(LINEST(Returns_2018!H2:H251-FF3_Factors_2018!$G$2:$G$251,FF3_Factors_2018!$B$2:$D$251,TRUE,TRUE),1,2)} | E16: {=INDEX(LINEST(Returns_2018!H2:H251-FF3_Factors_2018!$G$2:$G$251,FF3_Factors_2018!$B$2:$D$251,TRUE,TRUE),1,1)} | F16: {=INDEX(LINEST(Returns_2018!H2:H251-FF3_Factors_2018!$G$2:$G$251,FF3_Factors_2018!$B$2:$D$251,TRUE,TRUE),3,1)} | G16: =$B$7+C16*$B$4+D16*$B$5+E16*$B$6 | H16: =AVERAGE(Returns_2018!H2:H251)
A17: GG | B17: {=INDEX(LINEST(Returns_2018!I2:I251-FF3_Factors_2018!$G$2:$G$251,FF3_Factors_2018!$B$2:$D$251,TRUE,TRUE),1,4)} | C17: {=INDEX(LINEST(Returns_2018!I2:I251-FF3_Factors_2018!$G$2:$G$251,FF3_Factors_2018!$B$2:$D$251,TRUE,TRUE),1,3)} | D17: {=INDEX(LINEST(Returns_2018!I2:I251-FF3_Factors_2018!$G$2:$G$251,FF3_Factors_2018!$B$2:$D$251,TRUE,TRUE),1,2)} | E17: {=INDEX(LINEST(Returns_2018!I2:I251-FF3_Factors_2018!$G$2:$G$251,FF3_Factors_2018!$B$2:$D$251,TRUE,TRUE),1,1)} | F17: {=INDEX(LINEST(Returns_2018!I2:I251-FF3_Factors_2018!$G$2:$G$251,FF3_Factors_2018!$B$2:$D$251,TRUE,TRUE),3,1)} | G17: =$B$7+C17*$B$4+D17*$B$5+E17*$B$6 | H17: =AVERAGE(Returns_2018!I2:I251)
A18: SIRI | B18: {=INDEX(LINEST(Returns_2018!J2:J251-FF3_Factors_2018!$G$2:$G$251,FF3_Factors_2018!$B$2:$D$251,TRUE,TRUE),1,4)} | C18: {=INDEX(LINEST(Returns_2018!J2:J251-FF3_Factors_2018!$G$2:$G$251,FF3_Factors_2018!$B$2:$D$251,TRUE,TRUE),1,3)} | D18: {=INDEX(LINEST(Returns_2018!J2:J251-FF3_Factors_2018!$G$2:$G$251,FF3_Factors_2018!$B$2:$D$251,TRUE,TRUE),1,2)} | E18: {=INDEX(LINEST(Returns_2018!J2:J251-FF3_Factors_2018!$G$2:$G$251,FF3_Factors_2018!$B$2:$D$251,TRUE,TRUE),1,1)} | F18: {=INDEX(LINEST(Returns_2018!J2:J251-FF3_Factors_2018!$G$2:$G$251,FF3_Factors_2018!$B$2:$D$251,TRUE,TRUE),3,1)} | G18: =$B$7+C18*$B$4+D18*$B$5+E18*$B$6 | H18: =AVERAGE(Returns_2018!J2:J251)
A19: ACB | B19: {=INDEX(LINEST(Returns_2018!K2:K251-FF3_Factors_2018!$G$2:$G$251,FF3_Factors_2018!$B$2:$D$251,TRUE,TRUE),1,4)} | C19: {=INDEX(LINEST(Returns_2018!K2:K251-FF3_Factors_2018!$G$2:$G$251,FF3_Factors_2018!$B$2:$D$251,TRUE,TRUE),1,3)} | D19: {=INDEX(LINEST(Returns_2018!K2:K251-FF3_Factors_2018!$G$2:$G$251,FF3_Factors_2018!$B$2:$D$251,TRUE,TRUE),1,2)} | E19: {=INDEX(LINEST(Returns_2018!K2:K251-FF3_Factors_2018!$G$2:$G$251,FF3_Factors_2018!$B$2:$D$251,TRUE,TRUE),1,1)} | F19: {=INDEX(LINEST(Returns_2018!K2:K251-FF3_Factors_2018!$G$2:$G$251,FF3_Factors_2018!$B$2:$D$251,TRUE,TRUE),3,1)} | G19: =$B$7+C19*$B$4+D19*$B$5+E19*$B$6 | H19: =AVERAGE(Returns_2018!K2:K251)
A20: VALE | B20: {=INDEX(LINEST(Returns_2018!L2:L251-FF3_Factors_2018!$G$2:$G$251,FF3_Factors_2018!$B$2:$D$251,TRUE,TRUE),1,4)} | C20: {=INDEX(LINEST(Returns_2018!L2:L251-FF3_Factors_2018!$G$2:$G$251,FF3_Factors_2018!$B$2:$D$251,TRUE,TRUE),1,3)} | D20: {=INDEX(LINEST(Returns_2018!L2:L251-FF3_Factors_2018!$G$2:$G$251,FF3_Factors_2018!$B$2:$D$251,TRUE,TRUE),1,2)} | E20: {=INDEX(LINEST(Returns_2018!L2:L251-FF3_Factors_2018!$G$2:$G$251,FF3_Factors_2018!$B$2:$D$251,TRUE,TRUE),1,1)} | F20: {=INDEX(LINEST(Returns_2018!L2:L251-FF3_Factors_2018!$G$2:$G$251,FF3_Factors_2018!$B$2:$D$251,TRUE,TRUE),3,1)} | G20: =$B$7+C20*$B$4+D20*$B$5+E20*$B$6 | H20: =AVERAGE(Returns_2018!L2:L251)
A21: PFE | B21: {=INDEX(LINEST(Returns_2018!M2:M251-FF3_Factors_2018!$G$2:$G$251,FF3_Factors_2018!$B$2:$D$251,TRUE,TRUE),1,4)} | C21: {=INDEX(LINEST(Returns_2018!M2:M251-FF3_Factors_2018!$G$2:$G$251,FF3_Factors_2018!$B$2:$D$251,TRUE,TRUE),1,3)} | D21: {=INDEX(LINEST(Returns_2018!M2:M251-FF3_Factors_2018!$G$2:$G$251,FF3_Factors_2018!$B$2:$D$251,TRUE,TRUE),1,2)} | E21: {=INDEX(LINEST(Returns_2018!M2:M251-FF3_Factors_2018!$G$2:$G$251,FF3_Factors_2018!$B$2:$D$251,TRUE,TRUE),1,1)} | F21: {=INDEX(LINEST(Returns_2018!M2:M251-FF3_Factors_2018!$G$2:$G$251,FF3_Factors_2018!$B$2:$D$251,TRUE,TRUE),3,1)} | G21: =$B$7+C21*$B$4+D21*$B$5+E21*$B$6 | H21: =AVERAGE(Returns_2018!M2:M251)
A22: CTL | B22: {=INDEX(LINEST(Returns_2018!N2:N251-FF3_Factors_2018!$G$2:$G$251,FF3_Factors_2018!$B$2:$D$251,TRUE,TRUE),1,4)} | C22: {=INDEX(LINEST(Returns_2018!N2:N251-FF3_Factors_2018!$G$2:$G$251,FF3_Factors_2018!$B$2:$D$251,TRUE,TRUE),1,3)} | D22: {=INDEX(LINEST(Returns_2018!N2:N251-FF3_Factors_2018!$G$2:$G$251,FF3_Factors_2018!$B$2:$D$251,TRUE,TRUE),1,2)} | E22: {=INDEX(LINEST(Returns_2018!N2:N251-FF3_Factors_2018!$G$2:$G$251,FF3_Factors_2018!$B$2:$D$251,TRUE,TRUE),1,1)} | F22: {=INDEX(LINEST(Returns_2018!N2:N251-FF3_Factors_2018!$G$2:$G$251,FF3_Factors_2018!$B$2:$D$251,TRUE,TRUE),3,1)} | G22: =$B$7+C22*$B$4+D22*$B$5+E22*$B$6 | H22: =AVERAGE(Returns_2018!N2:N251)
A23: T | B23: {=INDEX(LINEST(Returns_2018!O2:O251-FF3_Factors_2018!$G$2:$G$251,FF3_Factors_2018!$B$2:$D$251,TRUE,TRUE),1,4)} | C23: {=INDEX(LINEST(Returns_2018!O2:O251-FF3_Factors_2018!$G$2:$G$251,FF3_Factors_2018!$B$2:$D$251,TRUE,TRUE),1,3)} | D23: {=INDEX(LINEST(Returns_2018!O2:O251-FF3_Factors_2018!$G$2:$G$251,FF3_Factors_2018!$B$2:$D$251,TRUE,TRUE),1,2)} | E23: {=INDEX(LINEST(Returns_2018!O2:O251-FF3_Factors_2018!$G$2:$G$251,FF3_Factors_2018!$B$2:$D$251,TRUE,TRUE),1,1)} | F23: {=INDEX(LINEST(Returns_2018!O2:O251-FF3_Factors_2018!$G$2:$G$251,FF3_Factors_2018!$B$2:$D$251,TRUE,TRUE),3,1)} | G23: =$B$7+C23*$B$4+D23*$B$5+E23*$B$6 | H23: =AVERAGE(Returns_2018!O2:O251)
A24: ECA | B24: {=INDEX(LINEST(Returns_2018!P2:P251-FF3_Factors_2018!$G$2:$G$251,FF3_Factors_2018!$B$2:$D$251,TRUE,TRUE),1,4)} | C24: {=INDEX(LINEST(Returns_2018!P2:P251-FF3_Factors_2018!$G$2:$G$251,FF3_Factors_2018!$B$2:$D$251,TRUE,TRUE),1,3)} | D24: {=INDEX(LINEST(Returns_2018!P2:P251-FF3_Factors_2018!$G$2:$G$251,FF3_Factors_2018!$B$2:$D$251,TRUE,TRUE),1,2)} | E24: {=INDEX(LINEST(Returns_2018!P2:P251-FF3_Factors_2018!$G$2:$G$251,FF3_Factors_2018!$B$2:$D$251,TRUE,TRUE),1,1)} | F24: {=INDEX(LINEST(Returns_2018!P2:P251-FF3_Factors_2018!$G$2:$G$251,FF3_Factors_2018!$B$2:$D$251,TRUE,TRUE),3,1)} | G24: =$B$7+C24*$B$4+D24*$B$5+E24*$B$6 | H24: =AVERAGE(Returns_2018!P2:P251)
A25: ABEV | B25: {=INDEX(LINEST(Returns_2018!Q2:Q251-FF3_Factors_2018!$G$2:$G$251,FF3_Factors_2018!$B$2:$D$251,TRUE,TRUE),1,4)} | C25: {=INDEX(LINEST(Returns_2018!Q2:Q251-FF3_Factors_2018!$G$2:$G$251,FF3_Factors_2018!$B$2:$D$251,TRUE,TRUE),1,3)} | D25: {=INDEX(LINEST(Returns_2018!Q2:Q251-FF3_Factors_2018!$G$2:$G$251,FF3_Factors_2018!$B$2:$D$251,TRUE,TRUE),1,2)} | E25: {=INDEX(LINEST(Returns_2018!Q2:Q251-FF3_Factors_2018!$G$2:$G$251,FF3_Factors_2018!$B$2:$D$251,TRUE,TRUE),1,1)} | F25: {=INDEX(LINEST(Returns_2018!Q2:Q251-FF3_Factors_2018!$G$2:$G$251,FF3_Factors_2018!$B$2:$D$251,TRUE,TRUE),3,1)} | G25: =$B$7+C25*$B$4+D25*$B$5+E25*$B$6 | H25: =AVERAGE(Returns_2018!Q2:Q251)
A26: CVS | B26: {=INDEX(LINEST(Returns_2018!R2:R251-FF3_Factors_2018!$G$2:$G$251,FF3_Factors_2018!$B$2:$D$251,TRUE,TRUE),1,4)} | C26: {=INDEX(LINEST(Returns_2018!R2:R251-FF3_Factors_2018!$G$2:$G$251,FF3_Factors_2018!$B$2:$D$251,TRUE,TRUE),1,3)} | D26: {=INDEX(LINEST(Returns_2018!R2:R251-FF3_Factors_2018!$G$2:$G$251,FF3_Factors_2018!$B$2:$D$251,TRUE,TRUE),1,2)} | E26: {=INDEX(LINEST(Returns_2018!R2:R251-FF3_Factors_2018!$G$2:$G$251,FF3_Factors_2018!$B$2:$D$251,TRUE,TRUE),1,1)} | F26: {=INDEX(LINEST(Returns_2018!R2:R251-FF3_Factors_2018!$G$2:$G$251,FF3_Factors_2018!$B$2:$D$251,TRUE,TRUE),3,1)} | G26: =$B$7+C26*$B$4+D26*$B$5+E26*$B$6 | H26: =AVERAGE(Returns_2018!R2:R251)
A27: MRVL | B27: {=INDEX(LINEST(Returns_2018!S2:S251-FF3_Factors_2018!$G$2:$G$251,FF3_Factors_2018!$B$2:$D$251,TRUE,TRUE),1,4)} | C27: {=INDEX(LINEST(Returns_2018!S2:S251-FF3_Factors_2018!$G$2:$G$251,FF3_Factors_2018!$B$2:$D$251,TRUE,TRUE),1,3)} | D27: {=INDEX(LINEST(Returns_2018!S2:S251-FF3_Factors_2018!$G$2:$G$251,FF3_Factors_2018!$B$2:$D$251,TRUE,TRUE),1,2)} | E27: {=INDEX(LINEST(Returns_2018!S2:S251-FF3_Factors_2018!$G$2:$G$251,FF3_Factors_2018!$B$2:$D$251,TRUE,TRUE),1,1)} | F27: {=INDEX(LINEST(Returns_2018!S2:S251-FF3_Factors_2018!$G$2:$G$251,FF3_Factors_2018!$B$2:$D$251,TRUE,TRUE),3,1)} | G27: =$B$7+C27*$B$4+D27*$B$5+E27*$B$6 | H27: =AVERAGE(Returns_2018!S2:S251)
A28: CSCO | B28: {=INDEX(LINEST(Returns_2018!T2:T251-FF3_Factors_2018!$G$2:$G$251,FF3_Factors_2018!$B$2:$D$251,TRUE,TRUE),1,4)} | C28: {=INDEX(LINEST(Returns_2018!T2:T251-FF3_Factors_2018!$G$2:$G$251,FF3_Factors_2018!$B$2:$D$251,TRUE,TRUE),1,3)} | D28: {=INDEX(LINEST(Returns_2018!T2:T251-FF3_Factors_2018!$G$2:$G$251,FF3_Factors_2018!$B$2:$D$251,TRUE,TRUE),1,2)} | E28: {=INDEX(LINEST(Returns_2018!T2:T251-FF3_Factors_2018!$G$2:$G$251,FF3_Factors_2018!$B$2:$D$251,TRUE,TRUE),1,1)} | F28: {=INDEX(LINEST(Returns_2018!T2:T251-FF3_Factors_2018!$G$2:$G$251,FF3_Factors_2018!$B$2:$D$251,TRUE,TRUE),3,1)} | G28: =$B$7+C28*$B$4+D28*$B$5+E28*$B$6 | H28: =AVERAGE(Returns_2018!T2:T251)
A29: MO | B29: {=INDEX(LINEST(Returns_2018!U2:U251-FF3_Factors_2018!$G$2:$G$251,FF3_Factors_2018!$B$2:$D$251,TRUE,TRUE),1,4)} | C29: {=INDEX(LINEST(Returns_2018!U2:U251-FF3_Factors_2018!$G$2:$G$251,FF3_Factors_2018!$B$2:$D$251,TRUE,TRUE),1,3)} | D29: {=INDEX(LINEST(Returns_2018!U2:U251-FF3_Factors_2018!$G$2:$G$251,FF3_Factors_2018!$B$2:$D$251,TRUE,TRUE),1,2)} | E29: {=INDEX(LINEST(Returns_2018!U2:U251-FF3_Factors_2018!$G$2:$G$251,FF3_Factors_2018!$B$2:$D$251,TRUE,TRUE),1,1)} | F29: {=INDEX(LINEST(Returns_2018!U2:U251-FF3_Factors_2018!$G$2:$G$251,FF3_Factors_2018!$B$2:$D$251,TRUE,TRUE),3,1)} | G29: =$B$7+C29*$B$4+D29*$B$5+E29*$B$6 | H29: =AVERAGE(Returns_2018!U2:U251)
A30: BMY | B30: {=INDEX(LINEST(Returns_2018!V2:V251-FF3_Factors_2018!$G$2:$G$251,FF3_Factors_2018!$B$2:$D$251,TRUE,TRUE),1,4)} | C30: {=INDEX(LINEST(Returns_2018!V2:V251-FF3_Factors_2018!$G$2:$G$251,FF3_Factors_2018!$B$2:$D$251,TRUE,TRUE),1,3)} | D30: {=INDEX(LINEST(Returns_2018!V2:V251-FF3_Factors_2018!$G$2:$G$251,FF3_Factors_2018!$B$2:$D$251,TRUE,TRUE),1,2)} | E30: {=INDEX(LINEST(Returns_2018!V2:V251-FF3_Factors_2018!$G$2:$G$251,FF3_Factors_2018!$B$2:$D$251,TRUE,TRUE),1,1)} | F30: {=INDEX(LINEST(Returns_2018!V2:V251-FF3_Factors_2018!$G$2:$G$251,FF3_Factors_2018!$B$2:$D$251,TRUE,TRUE),3,1)} | G30: =$B$7+C30*$B$4+D30*$B$5+E30*$B$6 | H30: =AVERAGE(Returns_2018!V2:V251)
A31: WFC | B31: {=INDEX(LINEST(Returns_2018!W2:W251-FF3_Factors_2018!$G$2:$G$251,FF3_Factors_2018!$B$2:$D$251,TRUE,TRUE),1,4)} | C31: {=INDEX(LINEST(Returns_2018!W2:W251-FF3_Factors_2018!$G$2:$G$251,FF3_Factors_2018!$B$2:$D$251,TRUE,TRUE),1,3)} | D31: {=INDEX(LINEST(Returns_2018!W2:W251-FF3_Factors_2018!$G$2:$G$251,FF3_Factors_2018!$B$2:$D$251,TRUE,TRUE),1,2)} | E31: {=INDEX(LINEST(Returns_2018!W2:W251-FF3_Factors_2018!$G$2:$G$251,FF3_Factors_2018!$B$2:$D$251,TRUE,TRUE),1,1)} | F31: {=INDEX(LINEST(Returns_2018!W2:W251-FF3_Factors_2018!$G$2:$G$251,FF3_Factors_2018!$B$2:$D$251,TRUE,TRUE),3,1)} | G31: =$B$7+C31*$B$4+D31*$B$5+E31*$B$6 | H31: =AVERAGE(Returns_2018!W2:W251)
A32: HBAN | B32: {=INDEX(LINEST(Returns_2018!X2:X251-FF3_Factors_2018!$G$2:$G$251,FF3_Factors_2018!$B$2:$D$251,TRUE,TRUE),1,4)} | C32: {=INDEX(LINEST(Returns_2018!X2:X251-FF3_Factors_2018!$G$2:$G$251,FF3_Factors_2018!$B$2:$D$251,TRUE,TRUE),1,3)} | D32: {=INDEX(LINEST(Returns_2018!X2:X251-FF3_Factors_2018!$G$2:$G$251,FF3_Factors_2018!$B$2:$D$251,TRUE,TRUE),1,2)} | E32: {=INDEX(LINEST(Returns_2018!X2:X251-FF3_Factors_2018!$G$2:$G$251,FF3_Factors_2018!$B$2:$D$251,TRUE,TRUE),1,1)} | F32: {=INDEX(LINEST(Returns_2018!X2:X251-FF3_Factors_2018!$G$2:$G$251,FF3_Factors_2018!$B$2:$D$251,TRUE,TRUE),3,1)} | G32: =$B$7+C32*$B$4+D32*$B$5+E32*$B$6 | H32: =AVERAGE(Returns_2018!X2:X251)
A34: Cross-sectional std dev, raw means | B34: =_xlfn.STDEV.S(H10:H32)
A35: Cross-sectional std dev, FF3-implied means | B35: =_xlfn.STDEV.S(G10:G32)
A36: Average R2 across stocks | B36: =AVERAGE(F10:F32)
A38: Recomputed tangency portfolio using FF3-implied means (same covariance, same rf)
A39: FF3_implied_tangency_weights | B39: -0.16107302 | C39: -0.0045521875 | D39: 0.17013369 | E39: 0.20516542 | F39: 0.14408965 | G39: -0.40400752 | H39: -0.17745599 | I39: 0.5141168 | J39: -0.26008826 | K39: -0.050801364 | L39: -0.50427486 | M39: 0.92682471 | N39: 0.16643076 | O39: -0.082065415 | P39: 0.048428807 | Q39: 0.3338974 | R39: -0.23207919 | S39: -0.087054902 | T39: -0.17590412 | U39: 0.33891242 | V39: 0.026581619 | W39: -0.50446427 | X39: 0.76923982
A41: Max |weight|, FF3-implied tangency | B41: {=MAX(ABS(B39:X39))}
A42: Max |weight|, raw-mean tangency (Analysis_2018!B109:X109) | B42: {=MAX(ABS(Analysis_2018!B109:X109))}
A43: Weight-extremity reduction factor | B43: =B42/B41
